Workbook

Sheet plan1
B1: Tavares Concrete Company Inc.
B2: Monthly Performance Report - Budgeted vs Actual Claims Paid
G3: Plan Year: | H3: 46054 | I3: thru | J3: 46418
B5: Group ID: | D5: S448 | K5: Plan Name: | M5: Standard
B6: Coverage: | D6: Dental | K6: Plan ID: | M6: S448DEN
B8: ENROLLMENT | H8: ADMIN | I8: CLAIMS | M8: PROFIT OR LOSS
M9: Surplus/ | N9: Loss
B10: Mon, Yr | C10: EE | D10: EE+1 | F10: EF | G10: Total | H10: Costs | I10: Budgeted | J10: Submitted | K10: Paid | L10: Number | M10: Deficit | N10: Ratio
B12: 46054 | C12: 4 | D12: =4+2 -> 6 | F12: 13 | G12: =SUM(C12:F12) -> 23 | H12: 152 | I12: =(C12*$C$29)+(D12*$C$30)+(E12*$C$31)+(F12*$C$32) -> 1900.9 | J12: 0 | K12: 0 | L12: 0 | M12: =I12-K12 -> 1900.9 | N12: =K12/I12 -> 0
B13: 46082 | C13: 4 | D13: =4+2 -> 6 | F13: 13 | G13: =SUM(C13:F13) -> 23 | H13: 152 | I13: =(C13*$C$29)+(D13*$C$30)+(E13*$C$31)+(F13*$C$32) -> 1900.9 | J13: 0 | K13: 0 | L13: 0 | M13: =I13-K13 -> 1900.9 | N13: =K13/I13 -> 0
B14: 46113 | C14: 4 | D14: 6 | F14: 14 | G14: =SUM(C14:F14) -> 24 | H14: 152 | I14: =(C14*$C$29)+(D14*$C$30)+(E14*$C$31)+(F14*$C$32) -> 2003.9 | J14: 103910.99 | K14: 37090.53 | L14: 174 | M14: =I14-K14 -> -35086.63 | N14: =K14/I14 -> 18.509172
B15: 46143 | C15: 4 | D15: 6 | F15: 14 | G15: =SUM(C15:F15) -> 24 | H15: 152 | I15: =(C15*$C$29)+(D15*$C$30)+(E15*$C$31)+(F15*$C$32) -> 2003.9 | J15: 28149.5 | K15: 9234.1 | L15: 30 | M15: =I15-K15 -> -7230.2 | N15: =K15/I15 -> 4.6080643
B16: 46174 | C16: 4 | D16: 6 | F16: 14 | G16: =SUM(C16:F16) -> 24 | H16: 152 | I16: =(C16*$C$29)+(D16*$C$30)+(E16*$C$31)+(F16*$C$32) -> 2003.9 | J16: 9928 | K16: 1126.3 | L16: 13 | M16: =I16-K16 -> 877.6 | N16: =K16/I16 -> 0.56205399
B17: 46204 | G17: =SUM(C17:F17) -> 0 | H17: 152 | I17: =(C17*$C$29)+(D17*$C$30)+(E17*$C$31)+(F17*$C$32) -> 0 | M17: =I17-K17 -> 0
B18: 46235 | G18: =SUM(C18:F18) -> 0 | H18: 152 | I18: =(C18*$C$29)+(D18*$C$30)+(E18*$C$31)+(F18*$C$32) -> 0 | M18: =I18-K18 -> 0
B19: 46266 | G19: =SUM(C19:F19) -> 0 | H19: 152 | I19: =(C19*$C$29)+(D19*$C$30)+(E19*$C$31)+(F19*$C$32) -> 0 | M19: =I19-K19 -> 0
B20: 46296 | G20: =SUM(C20:F20) -> 0 | H20: 152 | I20: =(C20*$C$29)+(D20*$C$30)+(E20*$C$31)+(F20*$C$32) -> 0 | M20: =I20-K20 -> 0
B21: 46327 | G21: =SUM(C21:F21) -> 0 | H21: 152 | I21: =(C21*$C$29)+(D21*$C$30)+(E21*$C$31)+(F21*$C$32) -> 0 | M21: =I21-K21 -> 0
B22: 46357 | G22: =SUM(C22:F22) -> 0 | H22: 152 | I22: =(C22*$C$29)+(D22*$C$30)+(E22*$C$31)+(F22*$C$32) -> 0 | M22: =I22-K22 -> 0
B23: 46388 | G23: =SUM(C23:F23) -> 0 | H23: 152 | I23: =(C23*$C$29)+(D23*$C$30)+(E23*$C$31)+(F23*$C$32) -> 0 | M23: =I23-K23 -> 0 | N23: =K23/(H23+I23) -> 0
B25: Averages | C25: =AVERAGEIF(C12:C23,">0") -> 4 | D25: =AVERAGEIF(D12:D23,">0") -> 6 | E25: =AVERAGEIF(E12:E23,">0") -> #DIV/0! | F25: =AVERAGEIF(F12:F23,">0") -> 13.6 | G25: =AVERAGEIF(G12:G23,">0") -> 23.6 | H25: =SUM(H11:H23) -> 1824 | I25: =SUM(I11:I23) -> 9813.5 | J25: =SUM(J11:J23) -> 141988.49 | K25: =SUM(K11:K23) -> 47450.93 | L25: =SUM(L12:L23) -> 217 | M25: =SUM(M12:M23) -> -37637.43 | N25: =K25/I25 -> 4.8352708
B27: Plan Information | J27: Important Year to Date Data
C28: Claims | E28: Administration | G28: Total | J28: Average Claim Submitted | N28: =J25/L25 -> 654.32484
B29: EE Only | C29: 42.15 | E29: 0 | G29: =C29+E29 -> 42.15 | J29: Average Reimbursement | N29: =K25/L25 -> 218.66788
B30: =IF(D10="E+1","EE & One","EE & Spouse") -> EE & Spouse | C30: 65.55 | E30: 0 | G30: =C30+E30 -> 65.55 | J30: Average Number of Claims per Employee per Year | N30: =((L25/COUNTIF(G12:G23,">0"))*12)/G25 -> 22.067797
B31: Admin Cost is a monthly flat rate of $152.00 | J31: Average Reimbursement % of Submitted Charges | N31: =K25/J25 -> 0.33418857
B32: EE & Family | C32: 103 | E32: 0 | G32: =C32+E32 -> 103 | J32: Average Claim Paid per Employee per Month | N32: =K25/G25/(COUNTIF(G12:G23,">0")) -> 402.12653
B35: Plan Design | J35: Prior Year Data
B36: 100% of the first $180; $50 Deductible | J36: Average Claim Submitted | N36: 427.21
B37: 80% of the next $150; 50% of the next $1,400 | J37: Average Reimbursement | N37: 242.12
B38: Ortho covered for Adults and Children | J38: Average Number of Claims per Employee per Year | N38: 4.92
B39: Annual Maximum Amount $1,500 | J39: Average Reimbursement % of Submitted Charges | N39: 0.5668
B40: Assignment of Benefits | J40: Average Claim Paid per Employee per Month | N40: 99.29
J41: Surplus (Deficit) | N41: -2629.92
B43: Important Note: This report reflects claims paid and mailed as of the end of each month. It does not include claims incurred and not yet processed or paid. There are also ongoing adjustments to an employer's benefit account such as corrected claim checks, checks not cashed and claims processed but not yet released due to Simple waiting on the funding of the claims account by the employer. Also, adjustments or corrections to employee enrollments will affect the actual outcomes. Finally, an employer may have deposited more or less to the claims bank account than shown in the budgeted claims column.

Sheet Plan Acct
C1: =[1]plan1!B1 -> Tavares Concrete Company Inc.
C2: Dental or Vision Plan Year Accounting
D4: Plan Year: | E4: =plan1!H3 -> 46054 | F4: through | H4: =plan1!J3 -> 46418
C6: Group ID: | D6: =[1]plan1!D5 -> S448 | H6: Coverage: | J6: =[1]plan1!D6 -> Dental
C8: Month | D8: Deposit | E8: Plan Expenses | H8: Account Balance | J8: NOTES
E9: Claims | F9: Admin | G9: Total | I9: No Pay Premium
C10: Prior Plan Year Ending Balance | H10: 19060.84
C11: =plan1!B12 -> 46054 | D11: 0 | E11: =plan1!K12 -> 0 | F11: =plan1!H12 -> 152 | G11: =E11+F11 -> 152 | H11: =D11-G11 -> -152
C12: =plan1!B13 -> 46082
C13: =plan1!B14 -> 46113
C14: =plan1!B15 -> 46143
C15: =plan1!B16 -> 46174
C16: =plan1!B17 -> 46204
C17: =plan1!B18 -> 46235
C18: =plan1!B19 -> 46266
C19: =plan1!B20 -> 46296
C20: =plan1!B21 -> 46327
C21: =plan1!B22 -> 46357
C22: =plan1!B23 -> 46388 | G22: =E22+F22 -> 0 | H22: =D22-G22 -> 0
C24: Total | D24: =SUM(D11:D22) -> 0 | E24: =SUM(E11:E22) -> 0 | F24: =SUM(F11:F22) -> 152 | G24: =SUM(G11:G22) -> 152 | H24: =SUM(H10:H22) -> 18908.84
C27: Note: The above figures do not include claim adjustments.
C28: * Pending claims include claims processed and not yet released for reimbursement due to low account balance.
C29: * Claims may also be pending if funding was received and posted after the final check run for the month.
