Workbook

Sheet Standard
B1: Quality Plus Services, Inc.
B2: Monthly Performance Report - Budgeted vs Actual Claims Paid
G3: Plan Year: | H3: 46023 | I3: through | J3: 46387
B5: Group ID: | D5: S134 | K5: Plan Name: | M5: Dental
B6: Coverage: | D6: Dental | K6: Plan ID: | M6: S134DEN
B8: ENROLLMENT | H8: ADMIN | I8: CLAIMS | M8: PROFIT OR LOSS
M9: Surplus/ | N9: Loss
B10: Mon, Yr | C10: EE | D10: ES | E10: EC | F10: EF | G10: Total | H10: Costs | I10: Budgeted | J10: Submitted | K10: Paid | L10: Number | M10: Deficit | N10: Ratio
B12: 46023 | C12: 171 | D12: 16 | E12: 14 | F12: 11 | G12: =SUM(C12:F12) -> 212 | H12: =(C12*$E$29)+(D12*$E$30)+(E12*$E$31)+(F12*$E$32) -> 1388.6 | I12: =(C12*$C$29)+(D12*$C$30)+(E12*$C$31)+(F12*$C$32) -> 3157.49 | J12: 0 | K12: 0 | L12: 0 | M12: =I12-K12 -> 3157.49 | N12: =K12/I12 -> 0
B13: 46054 | C13: 168 | D13: 15 | E13: 14 | F13: 11 | G13: =SUM(C13:F13) -> 208 | H13: =(C13*$E$29)+(D13*$E$30)+(E13*$E$31)+(F13*$E$32) -> 1362.4 | I13: =(C13*$C$29)+(D13*$C$30)+(E13*$C$31)+(F13*$C$32) -> 3099.47 | J13: 4116 | K13: 2335 | L13: 11 | M13: =I13-K13 -> 764.47 | N13: =K13/I13 -> 0.75335461
B14: 46082 | C14: 166 | D14: 16 | E14: 14 | F14: 11 | G14: =SUM(C14:F14) -> 207 | H14: =(C14*$E$29)+(D14*$E$30)+(E14*$E$31)+(F14*$E$32) -> 1355.85 | I14: =(C14*$C$29)+(D14*$C$30)+(E14*$C$31)+(F14*$C$32) -> 3099.49 | J14: 7217.5 | K14: 2345.9 | L14: 14 | M14: =I14-K14 -> 753.59 | N14: =K14/I14 -> 0.75686645
B15: 46113 | C15: 165 | D15: 16 | E15: 14 | F15: 11 | G15: =SUM(C15:F15) -> 206 | H15: =(C15*$E$29)+(D15*$E$30)+(E15*$E$31)+(F15*$E$32) -> 1349.3 | I15: =(C15*$C$29)+(D15*$C$30)+(E15*$C$31)+(F15*$C$32) -> 3087.89 | J15: 2984.5 | K15: 1465.9 | L15: 11 | M15: =I15-K15 -> 1621.99 | N15: =K15/I15 -> 0.47472546
B16: 46143 | C16: 139 | D16: 16 | E16: 13 | F16: 9 | G16: =SUM(C16:F16) -> 177 | H16: =(C16*$E$29)+(D16*$E$30)+(E16*$E$31)+(F16*$E$32) -> 1159.35 | I16: =(C16*$C$29)+(D16*$C$30)+(E16*$C$31)+(F16*$C$32) -> 2676.29 | J16: 8146.5 | K16: 4159.3 | L16: 32 | M16: =I16-K16 -> -1483.01 | N16: =K16/I16 -> 1.554129
B17: 46174 | C17: 137 | D17: 16 | E17: 13 | F17: 9 | G17: =SUM(C17:F17) -> 175 | H17: =(C17*$E$29)+(D17*$E$30)+(E17*$E$31)+(F17*$E$32) -> 1146.25 | I17: =(C17*$C$29)+(D17*$C$30)+(E17*$C$31)+(F17*$C$32) -> 2653.09 | J17: 7865 | K17: 2705.1 | L17: 16 | M17: =I17-K17 -> -52.01 | N17: =K17/I17 -> 1.0196036
B18: 46204 | G18: =SUM(C18:F18) -> 0 | H18: =(C18*$E$29)+(D18*$E$30)+(E18*$E$31)+(F18*$E$32) -> 0 | I18: =(C18*$C$29)+(D18*$C$30)+(E18*$C$31)+(F18*$C$32) -> 0 | M18: =I18-K18 -> 0
B19: 46235 | G19: =SUM(C19:F19) -> 0 | H19: =(C19*$E$29)+(D19*$E$30)+(E19*$E$31)+(F19*$E$32) -> 0 | I19: =(C19*$C$29)+(D19*$C$30)+(E19*$C$31)+(F19*$C$32) -> 0 | M19: =I19-K19 -> 0
B20: 46266 | G20: =SUM(C20:F20) -> 0 | H20: =(C20*$E$29)+(D20*$E$30)+(E20*$E$31)+(F20*$E$32) -> 0 | I20: =(C20*$C$29)+(D20*$C$30)+(E20*$C$31)+(F20*$C$32) -> 0 | M20: =I20-K20 -> 0
B21: 46296 | G21: =SUM(C21:F21) -> 0 | H21: =(C21*$E$29)+(D21*$E$30)+(E21*$E$31)+(F21*$E$32) -> 0 | I21: =(C21*$C$29)+(D21*$C$30)+(E21*$C$31)+(F21*$C$32) -> 0 | M21: =I21-K21 -> 0
B22: 46327 | G22: =SUM(C22:F22) -> 0 | H22: =(C22*$E$29)+(D22*$E$30)+(E22*$E$31)+(F22*$E$32) -> 0 | I22: =(C22*$C$29)+(D22*$C$30)+(E22*$C$31)+(F22*$C$32) -> 0 | M22: =I22-K22 -> 0
B23: 46357 | G23: =SUM(C23:F23) -> 0 | H23: =(C23*$E$29)+(D23*$E$30)+(E23*$E$31)+(F23*$E$32) -> 0 | I23: =(C23*$C$29)+(D23*$C$30)+(E23*$C$31)+(F23*$C$32) -> 0 | M23: =I23-K23 -> 0
B25: Averages | C25: =AVERAGEIF(C12:C23,">0") -> 157.66667 | D25: =AVERAGEIF(D12:D23,">0") -> 15.833333 | E25: =AVERAGEIF(E12:E23,">0") -> 13.666667 | F25: =AVERAGEIF(F12:F23,">0") -> 10.333333 | G25: =AVERAGEIF(G12:G23,">0") -> 197.5 | H25: =SUM(H11:H23) -> 7761.75 | I25: =SUM(I11:I23) -> 17773.72 | J25: =SUM(J11:J23) -> 30329.5 | K25: =SUM(K11:K23) -> 13011.2 | L25: =SUM(L12:L23) -> 84 | M25: =SUM(M12:M23) -> 4762.52 | N25: =K25/I25 -> 0.73204709
B27: Plan Information | J27: Important Year to Date Data
C28: Claims | E28: Administration | G28: Total | J28: Average Claim Submitted | N28: =J25/L25 -> 361.06548
B29: EE Only | C29: 11.6 | E29: 6.55 | G29: =C29+E29 -> 18.15 | J29: Average Reimbursement | N29: =K25/L25 -> 154.89524
B30: =IF(D10="E+1","EE & One","EE & Spouse") -> EE & Spouse | C30: 23.22 | E30: 6.55 | G30: =C30+E30 -> 29.77 | J30: Average Number of Claims per Employee per Year | N30: =((L25/COUNTIF(G12:G23,">0"))*12)/G25 -> 0.85063291
B31: EE & Child | C31: 23.22 | E31: 6.55 | G31: =C31+E31 -> 29.77 | J31: Average Reimbursement % of Submitted Charges | N31: =K25/J25 -> 0.42899487
B32: EE & Family | C32: 43.39 | E32: 6.55 | G32: =C32+E32 -> 49.94 | J32: Average Claim Paid per Employee per Month | N32: =K25/G25/(COUNTIF(G12:G23,">0")) -> 10.979916
B35: Plan Design | J35: Prior Year Data
B36: 100% of the first $100; $50 Deductible | J36: Average Claim Submitted | N36: 425.25
B37: 80% of the next $200; 50% of the next $480 | J37: Average Reimbursement | N37: 287.01
B38: Orthodontics not included | J38: Average Number of Claims per Employee per Year | N38: 0.74
B39: Annual Maximum Amount $500 | J39: Average Reimbursement % of Submitted Charges | N39: 0.6749
B40: Assignment of Benefits | J40: Average Claim Paid per Employee per Month | N40: 17.74
J41: Surplus (Deficit) | N41: 11859.81
B43: Important Note: This report reflects claims paid and mailed as of the end of each month. It does not include claims incurred and not yet processed or paid. There are also ongoing adjustments to an employer's benefit account such as corrected claim checks, checks not cashed and claims processed but not yet released due to Simple waiting on the funding of the claims account by the employer. Also, adjustments or corrections to employee enrollments will affect the actual outcomes. Finally, an employer may have deposited more or less to the claims bank account than shown in the budgeted claims column.

Sheet Plan Acct
B1: Quality Plus Services, Inc.
B2: Dental Plan Year Accounting
C4: Plan Year: | D4: 46023 | E4: through | G4: 46387
B6: Group ID: | C6: S134 | G6: Coverage: | H6: DEN
B8: Month | C8: Deposit | D8: Plan Expenses | G8: Adjustments (credit) and debits | H8: Account Balance | I8: Notes
D9: Claims | E9: Admin | F9: Total
B10: Prior Plan Year Ending Balance | H10: 79478.29
B11: =Standard!B12 -> 46023 | C11: 6439.77 | D11: =Standard!K12 -> 0 | E11: =Standard!H12 -> 1388.6 | F11: =D11+E11 -> 1388.6 | H11: =C11-F11 -> 5051.17
B12: =Standard!B13 -> 46054 | D12: =Standard!K13 -> 2335 | E12: =Standard!H13 -> 1362.4 | F12: =D12+E12 -> 3697.4 | H12: =C12-F12 -> -3697.4
B13: =Standard!B14 -> 46082 | C13: 500 | D13: =Standard!K14 -> 2345.9 | E13: =Standard!H14 -> 1355.85 | F13: =D13+E13 -> 3701.75 | H13: =C13-F13 -> -3201.75
B14: =Standard!B15 -> 46113
B15: =Standard!B16 -> 46143
B16: =Standard!B17 -> 46174
B17: =Standard!B18 -> 46204
B18: =Standard!B19 -> 46235
B19: =Standard!B20 -> 46266
B20: =Standard!B21 -> 46296
B21: =Standard!B22 -> 46327
B22: =Standard!B23 -> 46357
B24: Total | C24: =SUM(C11:C22) -> 6939.77 | D24: =SUM(D11:D22) -> 4680.9 | E24: =SUM(E11:E22) -> 4106.85 | F24: =SUM(F11:F22) -> 8787.75 | G24: =SUM(G10:G22) -> 0 | H24: =SUM(H10:H22) -> 77630.31
B27: Note:
B28: * Pending claims include claims processed and not yet released for reimbursement due to low account balance.
B29: * Claims may also be pending if funding was received and posted after the final check run for the month.
