Workbook

Sheet Summary
B1: Windsor HR Services, Inc.
B2: Monthly Performance Report - Budgeted vs Actual Claims Paid
G3: Plan Year: | H3: 46023 | I3: through | J3: 46387
B5: Group ID: | D5: S468 | K5: Plan Name: | M5: Summary
B6: Coverage: | D6: Dental | K6: Plan ID: | M6: S468DEN
B8: ENROLLMENT | H8: ADMIN | I8: CLAIMS | M8: PROFIT OR LOSS
M9: Surplus/ | N9: Loss
B10: Mon, Yr | C10: EE | D10: ES | E10: EC | F10: EF | G10: Total | H10: Costs | I10: Budgeted | J10: Submitted | K10: Paid | L10: Number | M10: Deficit | N10: Ratio
B12: 46023 | C12: =(SILVER!C12)+(PLATINUM!C12) -> 10 | D12: =(SILVER!D12)+(PLATINUM!D12) -> 5 | E12: =(SILVER!E12)+(PLATINUM!E12) -> 6 | F12: =(SILVER!F12)+(PLATINUM!F12) -> 3 | G12: =(SILVER!G12)+(PLATINUM!G12) -> 24 | H12: =(SILVER!H12)+(PLATINUM!H12) -> 148.8 | I12: =(SILVER!I12)+(PLATINUM!I12) -> 1001.31 | J12: =(SILVER!J12)+(PLATINUM!J12) -> 0 | ... M12: =(SILVER!M12)+(PLATINUM!M12) -> 1001.31 | N12: =K12/I12 -> 0
B13: 46054 | C13: =(SILVER!C13)+(PLATINUM!C13) -> 11 | D13: =(SILVER!D13)+(PLATINUM!D13) -> 6 | E13: =(SILVER!E13)+(PLATINUM!E13) -> 6 | F13: =(SILVER!F13)+(PLATINUM!F13) -> 3 | G13: =(SILVER!G13)+(PLATINUM!G13) -> 26 | H13: =(SILVER!H13)+(PLATINUM!H13) -> 161.2 | I13: =(SILVER!I13)+(PLATINUM!I13) -> 1058.56 | J13: =(SILVER!J13)+(PLATINUM!J13) -> 0 | ... M13: =(SILVER!M13)+(PLATINUM!M13) -> 1058.56 | N13: =K13/I13 -> 0
B14: 46082 | C14: =(SILVER!C14)+(PLATINUM!C14) -> 11 | D14: =(SILVER!D14)+(PLATINUM!D14) -> 6 | E14: =(SILVER!E14)+(PLATINUM!E14) -> 6 | F14: =(SILVER!F14)+(PLATINUM!F14) -> 3 | G14: =(SILVER!G14)+(PLATINUM!G14) -> 26 | H14: =(SILVER!H14)+(PLATINUM!H14) -> 161.2 | I14: =(SILVER!I14)+(PLATINUM!I14) -> 1058.56 | J14: =(SILVER!J14)+(PLATINUM!J14) -> 2430.7 | ... M14: =(SILVER!M14)+(PLATINUM!M14) -> -276.34 | N14: =K14/I14 -> 1.2610528
B15: 46113 | C15: =(SILVER!C15)+(PLATINUM!C15) -> 11 | D15: =(SILVER!D15)+(PLATINUM!D15) -> 6 | E15: =(SILVER!E15)+(PLATINUM!E15) -> 6 | F15: =(SILVER!F15)+(PLATINUM!F15) -> 3 | G15: =(SILVER!G15)+(PLATINUM!G15) -> 26 | H15: =(SILVER!H15)+(PLATINUM!H15) -> 161.2 | I15: =(SILVER!I15)+(PLATINUM!I15) -> 1058.56 | J15: =(SILVER!J15)+(PLATINUM!J15) -> 558 | ... M15: =(SILVER!M15)+(PLATINUM!M15) -> 1058.56 | N15: =K15/I15 -> 0
B16: 46143 | C16: =(SILVER!C16)+(PLATINUM!C16) -> 12 | D16: =(SILVER!D16)+(PLATINUM!D16) -> 6 | E16: =(SILVER!E16)+(PLATINUM!E16) -> 5 | F16: =(SILVER!F16)+(PLATINUM!F16) -> 3 | G16: =(SILVER!G16)+(PLATINUM!G16) -> 26 | H16: =(SILVER!H16)+(PLATINUM!H16) -> 161.2 | I16: =(SILVER!I16)+(PLATINUM!I16) -> 1030.96 | J16: =(SILVER!J16)+(PLATINUM!J16) -> 423 | K16: =(SILVER!K16)+(PLATINUM!K16) -> 0 | L16: 1 | M16: =(SILVER!M16)+(PLATINUM!M16) -> 1030.96 | N16: =K16/I16 -> 0
B17: 46174 | C17: =(SILVER!C17)+(PLATINUM!C17) -> 12 | D17: =(SILVER!D17)+(PLATINUM!D17) -> 6 | E17: =(SILVER!E17)+(PLATINUM!E17) -> 5 | F17: =(SILVER!F17)+(PLATINUM!F17) -> 3 | G17: =(SILVER!G17)+(PLATINUM!G17) -> 26 | H17: =(SILVER!H17)+(PLATINUM!H17) -> 161.2 | I17: =(SILVER!I17)+(PLATINUM!I17) -> 1030.96 | J17: =(SILVER!J17)+(PLATINUM!J17) -> 348 | K17: =(SILVER!K17)+(PLATINUM!K17) -> 224 | M17: =(SILVER!M17)+(PLATINUM!M17) -> 806.96 | N17: =K17/I17 -> 0.21727322
B18: 46204 | C18: =(SILVER!C18)+(PLATINUM!C18) -> 0 | D18: =(SILVER!D18)+(PLATINUM!D18) -> 0 | E18: =(SILVER!E18)+(PLATINUM!E18) -> 0 | F18: =(SILVER!F18)+(PLATINUM!F18) -> 0 | G18: =(SILVER!G18)+(PLATINUM!G18) -> 0 | H18: =(SILVER!H18)+(PLATINUM!H18) -> 0 | I18: =(SILVER!I18)+(PLATINUM!I18) -> 0 | J18: =(SILVER!J18)+(PLATINUM!J18) -> 0 | K18: =(SILVER!K18)+(PLATINUM!K18) -> 0 | M18: =(SILVER!M18)+(PLATINUM!M18) -> 0
B19: 46235 | C19: =(SILVER!C19)+(PLATINUM!C19) -> 0 | D19: =(SILVER!D19)+(PLATINUM!D19) -> 0 | E19: =(SILVER!E19)+(PLATINUM!E19) -> 0 | F19: =(SILVER!F19)+(PLATINUM!F19) -> 0 | G19: =(SILVER!G19)+(PLATINUM!G19) -> 0 | H19: =(SILVER!H19)+(PLATINUM!H19) -> 0 | I19: =(SILVER!I19)+(PLATINUM!I19) -> 0 | J19: =(SILVER!J19)+(PLATINUM!J19) -> 0 | K19: =(SILVER!K19)+(PLATINUM!K19) -> 0 | M19: =(SILVER!M19)+(PLATINUM!M19) -> 0
B20: 46266 | C20: =(SILVER!C20)+(PLATINUM!C20) -> 0 | D20: =(SILVER!D20)+(PLATINUM!D20) -> 0 | E20: =(SILVER!E20)+(PLATINUM!E20) -> 0 | F20: =(SILVER!F20)+(PLATINUM!F20) -> 0 | G20: =(SILVER!G20)+(PLATINUM!G20) -> 0 | H20: =(SILVER!H20)+(PLATINUM!H20) -> 0 | I20: =(SILVER!I20)+(PLATINUM!I20) -> 0 | J20: =(SILVER!J20)+(PLATINUM!J20) -> 0 | K20: =(SILVER!K20)+(PLATINUM!K20) -> 0 | M20: =(SILVER!M20)+(PLATINUM!M20) -> 0
B21: 46296 | C21: =(SILVER!C21)+(PLATINUM!C21) -> 0 | D21: =(SILVER!D21)+(PLATINUM!D21) -> 0 | E21: =(SILVER!E21)+(PLATINUM!E21) -> 0 | F21: =(SILVER!F21)+(PLATINUM!F21) -> 0 | G21: =(SILVER!G21)+(PLATINUM!G21) -> 0 | H21: =(SILVER!H21)+(PLATINUM!H21) -> 0 | I21: =(SILVER!I21)+(PLATINUM!I21) -> 0 | J21: =(SILVER!J21)+(PLATINUM!J21) -> 0 | K21: =(SILVER!K21)+(PLATINUM!K21) -> 0 | M21: =(SILVER!M21)+(PLATINUM!M21) -> 0
B22: 46327 | C22: =(SILVER!C22)+(PLATINUM!C22) -> 0 | D22: =(SILVER!D22)+(PLATINUM!D22) -> 0 | E22: =(SILVER!E22)+(PLATINUM!E22) -> 0 | F22: =(SILVER!F22)+(PLATINUM!F22) -> 0 | G22: =(SILVER!G22)+(PLATINUM!G22) -> 0 | H22: =(SILVER!H22)+(PLATINUM!H22) -> 0 | I22: =(SILVER!I22)+(PLATINUM!I22) -> 0 | J22: =(SILVER!J22)+(PLATINUM!J22) -> 0 | K22: =(SILVER!K22)+(PLATINUM!K22) -> 0 | M22: =(SILVER!M22)+(PLATINUM!M22) -> 0
B23: 46357 | C23: =(SILVER!C23)+(PLATINUM!C23) -> 0 | D23: =(SILVER!D23)+(PLATINUM!D23) -> 0 | E23: =(SILVER!E23)+(PLATINUM!E23) -> 0 | F23: =(SILVER!F23)+(PLATINUM!F23) -> 0 | G23: =(SILVER!G23)+(PLATINUM!G23) -> 0 | H23: =(SILVER!H23)+(PLATINUM!H23) -> 0 | I23: =(SILVER!I23)+(PLATINUM!I23) -> 0 | J23: =(SILVER!J23)+(PLATINUM!J23) -> 0 | K23: =(SILVER!K23)+(PLATINUM!K23) -> 0 | M23: =(SILVER!M23)+(PLATINUM!M23) -> 0
B25: Averages | C25: =AVERAGEIF(C12:C23,">0") -> 11.166667 | D25: =AVERAGEIF(D12:D23,">0") -> 5.8333333 | E25: =AVERAGEIF(E12:E23,">0") -> 5.6666667 | F25: =AVERAGEIF(F12:F23,">0") -> 3 | G25: =AVERAGEIF(G12:G23,">0") -> 25.666667 | H25: =SUM(H11:H23) -> 954.8 | I25: =SUM(I11:I23) -> 6238.91 | J25: =SUM(J11:J23) -> 3759.7 | K25: =SUM(K11:K23) -> 1558.9 | L25: =SUM(L12:L23) -> 9 | M25: =SUM(M12:M23) -> 4680.01 | N25: =K25/I25 -> 0.24986736
J27: Important Year to Date Data
J28: Average Claim Submitted | N28: =J25/L25 -> 417.74444
J29: Average Reimbursement | N29: =K25/L25 -> 173.21111
J30: Average Number of Claims per Employee per Year | N30: =((L25/COUNTIF(G12:G23,">0"))*12)/G25 -> 0.7012987
J31: Average Reimbursement % of Submitted Charges | N31: =K25/J25 -> 0.41463415
J32: Average Claim Paid per Employee per Month | N32: =K25/G25/(COUNTIF(G12:G23,">0")) -> 10.122727
J35: Prior Year Data
J36: Average Claim Submitted | N36: 534.06
J37: Average Reimbursement | N37: 328.09
J38: Average Number of Claims per Employee per Year | N38: 1.24
J39: Average Reimbursement % of Submitted Charges | N39: 0.6143
J40: Average Claim Paid per Employee per Month | N40: 33.79
J41: Surplus (Deficit) | N41: 4680.05
B43: Important Note: This report reflects claims paid and mailed as of the end of each month. It does not include claims incurred and not yet processed or paid. There are also ongoing adjustments to an employer's benefit account such as corrected claim checks, checks not cashed and claims processed but not yet released due to Simple waiting on the funding of the claims account by the employer. Also, adjustments or corrections to employee enrollments will affect the actual outcomes. Finally, an employer may have deposited more or less to the claims bank account than shown in the budgeted claims column.

Sheet SILVER
B1: =Summary!B1 -> Windsor HR Services, Inc.
B2: =Summary!B2 -> Monthly Performance Report - Budgeted vs Actual Claims Paid
G3: Plan Year: | H3: =Summary!H3 -> 46023 | I3: through | J3: =Summary!J3 -> 46387
B5: Group ID: | D5: =Summary!D5 -> S468 | K5: Plan Name: | M5: Silver
B6: Coverage: | D6: Dental | K6: Plan ID: | M6: S468DEN SILVER
B8: ENROLLMENT | H8: ADMIN | I8: CLAIMS | M8: PROFIT OR LOSS
M9: Surplus/ | N9: Loss
B10: Mon, Yr | C10: EE | D10: E+S | E10: EC | F10: EF | G10: Total | H10: Costs | I10: Budgeted | J10: Submitted | K10: Paid | L10: Number | M10: Deficit | N10: Ratio
B12: =Summary!B12 -> 46023 | C12: 3 | D12: 1 | E12: 2 | F12: 1 | G12: =SUM(C12:F12) -> 7 | H12: =(C12*$E$29)+(D12*$E$30)+(E12*$E$31)+(F12*$E$32) -> 43.4 | I12: =(C12*$C$29)+(D12*$C$30)+(E12*$C$31)+(F12*$C$32) -> 173.71 | J12: 0 | K12: 0 | L12: 0 | M12: =I12-K12 -> 173.71 | N12: =K12/I12 -> 0
B13: =Summary!B13 -> 46054 | C13: 3 | D13: 2 | E13: 2 | F13: 1 | G13: =SUM(C13:F13) -> 8 | H13: =(C13*$E$29)+(D13*$E$30)+(E13*$E$31)+(F13*$E$32) -> 49.6 | I13: =(C13*$C$29)+(D13*$C$30)+(E13*$C$31)+(F13*$C$32) -> 201.16 | J13: 0 | K13: 0 | L13: 0 | M13: =I13-K13 -> 201.16 | N13: =K13/I13 -> 0
B14: =Summary!B14 -> 46082 | C14: 3 | D14: 2 | E14: 2 | F14: 1 | G14: =SUM(C14:F14) -> 8 | H14: =(C14*$E$29)+(D14*$E$30)+(E14*$E$31)+(F14*$E$32) -> 49.6 | I14: =(C14*$C$29)+(D14*$C$30)+(E14*$C$31)+(F14*$C$32) -> 201.16 | J14: 323 | K14: 211.5 | L14: 1 | M14: =I14-K14 -> -10.34 | N14: =K14/I14 -> 1.0514019
B15: =Summary!B15 -> 46113 | C15: 3 | D15: 2 | E15: 2 | F15: 1 | G15: =SUM(C15:F15) -> 8 | H15: =(C15*$E$29)+(D15*$E$30)+(E15*$E$31)+(F15*$E$32) -> 49.6 | I15: =(C15*$C$29)+(D15*$C$30)+(E15*$C$31)+(F15*$C$32) -> 201.16 | J15: 0 | K15: 0 | L15: 0 | M15: =I15-K15 -> 201.16 | N15: =K15/I15 -> 0
B16: =Summary!B16 -> 46143 | C16: 3 | D16: 2 | E16: 2 | F16: 1 | G16: =SUM(C16:F16) -> 8 | H16: =(C16*$E$29)+(D16*$E$30)+(E16*$E$31)+(F16*$E$32) -> 49.6 | I16: =(C16*$C$29)+(D16*$C$30)+(E16*$C$31)+(F16*$C$32) -> 201.16 | J16: 423 | K16: 0 | L16: 1 | M16: =I16-K16 -> 201.16 | N16: =K16/I16 -> 0
B17: =Summary!B17 -> 46174 | C17: 3 | D17: 2 | E17: 2 | F17: 1 | G17: =SUM(C17:F17) -> 8 | H17: =(C17*$E$29)+(D17*$E$30)+(E17*$E$31)+(F17*$E$32) -> 49.6 | I17: =(C17*$C$29)+(D17*$C$30)+(E17*$C$31)+(F17*$C$32) -> 201.16 | J17: 348 | K17: 224 | L17: 1 | M17: =I17-K17 -> -22.84 | N17: =K17/I17 -> 1.1135415
B18: =Summary!B18 -> 46204 | G18: =SUM(C18:F18) -> 0 | H18: =(C18*$E$29)+(D18*$E$30)+(E18*$E$31)+(F18*$E$32) -> 0 | I18: =(C18*$C$29)+(D18*$C$30)+(E18*$C$31)+(F18*$C$32) -> 0 | M18: =I18-K18 -> 0
B19: =Summary!B19 -> 46235 | G19: =SUM(C19:F19) -> 0 | H19: =(C19*$E$29)+(D19*$E$30)+(E19*$E$31)+(F19*$E$32) -> 0 | I19: =(C19*$C$29)+(D19*$C$30)+(E19*$C$31)+(F19*$C$32) -> 0 | M19: =I19-K19 -> 0
B20: =Summary!B20 -> 46266 | G20: =SUM(C20:F20) -> 0 | H20: =(C20*$E$29)+(D20*$E$30)+(E20*$E$31)+(F20*$E$32) -> 0 | I20: =(C20*$C$29)+(D20*$C$30)+(E20*$C$31)+(F20*$C$32) -> 0 | M20: =I20-K20 -> 0
B21: =Summary!B21 -> 46296 | G21: =SUM(C21:F21) -> 0 | H21: =(C21*$E$29)+(D21*$E$30)+(E21*$E$31)+(F21*$E$32) -> 0 | I21: =(C21*$C$29)+(D21*$C$30)+(E21*$C$31)+(F21*$C$32) -> 0 | M21: =I21-K21 -> 0
B22: =Summary!B22 -> 46327 | G22: =SUM(C22:F22) -> 0 | H22: =(C22*$E$29)+(D22*$E$30)+(E22*$E$31)+(F22*$E$32) -> 0 | I22: =(C22*$C$29)+(D22*$C$30)+(E22*$C$31)+(F22*$C$32) -> 0 | M22: =I22-K22 -> 0
B23: =Summary!B23 -> 46357 | G23: =SUM(C23:F23) -> 0 | H23: =(C23*$E$29)+(D23*$E$30)+(E23*$E$31)+(F23*$E$32) -> 0 | I23: =(C23*$C$29)+(D23*$C$30)+(E23*$C$31)+(F23*$C$32) -> 0 | M23: =I23-K23 -> 0
B25: Averages | C25: =AVERAGEIF(C12:C23,">0") -> 3 | D25: =AVERAGEIF(D12:D23,">0") -> 1.8333333 | E25: =AVERAGEIF(E12:E23,">0") -> 2 | F25: =AVERAGEIF(F12:F23,">0") -> 1 | G25: =AVERAGEIF(G12:G23,">0") -> 7.8333333 | H25: =SUM(H11:H23) -> 291.4 | I25: =SUM(I11:I23) -> 1179.51 | J25: =SUM(J11:J23) -> 1094 | K25: =SUM(K11:K23) -> 435.5 | L25: =SUM(L12:L23) -> 3 | M25: =SUM(M12:M23) -> 744.01 | N25: =K25/I25 -> 0.36922112
B27: Plan Information | J27: Important Year to Date Data
C28: Claims | E28: Administration | G28: Total | J28: Average Claim Submitted | N28: =J25/L25 -> 364.66667
B29: EE Only | C29: 13.32 | E29: 6.2 | G29: =C29+E29 -> 19.52 | J29: Average Reimbursement | N29: =K25/L25 -> 145.16667
B30: =IF(D10="E+1","EE & One","EE & Spouse") -> EE & Spouse | C30: 27.45 | E30: 6.2 | G30: =C30+E30 -> 33.65 | J30: Average Number of Claims per Employee per Year | N30: =((L25/COUNTIF(G12:G23,">0"))*12)/G25 -> 0.76595745
B31: EE & Children | C31: 30.15 | E31: 6.2 | G31: =C31+E31 -> 36.35 | J31: Average Reimbursement % of Submitted Charges | N31: =K25/J25 -> 0.39808044
B32: EE & Family | C32: 46 | E32: 6.2 | G32: =C32+E32 -> 52.2 | J32: Average Claim Paid per Employee per Month | N32: =K25/G25/(COUNTIF(G12:G23,">0")) -> 9.2659574
B35: Plan Design | J35: Prior Year Data
B36: 100% of the first $100 | J36: Average Claim Submitted | N36: 240.2
B37: 50% of the next $2,300 | J37: Average Reimbursement | N37: 150.1
B38: Ortho not covered | J38: Average Number of Claims per Employee per Year | N38: 0.5
B39: Annual Maximum Amount $1,250 | J39: Average Reimbursement % of Submitted Charges | N39: 0.6249
B40: Assignment of Benefits | J40: Average Claim Paid per Employee per Month | N40: 6.2
J41: Surplus (Deficit) | N41: 2785.05
B43: Important Note: This report reflects claims paid and mailed as of the end of each month. It does not include claims incurred and not yet processed or paid. There are also ongoing adjustments to an employer's benefit account such as corrected claim checks, checks not cashed and claims processed but not yet released due to Simple waiting on the funding of the claims account by the employer. Also, adjustments or corrections to employee enrollments will affect the actual outcomes. Finally, an employer may have deposited more or less to the claims bank account than shown in the budgeted claims column.

Sheet PLATINUM
B1: =Summary!B1 -> Windsor HR Services, Inc.
B2: =Summary!B2 -> Monthly Performance Report - Budgeted vs Actual Claims Paid
G3: Plan Year: | H3: =Summary!H3 -> 46023 | I3: through | J3: =Summary!J3 -> 46387
B5: Group ID: | D5: =Summary!D5 -> S468 | K5: Plan Name: | M5: PLATINUM
B6: Coverage: | D6: Dental | K6: Plan ID: | M6: S468DEN PLATINUM
B8: ENROLLMENT | H8: ADMIN | I8: CLAIMS | M8: PROFIT OR LOSS
M9: Surplus/ | N9: Loss
B10: Mon, Yr | C10: EE | D10: E+S | E10: EC | F10: EF | G10: Total | H10: Costs | I10: Budgeted | J10: Submitted | K10: Paid | L10: Number | M10: Deficit | N10: Ratio
B12: =Summary!B12 -> 46023 | C12: 7 | D12: 4 | E12: 4 | F12: 2 | G12: =SUM(C12:F12) -> 17 | H12: =(C12*$E$29)+(D12*$E$30)+(E12*$E$31)+(F12*$E$32) -> 105.4 | I12: =(C12*$C$29)+(D12*$C$30)+(E12*$C$31)+(F12*$C$32) -> 827.6 | J12: 0 | K12: 0 | L12: 0 | M12: =I12-K12 -> 827.6 | N12: =K12/I12 -> 0
B13: =Summary!B13 -> 46054 | C13: 8 | D13: 4 | E13: 4 | F13: 2 | G13: =SUM(C13:F13) -> 18 | H13: =(C13*$E$29)+(D13*$E$30)+(E13*$E$31)+(F13*$E$32) -> 111.6 | I13: =(C13*$C$29)+(D13*$C$30)+(E13*$C$31)+(F13*$C$32) -> 857.4 | J13: 0 | K13: 0 | L13: 0 | M13: =I13-K13 -> 857.4 | N13: =K13/I13 -> 0
B14: =Summary!B14 -> 46082 | C14: 8 | D14: 4 | E14: 4 | F14: 2 | G14: =SUM(C14:F14) -> 18 | H14: =(C14*$E$29)+(D14*$E$30)+(E14*$E$31)+(F14*$E$32) -> 111.6 | I14: =(C14*$C$29)+(D14*$C$30)+(E14*$C$31)+(F14*$C$32) -> 857.4 | J14: 2107.7 | K14: 1123.4 | L14: 5 | M14: =I14-K14 -> -266 | N14: =K14/I14 -> 1.3102403
B15: =Summary!B15 -> 46113 | C15: 8 | D15: 4 | E15: 4 | F15: 2 | G15: =SUM(C15:F15) -> 18 | H15: =(C15*$E$29)+(D15*$E$30)+(E15*$E$31)+(F15*$E$32) -> 111.6 | I15: =(C15*$C$29)+(D15*$C$30)+(E15*$C$31)+(F15*$C$32) -> 857.4 | J15: 558 | K15: 0 | L15: 2 | M15: =I15-K15 -> 857.4 | N15: =K15/I15 -> 0
B16: =Summary!B16 -> 46143 | C16: 9 | D16: 4 | E16: 3 | F16: 2 | G16: =SUM(C16:F16) -> 18 | H16: =(C16*$E$29)+(D16*$E$30)+(E16*$E$31)+(F16*$E$32) -> 111.6 | I16: =(C16*$C$29)+(D16*$C$30)+(E16*$C$31)+(F16*$C$32) -> 829.8 | J16: 0 | K16: 0 | L16: 0 | M16: =I16-K16 -> 829.8 | N16: =K16/I16 -> 0
B17: =Summary!B17 -> 46174 | C17: 9 | D17: 4 | E17: 3 | F17: 2 | G17: =SUM(C17:F17) -> 18 | H17: =(C17*$E$29)+(D17*$E$30)+(E17*$E$31)+(F17*$E$32) -> 111.6 | I17: =(C17*$C$29)+(D17*$C$30)+(E17*$C$31)+(F17*$C$32) -> 829.8 | J17: 0 | K17: 0 | L17: 0 | M17: =I17-K17 -> 829.8 | N17: =K17/I17 -> 0
B18: =Summary!B18 -> 46204 | G18: =SUM(C18:F18) -> 0 | H18: =(C18*$E$29)+(D18*$E$30)+(E18*$E$31)+(F18*$E$32) -> 0 | I18: =(C18*$C$29)+(D18*$C$30)+(E18*$C$31)+(F18*$C$32) -> 0 | M18: =I18-K18 -> 0
B19: =Summary!B19 -> 46235 | G19: =SUM(C19:F19) -> 0 | H19: =(C19*$E$29)+(D19*$E$30)+(E19*$E$31)+(F19*$E$32) -> 0 | I19: =(C19*$C$29)+(D19*$C$30)+(E19*$C$31)+(F19*$C$32) -> 0 | M19: =I19-K19 -> 0
B20: =Summary!B20 -> 46266 | G20: =SUM(C20:F20) -> 0 | H20: =(C20*$E$29)+(D20*$E$30)+(E20*$E$31)+(F20*$E$32) -> 0 | I20: =(C20*$C$29)+(D20*$C$30)+(E20*$C$31)+(F20*$C$32) -> 0 | M20: =I20-K20 -> 0
B21: =Summary!B21 -> 46296 | G21: =SUM(C21:F21) -> 0 | H21: =(C21*$E$29)+(D21*$E$30)+(E21*$E$31)+(F21*$E$32) -> 0 | I21: =(C21*$C$29)+(D21*$C$30)+(E21*$C$31)+(F21*$C$32) -> 0 | M21: =I21-K21 -> 0
B22: =Summary!B22 -> 46327 | G22: =SUM(C22:F22) -> 0 | H22: =(C22*$E$29)+(D22*$E$30)+(E22*$E$31)+(F22*$E$32) -> 0 | I22: =(C22*$C$29)+(D22*$C$30)+(E22*$C$31)+(F22*$C$32) -> 0 | M22: =I22-K22 -> 0
B23: =Summary!B23 -> 46357 | G23: =SUM(C23:F23) -> 0 | H23: =(C23*$E$29)+(D23*$E$30)+(E23*$E$31)+(F23*$E$32) -> 0 | I23: =(C23*$C$29)+(D23*$C$30)+(E23*$C$31)+(F23*$C$32) -> 0 | M23: =I23-K23 -> 0
B25: Averages | C25: =AVERAGEIF(C12:C23,">0") -> 8.1666667 | D25: =AVERAGEIF(D12:D23,">0") -> 4 | E25: =AVERAGEIF(E12:E23,">0") -> 3.6666667 | F25: =AVERAGEIF(F12:F23,">0") -> 2 | G25: =AVERAGEIF(G12:G23,">0") -> 17.833333 | H25: =SUM(H11:H23) -> 663.4 | I25: =SUM(I11:I23) -> 5059.4 | J25: =SUM(J11:J23) -> 2665.7 | K25: =SUM(K11:K23) -> 1123.4 | L25: =SUM(L12:L23) -> 7 | M25: =SUM(M12:M23) -> 3936 | N25: =K25/I25 -> 0.22204214
B27: Plan Information | J27: Important Year to Date Data
C28: Claims | E28: Administration | G28: Total | J28: Average Claim Submitted | N28: =J25/L25 -> 380.81429
B29: EE Only | C29: 29.8 | E29: 6.2 | G29: =C29+E29 -> 36 | J29: Average Reimbursement | N29: =K25/L25 -> 160.48571
B30: =IF(D10="E+1","EE & One","EE & Spouse") -> EE & Spouse | C30: 55.3 | E30: 6.2 | G30: =C30+E30 -> 61.5 | J30: Average Number of Claims per Employee per Year | N30: =((L25/COUNTIF(G12:G23,">0"))*12)/G25 -> 0.78504673
B31: EE & Children | C31: 57.4 | E31: 6.2 | G31: =C31+E31 -> 63.6 | J31: Average Reimbursement % of Submitted Charges | N31: =K25/J25 -> 0.42142777
B32: EE & Family | C32: 84.1 | E32: 6.2 | G32: =C32+E32 -> 90.3 | J32: Average Claim Paid per Employee per Month | N32: =K25/G25/(COUNTIF(G12:G23,">0")) -> 10.499065
B35: Plan Design | J35: Prior Year Data
B36: 100% of the first $300.00 | J36: Average Claim Submitted | N36: 578.58
B37: 50% of the remaining $3,400 | J37: Average Reimbursement | N37: 355.06
B38: Ortho covered for Adults and Children*After waiting period | J38: Average Number of Claims per Employee per Year | N38: 1.6
B39: Annual Maximum Amount $2,000 | J39: Average Reimbursement % of Submitted Charges | N39: 0.6137
B40: Assignment of Benefits | J40: Average Claim Paid per Employee per Month | N40: 47.25
J41: Surplus (Deficit) | N41: 1895
B43: Important Note: This report reflects claims paid and mailed as of the end of each month. It does not include claims incurred and not yet processed or paid. There are also ongoing adjustments to an employer's benefit account such as corrected claim checks, checks not cashed and claims processed but not yet released due to Simple waiting on the funding of the claims account by the employer. Also, adjustments or corrections to employee enrollments will affect the actual outcomes. Finally, an employer may have deposited more or less to the claims bank account than shown in the budgeted claims column.
