Workbook

Sheet Summary
B1: Mountainseed Appraisal Management, LLC.
B2: Monthly Performance Report - Budgeted vs Actual Claims Paid
G3: Plan Year: | H3: 45962 | I3: through | J3: 46326
B5: Group ID: | D5: S480 | K5: Plan Name: | M5: Summary
B6: Coverage: | D6: Dental | K6: Plan ID: | M6: S480DEN
B8: ENROLLMENT | H8: ADMIN | I8: CLAIMS | M8: PROFIT OR LOSS
M9: Surplus/ | N9: Loss
B10: Mon, Yr | C10: EE | D10: ES | E10: EC | F10: EF | G10: Total | H10: Costs | I10: Budgeted | J10: Submitted | K10: Paid | L10: Number | M10: Deficit | N10: Ratio
B12: 45962 | C12: =(GOLD!C12)+(SILVER!C12)+(Platinum!C12) -> 51 | D12: =(GOLD!D12)+(SILVER!D12)+(Platinum!D12) -> 16 | E12: =(GOLD!E12)+(SILVER!E12)+(Platinum!E12) -> 4 | F12: =(GOLD!F12)+(SILVER!F12)+(Platinum!F12) -> 21 | G12: =(GOLD!G12)+(SILVER!G12)+(Platinum!G12) -> 92 | H12: =(GOLD!H12)+(SILVER!H12)+(Platinum!H12) -> 510.6 | I12: =(GOLD!I12)+(SILVER!I12)+(Platinum!I12) -> 9674.24 | J12: =(GOLD!J12)+(SILVER!J12)+(Platinum!J12) -> 0 | ... M12: =(GOLD!M12)+(SILVER!M12)+(Platinum!M12) -> 9674.24 | N12: =K12/I12 -> 0
B13: 45992 | C13: =(GOLD!C13)+(SILVER!C13)+(Platinum!C13) -> 51 | D13: =(GOLD!D13)+(SILVER!D13)+(Platinum!D13) -> 16 | E13: =(GOLD!E13)+(SILVER!E13)+(Platinum!E13) -> 4 | F13: =(GOLD!F13)+(SILVER!F13)+(Platinum!F13) -> 19 | G13: =(GOLD!G13)+(SILVER!G13)+(Platinum!G13) -> 90 | H13: =(GOLD!H13)+(SILVER!H13)+(Platinum!H13) -> 499.5 | I13: =(GOLD!I13)+(SILVER!I13)+(Platinum!I13) -> 8743.45 | J13: =(GOLD!J13)+(SILVER!J13)+(Platinum!J13) -> 18264.39 | ... M13: =(GOLD!M13)+(SILVER!M13)+(Platinum!M13) -> -3277.38 | N13: =K13/I13 -> 1.3748383
B14: 46023 | C14: =(GOLD!C14)+(SILVER!C14)+(Platinum!C14) -> 51 | D14: =(GOLD!D14)+(SILVER!D14)+(Platinum!D14) -> 16 | E14: =(GOLD!E14)+(SILVER!E14)+(Platinum!E14) -> 4 | F14: =(GOLD!F14)+(SILVER!F14)+(Platinum!F14) -> 19 | G14: =(GOLD!G14)+(SILVER!G14)+(Platinum!G14) -> 90 | H14: =(GOLD!H14)+(SILVER!H14)+(Platinum!H14) -> 499.5 | I14: =(GOLD!I14)+(SILVER!I14)+(Platinum!I14) -> 8743.45 | J14: =GOLD!J14+SILVER!J14+Platinum!J14 -> 4681.2 | K14: =GOLD!K14+SILVER!K14+Platinum!K14 -> 2547.44 | L14: =GOLD!L14+SILVER!L14+Platinum!L14 -> 8 | M14: =(GOLD!M14)+(SILVER!M14)+(Platinum!M14) -> 6196.01 | N14: =K14/I14 -> 0.2913541
B15: 46054 | C15: =(GOLD!C15)+(SILVER!C15)+(Platinum!C15) -> 48 | D15: =(GOLD!D15)+(SILVER!D15)+(Platinum!D15) -> 16 | E15: =(GOLD!E15)+(SILVER!E15)+(Platinum!E15) -> 4 | F15: =(GOLD!F15)+(SILVER!F15)+(Platinum!F15) -> 17 | G15: =(GOLD!G15)+(SILVER!G15)+(Platinum!G15) -> 85 | H15: =(GOLD!H15)+(SILVER!H15)+(Platinum!H15) -> 471.75 | I15: =(GOLD!I15)+(SILVER!I15)+(Platinum!I15) -> 8105.02 | J15: =(GOLD!J15)+(SILVER!J15)+(Platinum!J15) -> 9202 | ... M15: =(GOLD!M15)+(SILVER!M15)+(Platinum!M15) -> 2372.62 | N15: =K15/I15 -> 0.70726537
B16: 46082 | C16: =(GOLD!C16)+(SILVER!C16)+(Platinum!C16) -> 50 | D16: =(GOLD!D16)+(SILVER!D16)+(Platinum!D16) -> 16 | E16: =(GOLD!E16)+(SILVER!E16)+(Platinum!E16) -> 5 | F16: =(GOLD!F16)+(SILVER!F16)+(Platinum!F16) -> 17 | G16: =(GOLD!G16)+(SILVER!G16)+(Platinum!G16) -> 88 | H16: =(GOLD!H16)+(SILVER!H16)+(Platinum!H16) -> 488.4 | I16: =(GOLD!I16)+(SILVER!I16)+(Platinum!I16) -> 8422.84 | J16: =(GOLD!J16)+(SILVER!J16)+(Platinum!J16) -> 8771.09 | ... M16: =(GOLD!M16)+(SILVER!M16)+(Platinum!M16) -> 3366.42 | N16: =K16/I16 -> 0.60032246
B17: 46113 | C17: =(GOLD!C17)+(SILVER!C17)+(Platinum!C17) -> 50 | D17: =(GOLD!D17)+(SILVER!D17)+(Platinum!D17) -> 16 | E17: =(GOLD!E17)+(SILVER!E17)+(Platinum!E17) -> 5 | F17: =(GOLD!F17)+(SILVER!F17)+(Platinum!F17) -> 18 | G17: =(GOLD!G17)+(SILVER!G17)+(Platinum!G17) -> 89 | H17: =(GOLD!H17)+(SILVER!H17)+(Platinum!H17) -> 493.95 | I17: =(GOLD!I17)+(SILVER!I17)+(Platinum!I17) -> 8553.84 | J17: =(GOLD!J17)+(SILVER!J17)+(Platinum!J17) -> 32550.41 | ... M17: =(GOLD!M17)+(SILVER!M17)+(Platinum!M17) -> -6624.42 | N17: =K17/I17 -> 1.7744381
B18: 46143 | C18: =(GOLD!C18)+(SILVER!C18)+(Platinum!C18) -> 50 | D18: =(GOLD!D18)+(SILVER!D18)+(Platinum!D18) -> 16 | E18: =(GOLD!E18)+(SILVER!E18)+(Platinum!E18) -> 5 | F18: =(GOLD!F18)+(SILVER!F18)+(Platinum!F18) -> 18 | G18: =(GOLD!G18)+(SILVER!G18)+(Platinum!G18) -> 89 | H18: =(GOLD!H18)+(SILVER!H18)+(Platinum!H18) -> 493.95 | I18: =(GOLD!I18)+(SILVER!I18)+(Platinum!I18) -> 8553.84 | J18: =(GOLD!J18)+(SILVER!J18)+(Platinum!J18) -> 16799.64 | ... M18: =(GOLD!M18)+(SILVER!M18)+(Platinum!M18) -> 44.42 | N18: =K18/I18 -> 0.99480701
B19: 46174 | C19: =(GOLD!C19)+(SILVER!C19)+(Platinum!C19) -> 49 | D19: =(GOLD!D19)+(SILVER!D19)+(Platinum!D19) -> 16 | E19: =(GOLD!E19)+(SILVER!E19)+(Platinum!E19) -> 5 | F19: =(GOLD!F19)+(SILVER!F19)+(Platinum!F19) -> 19 | G19: =(GOLD!G19)+(SILVER!G19)+(Platinum!G19) -> 89 | H19: =(GOLD!H19)+(SILVER!H19)+(Platinum!H19) -> 493.95 | I19: =(GOLD!I19)+(SILVER!I19)+(Platinum!I19) -> 8645.84 | J19: =(GOLD!J19)+(SILVER!J19)+(Platinum!J19) -> 3442 | ... M19: =(GOLD!M19)+(SILVER!M19)+(Platinum!M19) -> 5559.84 | N19: =K19/I19 -> 0.35693466
B20: 46204 | C20: =(GOLD!C20)+(SILVER!C20)+(Platinum!C20) -> 0 | D20: =(GOLD!D20)+(SILVER!D20)+(Platinum!D20) -> 0 | E20: =(GOLD!E20)+(SILVER!E20)+(Platinum!E20) -> 0 | F20: =(GOLD!F20)+(SILVER!F20)+(Platinum!F20) -> 0 | G20: =(GOLD!G20)+(SILVER!G20)+(Platinum!G20) -> 0 | H20: =(GOLD!H20)+(SILVER!H20)+(Platinum!H20) -> 0 | I20: =(GOLD!I20)+(SILVER!I20)+(Platinum!I20) -> 0 | M20: =(GOLD!M20)+(SILVER!M20)+(Platinum!M20) -> 0
B21: 46235 | C21: =(GOLD!C21)+(SILVER!C21)+(Platinum!C21) -> 0 | D21: =(GOLD!D21)+(SILVER!D21)+(Platinum!D21) -> 0 | E21: =(GOLD!E21)+(SILVER!E21)+(Platinum!E21) -> 0 | F21: =(GOLD!F21)+(SILVER!F21)+(Platinum!F21) -> 0 | G21: =(GOLD!G21)+(SILVER!G21)+(Platinum!G21) -> 0 | H21: =(GOLD!H21)+(SILVER!H21)+(Platinum!H21) -> 0 | I21: =(GOLD!I21)+(SILVER!I21)+(Platinum!I21) -> 0 | M21: =(GOLD!M21)+(SILVER!M21)+(Platinum!M21) -> 0
B22: 46266 | C22: =(GOLD!C22)+(SILVER!C22)+(Platinum!C22) -> 0 | D22: =(GOLD!D22)+(SILVER!D22)+(Platinum!D22) -> 0 | E22: =(GOLD!E22)+(SILVER!E22)+(Platinum!E22) -> 0 | F22: =(GOLD!F22)+(SILVER!F22)+(Platinum!F22) -> 0 | G22: =(GOLD!G22)+(SILVER!G22)+(Platinum!G22) -> 0 | H22: =(GOLD!H22)+(SILVER!H22)+(Platinum!H22) -> 0 | I22: =(GOLD!I22)+(SILVER!I22)+(Platinum!I22) -> 0 | M22: =(GOLD!M22)+(SILVER!M22)+(Platinum!M22) -> 0
B23: 46296 | C23: =(GOLD!C23)+(SILVER!C23)+(Platinum!C23) -> 0 | D23: =(GOLD!D23)+(SILVER!D23)+(Platinum!D23) -> 0 | E23: =(GOLD!E23)+(SILVER!E23)+(Platinum!E23) -> 0 | F23: =(GOLD!F23)+(SILVER!F23)+(Platinum!F23) -> 0 | G23: =(GOLD!G23)+(SILVER!G23)+(Platinum!G23) -> 0 | H23: =(GOLD!H23)+(SILVER!H23)+(Platinum!H23) -> 0 | I23: =(GOLD!I23)+(SILVER!I23) -> 0 | M23: =(GOLD!M23)+(SILVER!M23)+(Platinum!M23) -> 0
B25: Averages | C25: =AVERAGEIF(C12:C23,">0") -> 50 | D25: =AVERAGEIF(D12:D23,">0") -> 16 | E25: =AVERAGEIF(E12:E23,">0") -> 4.5 | F25: =AVERAGEIF(F12:F23,">0") -> 18.5 | G25: =AVERAGEIF(G12:G23,">0") -> 89 | H25: =SUM(H11:H23) -> 3951.6 | I25: =SUM(I11:I23) -> 69442.52 | J25: =SUM(J11:J23) -> 93710.73 | K25: =SUM(K11:K23) -> 52130.77 | L25: =SUM(L12:L23) -> 174 | M25: =SUM(M12:M23) -> 17311.75 | N25: =K25/I25 -> 0.75070389
J27: Important Year to Date Data
J28: Average Claim Submitted | N28: =J25/L25 -> 538.56741
J29: Average Reimbursement | N29: =K25/L25 -> 299.60213
J30: Average Number of Claims per Employee per Year | N30: =((L25/COUNTIF(G12:G23,">0"))*12)/G25 -> 2.9325843
J31: Average Reimbursement % of Submitted Charges | N31: =K25/J25 -> 0.55629457
J32: Average Claim Paid per Employee per Month | N32: =K25/G25/(COUNTIF(G12:G23,">0")) -> 73.217374
J35: Prior Year Data
J36: Average Claim Submitted | N36: 461.65
J37: Average Reimbursement | N37: 326.26
J38: Average Number of Claims per Employee per Year | N38: 2.76
J39: Average Reimbursement % of Submitted Charges | N39: 0.7067
J40: Average Claim Paid per Employee per Month | N40: 75.04
J41: Surplus (Deficit) | N41: 449.9
B43: Important Note: This report reflects claims paid and mailed as of the end of each month. It does not include claims incurred and not yet processed or paid. There are also ongoing adjustments to an employer's benefit account such as corrected claim checks, checks not cashed and claims processed but not yet released due to Simple waiting on the funding of the claims account by the employer. Also, adjustments or corrections to employee enrollments will affect the actual outcomes. Finally, an employer may have deposited more or less to the claims bank account than shown in the budgeted claims column.

Sheet GOLD
B1: =Summary!B1 -> Mountainseed Appraisal Management, LLC.
B2: =Summary!B2 -> Monthly Performance Report - Budgeted vs Actual Claims Paid
G3: Plan Year: | H3: =Summary!H3 -> 45962 | I3: through | J3: =Summary!J3 -> 46326
B5: Group ID: | D5: =Summary!D5 -> S480 | K5: Plan Name: | M5: Gold Plan
B6: Coverage: | D6: Dental | K6: Plan ID: | M6: S480DEN GOLD
B8: ENROLLMENT | H8: ADMIN | I8: CLAIMS | M8: PROFIT OR LOSS
M9: Surplus/ | N9: Loss
B10: Mon, Yr | C10: EE | D10: ES | E10: EC | F10: EF | G10: Total | H10: Costs | I10: Budgeted | J10: Submitted | K10: Paid | L10: Number | M10: Deficit | N10: Ratio
B12: 45962 | C12: 21 | D12: 12 | E12: 3 | F12: 10 | G12: =SUM(C12:F12) -> 46 | H12: =(C12*$E$29)+(D12*$E$30)+(E12*$E$31)+(F12*$E$32) -> 255.3 | I12: =(C12*$C$29)+(D12*$C$30)+(E12*$C$31)+(F12*$C$32) -> 4239.8 | J12: 0 | K12: 0 | L12: 0 | M12: =I12-K12 -> 4239.8 | N12: =K12/I12 -> 0
B13: 45992 | C13: 21 | D13: 12 | E13: 3 | F13: 10 | G13: =SUM(C13:F13) -> 46 | H13: =(C13*$E$29)+(D13*$E$30)+(E13*$E$31)+(F13*$E$32) -> 255.3 | I13: =(C13*$C$29)+(D13*$C$30)+(E13*$C$31)+(F13*$C$32) -> 4239.8 | J13: 14268.39 | K13: 9081.83 | L13: 31 | M13: =I13-K13 -> -4842.03 | N13: =K13/I13 -> 2.1420421
B14: 46023 | C14: 21 | D14: 12 | E14: 3 | F14: 10 | G14: =SUM(C14:F14) -> 46 | H14: =(C14*$E$29)+(D14*$E$30)+(E14*$E$31)+(F14*$E$32) -> 255.3 | I14: =(C14*$C$29)+(D14*$C$30)+(E14*$C$31)+(F14*$C$32) -> 4239.8 | J14: 4336.2 | K14: 2202.44 | L14: 6 | M14: =I14-K14 -> 2037.36 | N14: =K14/I14 -> 0.5194679
B15: 46054 | C15: 19 | D15: 12 | E15: 3 | F15: 9 | G15: =SUM(C15:F15) -> 43 | H15: =(C15*$E$29)+(D15*$E$30)+(E15*$E$31)+(F15*$E$32) -> 238.65 | I15: =(C15*$C$29)+(D15*$C$30)+(E15*$C$31)+(F15*$C$32) -> 3994.3 | J15: 3302 | K15: 2062.8 | L15: 8 | M15: =I15-K15 -> 1931.5 | N15: =K15/I15 -> 0.51643592
B16: 46082 | C16: 20 | D16: 12 | E16: 3 | F16: 9 | G16: =SUM(C16:F16) -> 44 | H16: =(C16*$E$29)+(D16*$E$30)+(E16*$E$31)+(F16*$E$32) -> 244.2 | I16: =(C16*$C$29)+(D16*$C$30)+(E16*$C$31)+(F16*$C$32) -> 4051.55 | J16: 5501.09 | K16: 3127.92 | L16: 11 | M16: =I16-K16 -> 923.63 | N16: =K16/I16 -> 0.77203046
B17: 46113 | C17: 20 | D17: 12 | E17: 3 | F17: 9 | G17: =SUM(C17:F17) -> 44 | H17: =(C17*$E$29)+(D17*$E$30)+(E17*$E$31)+(F17*$E$32) -> 244.2 | I17: =(C17*$C$29)+(D17*$C$30)+(E17*$C$31)+(F17*$C$32) -> 4051.55 | J17: 20224.5 | K17: 8873.3 | L17: 31 | M17: =I17-K17 -> -4821.75 | N17: =K17/I17 -> 2.1901001
B18: 46143 | C18: 20 | D18: 12 | E18: 3 | F18: 9 | G18: =SUM(C18:F18) -> 44 | H18: =(C18*$E$29)+(D18*$E$30)+(E18*$E$31)+(F18*$E$32) -> 244.2 | I18: =(C18*$C$29)+(D18*$C$30)+(E18*$C$31)+(F18*$C$32) -> 4051.55 | J18: 10007 | K18: 5422 | L18: 24 | M18: =I18-K18 -> -1370.45 | N18: =K18/I18 -> 1.3382533
B19: 46174 | C19: 20 | D19: 12 | E19: 3 | F19: 9 | G19: =SUM(C19:F19) -> 44 | H19: =(C19*$E$29)+(D19*$E$30)+(E19*$E$31)+(F19*$E$32) -> 244.2 | I19: =(C19*$C$29)+(D19*$C$30)+(E19*$C$31)+(F19*$C$32) -> 4051.55 | J19: 1989 | K19: 1747.1 | L19: 8 | M19: =I19-K19 -> 2304.45 | N19: =K19/I19 -> 0.43121768
B20: 46204 | G20: =SUM(C20:F20) -> 0 | H20: =(C20*$E$29)+(D20*$E$30)+(E20*$E$31)+(F20*$E$32) -> 0 | I20: =(C20*$C$29)+(D20*$C$30)+(E20*$C$31)+(F20*$C$32) -> 0 | M20: =I20-K20 -> 0
B21: 46235 | G21: =SUM(C21:F21) -> 0 | H21: =(C21*$E$29)+(D21*$E$30)+(E21*$E$31)+(F21*$E$32) -> 0 | I21: =(C21*$C$29)+(D21*$C$30)+(E21*$C$31)+(F21*$C$32) -> 0 | M21: =I21-K21 -> 0
B22: 46266 | G22: =SUM(C22:F22) -> 0 | H22: =(C22*$E$29)+(D22*$E$30)+(E22*$E$31)+(F22*$E$32) -> 0 | I22: =(C22*$C$29)+(D22*$C$30)+(E22*$C$31)+(F22*$C$32) -> 0 | M22: =I22-K22 -> 0
B23: 46296 | G23: =SUM(C23:F23) -> 0 | H23: =(C23*$E$29)+(D23*$E$30)+(E23*$E$31)+(F23*$E$32) -> 0 | I23: =(C23*$C$29)+(D23*$C$30)+(E23*$C$31)+(F23*$C$32) -> 0 | M23: =I23-K23 -> 0
B25: Averages | C25: =AVERAGEIF(C12:C23,">0") -> 20.25 | D25: =AVERAGEIF(D12:D23,">0") -> 12 | E25: =AVERAGEIF(E12:E23,">0") -> 3 | F25: =AVERAGEIF(F12:F23,">0") -> 9.375 | G25: =AVERAGEIF(G12:G23,">0") -> 44.625 | H25: =SUM(H11:H23) -> 1981.35 | I25: =SUM(I11:I23) -> 32919.9 | J25: =SUM(J11:J23) -> 59628.18 | K25: =SUM(K11:K23) -> 32517.39 | L25: =SUM(L12:L23) -> 119 | M25: =SUM(M12:M23) -> 402.51 | N25: =K25/I25 -> 0.98777305
B27: Plan Information | J27: Important Year to Date Data
C28: Claims | E28: Administration | G28: Total | J28: Average Claim Submitted | N28: =J25/L25 -> 501.07714
B29: EE Only | C29: 57.25 | E29: 5.55 | G29: =C29+E29 -> 62.8 | J29: Average Reimbursement | N29: =K25/L25 -> 273.25538
B30: =IF(D10="E+1","EE & One","EE & Spouse") -> EE & Spouse | C30: 114.5 | E30: 5.55 | G30: =C30+E30 -> 120.05 | J30: Average Number of Claims per Employee per Year | N30: =((L25/COUNTIF(G12:G23,">0"))*12)/G25 -> 4
B31: EE & Children | C31: 117.85 | E31: 5.55 | G31: =C31+E31 -> 123.4 | J31: Average Reimbursement % of Submitted Charges | N31: =K25/J25 -> 0.54533595
B32: EE & Family | C32: 131 | E32: 5.55 | G32: =C32+E32 -> 136.55 | J32: Average Claim Paid per Employee per Month | N32: =K25/G25/(COUNTIF(G12:G23,">0")) -> 91.085126
B35: Plan Design | J35: Prior Year Data
B36: 100% OF THE FIRST $400 | J36: Average Claim Submitted | N36: 474.04
B37: 60% OF THE REMAINING BALANCE OF MAXIMUM | J37: Average Reimbursement | N37: 334.29
B38: Ortho is covered for Adults & Children in plan above with a | J38: Average Number of Claims per Employee per Year | N38: 3.39
B39: Lifetime maximum of $1,500 | J39: Average Reimbursement % of Submitted Charges | N39: 0.7052
B40: Plan Year Maximum $2,000 | J40: Average Claim Paid per Employee per Month | N40: 94.38
J41: Surplus (Deficit) | N41: -7409.76
B43: Important Note: This report reflects claims paid and mailed as of the end of each month. It does not include claims incurred and not yet processed or paid. There are also ongoing adjustments to an employer's benefit account such as corrected claim checks, checks not cashed and claims processed but not yet released due to Simple waiting on the funding of the claims account by the employer. Also, adjustments or corrections to employee enrollments will affect the actual outcomes. Finally, an employer may have deposited more or less to the claims bank account than shown in the budgeted claims column.

Sheet Platinum
B1: =Summary!B1 -> Mountainseed Appraisal Management, LLC.
B2: =Summary!B2 -> Monthly Performance Report - Budgeted vs Actual Claims Paid
G3: Plan Year: | H3: =Summary!H3 -> 45962 | I3: through | J3: =Summary!J3 -> 46326
B5: Group ID: | D5: =Summary!D5 -> S480 | K5: Plan Name: | M5: Premium
B6: Coverage: | D6: Dental | K6: Plan ID: | M6: S480DEN PLATINUM
B8: ENROLLMENT | H8: ADMIN | I8: CLAIMS | M8: PROFIT OR LOSS
M9: Surplus/ | N9: Loss
B10: Mon, Yr | C10: EE | D10: ES | E10: EC | F10: EF | G10: Total | H10: Costs | I10: Budgeted | J10: Submitted | K10: Paid | L10: Number | M10: Deficit | N10: Ratio
B12: =Summary!B12 -> 45962 | C12: 11 | D12: 1 | E12: 0 | F12: 7 | G12: =SUM(C12:F12) -> 19 | H12: =(C12*$E$29)+(D12*$E$30)+(E12*$E$31)+(F12*$E$32) -> 105.45 | I12: =(C12*$C$29)+(D12*$C$30)+(E12*$C$31)+(F12*$C$32) -> 3851.96 | J12: 0 | K12: 0 | L12: 0 | M12: =I12-K12 -> 3851.96 | N12: =K12/I12 -> 0
B13: =Summary!B13 -> 45992 | C13: 11 | D13: 1 | E13: 0 | F13: 4 | G13: =SUM(C13:F13) -> 16 | H13: =(C13*$E$29)+(D13*$E$30)+(E13*$E$31)+(F13*$E$32) -> 88.8 | I13: =(C13*$C$29)+(D13*$C$30)+(E13*$C$31)+(F13*$C$32) -> 2790.17 | J13: 3996 | K13: 2939 | L13: 5 | M13: =I13-K13 -> -148.83 | N13: =K13/I13 -> 1.0533408
B14: =Summary!B14 -> 46023 | C14: 11 | D14: 1 | F14: =1+3 -> 4 | G14: =SUM(C14:F14) -> 16 | H14: =(C14*$E$29)+(D14*$E$30)+(E14*$E$31)+(F14*$E$32) -> 88.8 | I14: =(C14*$C$29)+(D14*$C$30)+(E14*$C$31)+(F14*$C$32) -> 2790.17 | J14: 95 | K14: 95 | L14: 1 | M14: =I14-K14 -> 2695.17 | N14: =K14/I14 -> 0.034048105
B15: =Summary!B15 -> 46054 | C15: 11 | D15: 1 | F15: =1+2 -> 3 | G15: =SUM(C15:F15) -> 15 | H15: =(C15*$E$29)+(D15*$E$30)+(E15*$E$31)+(F15*$E$32) -> 83.25 | I15: =(C15*$C$29)+(D15*$C$30)+(E15*$C$31)+(F15*$C$32) -> 2436.24 | J15: 5900 | K15: 3669.6 | L15: 2 | M15: =I15-K15 -> -1233.36 | N15: =K15/I15 -> 1.5062555
B16: =Summary!B16 -> 46082 | C16: 11 | D16: 1 | E16: 1 | F16: =1+2 -> 3 | G16: =SUM(C16:F16) -> 16 | H16: =(C16*$E$29)+(D16*$E$30)+(E16*$E$31)+(F16*$E$32) -> 88.8 | I16: =(C16*$C$29)+(D16*$C$30)+(E16*$C$31)+(F16*$C$32) -> 2657.81 | J16: 1719 | K16: 1003 | L16: 3 | M16: =I16-K16 -> 1654.81 | N16: =K16/I16 -> 0.37737837
B17: =Summary!B17 -> 46113 | C17: 11 | D17: 1 | E17: 1 | F17: 3 | G17: =SUM(C17:F17) -> 16 | H17: =(C17*$E$29)+(D17*$E$30)+(E17*$E$31)+(F17*$E$32) -> 88.8 | I17: =(C17*$C$29)+(D17*$C$30)+(E17*$C$31)+(F17*$C$32) -> 2657.81 | J17: 4599 | K17: 2293 | L17: 9 | M17: =I17-K17 -> 364.81 | N17: =K17/I17 -> 0.86274038
B18: =Summary!B18 -> 46143 | C18: 11 | D18: 1 | E18: 1 | F18: 3 | G18: =SUM(C18:F18) -> 16 | H18: =(C18*$E$29)+(D18*$E$30)+(E18*$E$31)+(F18*$E$32) -> 88.8 | I18: =(C18*$C$29)+(D18*$C$30)+(E18*$C$31)+(F18*$C$32) -> 2657.81 | J18: 4947 | K18: 2626 | L18: 5 | M18: =I18-K18 -> 31.81 | N18: =K18/I18 -> 0.9880315
B19: =Summary!B19 -> 46174 | C19: 11 | D19: 1 | E19: 1 | F19: 3 | G19: =SUM(C19:F19) -> 16 | H19: =(C19*$E$29)+(D19*$E$30)+(E19*$E$31)+(F19*$E$32) -> 88.8 | I19: =(C19*$C$29)+(D19*$C$30)+(E19*$C$31)+(F19*$C$32) -> 2657.81 | J19: 448 | K19: 446.4 | L19: 1 | M19: =I19-K19 -> 2211.41 | N19: =K19/I19 -> 0.16795783
B20: =Summary!B20 -> 46204 | G20: =SUM(C20:F20) -> 0 | H20: =(C20*$E$29)+(D20*$E$30)+(E20*$E$31)+(F20*$E$32) -> 0 | I20: =(C20*$C$29)+(D20*$C$30)+(E20*$C$31)+(F20*$C$32) -> 0 | M20: =I20-K20 -> 0
B21: =Summary!B21 -> 46235 | G21: =SUM(C21:F21) -> 0 | H21: =(C21*$E$29)+(D21*$E$30)+(E21*$E$31)+(F21*$E$32) -> 0 | I21: =(C21*$C$29)+(D21*$C$30)+(E21*$C$31)+(F21*$C$32) -> 0 | M21: =I21-K21 -> 0
B22: =Summary!B22 -> 46266 | G22: =SUM(C22:F22) -> 0 | H22: =(C22*$E$29)+(D22*$E$30)+(E22*$E$31)+(F22*$E$32) -> 0 | I22: =(C22*$C$29)+(D22*$C$30)+(E22*$C$31)+(F22*$C$32) -> 0 | M22: =I22-K22 -> 0
B23: =Summary!B23 -> 46296 | G23: =SUM(C23:F23) -> 0 | H23: =(C23*$E$29)+(D23*$E$30)+(E23*$E$31)+(F23*$E$32) -> 0 | I23: =(C23*$C$29)+(D23*$C$30)+(E23*$C$31)+(F23*$C$32) -> 0 | M23: =I23-K23 -> 0
B25: Averages | C25: =AVERAGEIF(C12:C23,">0") -> 11 | D25: =AVERAGEIF(D12:D23,">0") -> 1 | E25: =AVERAGEIF(E12:E23,">0") -> 1 | F25: =AVERAGEIF(F12:F23,">0") -> 3.75 | G25: =AVERAGEIF(G12:G23,">0") -> 16.25 | H25: =SUM(H11:H23) -> 721.5 | I25: =SUM(I11:I23) -> 22499.78 | J25: =SUM(J11:J23) -> 21704 | K25: =SUM(K11:K23) -> 13072 | L25: =SUM(L12:L23) -> 26 | M25: =SUM(M12:M23) -> 9427.78 | N25: =K25/I25 -> 0.58098346
B27: Plan Information | J27: Important Year to Date Data
C28: Claims | E28: Administration | G28: Total | J28: Average Claim Submitted | N28: =J25/L25 -> 834.76923
B29: EE Only | C29: 105.65 | D29: =IF($A29="s",VLOOKUP("Print",'[1]Plan Input Form'!$C$6:$L$97,14),"") | E29: 5.55 | F29: =IF($A29="s",VLOOKUP("Print",'[1]Plan Input Form'!$C$6:$L$97,14),"") | G29: =C29+E29 -> 111.2 | J29: Average Reimbursement | N29: =K25/L25 -> 502.76923
B30: =IF(D10="E+1","EE & One","EE & Spouse") -> EE & Spouse | C30: 212.3 | D30: =IF($A30="s",VLOOKUP("Print",'[1]Plan Input Form'!$C$6:$L$97,14),"") | E30: 5.55 | F30: =IF($A30="s",VLOOKUP("Print",'[1]Plan Input Form'!$C$6:$L$97,14),"") | G30: =C30+E30 -> 217.85 | J30: Average Number of Claims per Employee per Year | N30: =((L25/COUNTIF(G12:G23,">0"))*12)/G25 -> 2.4
B31: EE & Children | C31: 221.57 | D31: =IF($A31="s",VLOOKUP("Print",'[1]Plan Input Form'!$C$6:$L$97,14),"") | E31: 5.55 | F31: =IF($A31="s",VLOOKUP("Print",'[1]Plan Input Form'!$C$6:$L$97,14),"") | G31: =C31+E31 -> 227.12 | J31: Average Reimbursement % of Submitted Charges | N31: =K25/J25 -> 0.60228529
B32: EE & Family | C32: 353.93 | D32: =IF($A32="s",VLOOKUP("Print",'[1]Plan Input Form'!$C$6:$L$97,14),"") | E32: 5.55 | F32: =IF($A32="s",VLOOKUP("Print",'[1]Plan Input Form'!$C$6:$L$97,14),"") | G32: =C32+E32 -> 359.48 | J32: Average Claim Paid per Employee per Month | N32: =K25/G25/(COUNTIF(G12:G23,">0")) -> 100.55385
B35: Plan Design | J35: Prior Year Data
B36: 100% of the first $600 | J36: Average Claim Submitted | N36: N/A
B37: 60% of the remaining maximum | J37: Average Reimbursement | N37: 0
B38: Ortho is covered for Adults and Children | J38: Average Number of Claims per Employee per Year | N38: 0
B39: Annual Maximum Amount $3,000 | J39: Average Reimbursement % of Submitted Charges | N39: 0
B40: Assignment of Benefits | J40: Average Claim Paid per Employee per Month | N40: 0
J41: Surplus (Deficit) | N41: 0
B43: Important Note: This report reflects claims paid and mailed as of the end of each month. It does not include claims incurred and not yet processed or paid. There are also ongoing adjustments to an employer's benefit account such as corrected claim checks, checks not cashed and claims processed but not yet released due to Simple waiting on the funding of the claims account by the employer. Also, adjustments or corrections to employee enrollments will affect the actual outcomes. Finally, an employer may have deposited more or less to the claims bank account than shown in the budgeted claims column.

Sheet SILVER
B1: =Summary!B1 -> Mountainseed Appraisal Management, LLC.
B2: =Summary!B2 -> Monthly Performance Report - Budgeted vs Actual Claims Paid
G3: Plan Year: | H3: =Summary!H3 -> 45962 | I3: through | J3: =Summary!J3 -> 46326
B5: Group ID: | D5: =Summary!D5 -> S480 | K5: Plan Name: | M5: Premium
B6: Coverage: | D6: Dental | K6: Plan ID: | M6: S480DEN SILVER
B8: ENROLLMENT | H8: ADMIN | I8: CLAIMS | M8: PROFIT OR LOSS
M9: Surplus/ | N9: Loss
B10: Mon, Yr | C10: EE | D10: ES | E10: EC | F10: EF | G10: Total | H10: Costs | I10: Budgeted | J10: Submitted | K10: Paid | L10: Number | M10: Deficit | N10: Ratio
B12: =Summary!B12 -> 45962 | C12: 19 | D12: 3 | E12: 1 | F12: 4 | G12: =SUM(C12:F12) -> 27 | H12: =(C12*$E$29)+(D12*$E$30)+(E12*$E$31)+(F12*$E$32) -> 149.85 | I12: =(C12*$C$29)+(D12*$C$30)+(E12*$C$31)+(F12*$C$32) -> 1582.48 | J12: 0 | K12: 0 | L12: 0 | M12: =I12-K12 -> 1582.48 | N12: =K12/I12 -> 0
B13: =Summary!B13 -> 45992 | C13: 19 | D13: 3 | E13: 1 | F13: 5 | G13: =SUM(C13:F13) -> 28 | H13: =(C13*$E$29)+(D13*$E$30)+(E13*$E$31)+(F13*$E$32) -> 155.4 | I13: =(C13*$C$29)+(D13*$C$30)+(E13*$C$31)+(F13*$C$32) -> 1713.48 | J13: 0 | K13: 0 | L13: 0 | M13: =I13-K13 -> 1713.48 | N13: =K13/I13 -> 0
B14: =Summary!B14 -> 46023 | C14: 19 | D14: 3 | E14: 1 | F14: 5 | G14: =SUM(C14:F14) -> 28 | H14: =(C14*$E$29)+(D14*$E$30)+(E14*$E$31)+(F14*$E$32) -> 155.4 | I14: =(C14*$C$29)+(D14*$C$30)+(E14*$C$31)+(F14*$C$32) -> 1713.48 | J14: 250 | K14: 250 | L14: 1 | M14: =I14-K14 -> 1463.48 | N14: =K14/I14 -> 0.14590191
B15: =Summary!B15 -> 46054 | C15: 18 | D15: 3 | E15: 1 | F15: 5 | G15: =SUM(C15:F15) -> 27 | H15: =(C15*$E$29)+(D15*$E$30)+(E15*$E$31)+(F15*$E$32) -> 149.85 | I15: =(C15*$C$29)+(D15*$C$30)+(E15*$C$31)+(F15*$C$32) -> 1674.48 | J15: 0 | K15: 0 | L15: 0 | M15: =I15-K15 -> 1674.48 | N15: =K15/I15 -> 0
B16: =Summary!B16 -> 46082 | C16: 19 | D16: 3 | E16: 1 | F16: 5 | G16: =SUM(C16:F16) -> 28 | H16: =(C16*$E$29)+(D16*$E$30)+(E16*$E$31)+(F16*$E$32) -> 155.4 | I16: =(C16*$C$29)+(D16*$C$30)+(E16*$C$31)+(F16*$C$32) -> 1713.48 | J16: 1551 | K16: 925.5 | L16: 2 | M16: =I16-K16 -> 787.98 | N16: =K16/I16 -> 0.54012886
B17: =Summary!B17 -> 46113 | C17: 19 | D17: 3 | E17: 1 | F17: 6 | G17: =SUM(C17:F17) -> 29 | H17: =(C17*$E$29)+(D17*$E$30)+(E17*$E$31)+(F17*$E$32) -> 160.95 | I17: =(C17*$C$29)+(D17*$C$30)+(E17*$C$31)+(F17*$C$32) -> 1844.48 | J17: 7726.91 | K17: 4011.96 | L17: 20 | M17: =I17-K17 -> -2167.48 | N17: =K17/I17 -> 2.1751171
B18: =Summary!B18 -> 46143 | C18: 19 | D18: 3 | E18: 1 | F18: 6 | G18: =SUM(C18:F18) -> 29 | H18: =(C18*$E$29)+(D18*$E$30)+(E18*$E$31)+(F18*$E$32) -> 160.95 | I18: =(C18*$C$29)+(D18*$C$30)+(E18*$C$31)+(F18*$C$32) -> 1844.48 | J18: 1845.64 | K18: 461.42 | L18: 2 | M18: =I18-K18 -> 1383.06 | N18: =K18/I18 -> 0.25016265
B19: =Summary!B19 -> 46174 | C19: 18 | D19: 3 | E19: 1 | F19: 7 | G19: =SUM(C19:F19) -> 29 | H19: =(C19*$E$29)+(D19*$E$30)+(E19*$E$31)+(F19*$E$32) -> 160.95 | I19: =(C19*$C$29)+(D19*$C$30)+(E19*$C$31)+(F19*$C$32) -> 1936.48 | J19: 1005 | K19: 892.5 | L19: 4 | M19: =I19-K19 -> 1043.98 | N19: =K19/I19 -> 0.4608878
B20: =Summary!B20 -> 46204 | G20: =SUM(C20:F20) -> 0 | H20: =(C20*$E$29)+(D20*$E$30)+(E20*$E$31)+(F20*$E$32) -> 0 | I20: =(C20*$C$29)+(D20*$C$30)+(E20*$C$31)+(F20*$C$32) -> 0 | M20: =I20-K20 -> 0
B21: =Summary!B21 -> 46235 | G21: =SUM(C21:F21) -> 0 | H21: =(C21*$E$29)+(D21*$E$30)+(E21*$E$31)+(F21*$E$32) -> 0 | I21: =(C21*$C$29)+(D21*$C$30)+(E21*$C$31)+(F21*$C$32) -> 0 | M21: =I21-K21 -> 0
B22: =Summary!B22 -> 46266 | G22: =SUM(C22:F22) -> 0 | H22: =(C22*$E$29)+(D22*$E$30)+(E22*$E$31)+(F22*$E$32) -> 0 | I22: =(C22*$C$29)+(D22*$C$30)+(E22*$C$31)+(F22*$C$32) -> 0 | M22: =I22-K22 -> 0
B23: =Summary!B23 -> 46296 | G23: =SUM(C23:F23) -> 0 | H23: =(C23*$E$29)+(D23*$E$30)+(E23*$E$31)+(F23*$E$32) -> 0 | I23: =(C23*$C$29)+(D23*$C$30)+(E23*$C$31)+(F23*$C$32) -> 0 | M23: =I23-K23 -> 0
B25: Averages | C25: =AVERAGEIF(C12:C23,">0") -> 18.75 | D25: =AVERAGEIF(D12:D23,">0") -> 3 | E25: =AVERAGEIF(E12:E23,">0") -> 1 | F25: =AVERAGEIF(F12:F23,">0") -> 5.375 | G25: =AVERAGEIF(G12:G23,">0") -> 28.125 | H25: =SUM(H11:H23) -> 1248.75 | I25: =SUM(I11:I23) -> 14022.84 | J25: =SUM(J11:J23) -> 12378.55 | K25: =SUM(K11:K23) -> 6541.38 | L25: =SUM(L12:L23) -> 29 | M25: =SUM(M12:M23) -> 7481.46 | N25: =K25/I25 -> 0.4664804
B27: Plan Information | J27: Important Year to Date Data
C28: Claims | E28: Administration | G28: Total | J28: Average Claim Submitted | N28: =J25/L25 -> 426.84655
B29: EE Only | C29: 39 | D29: =IF($A29="s",VLOOKUP("Print",'[1]Plan Input Form'!$C$6:$L$97,14),"") | E29: 5.55 | F29: =IF($A29="s",VLOOKUP("Print",'[1]Plan Input Form'!$C$6:$L$97,14),"") | G29: =C29+E29 -> 44.55 | J29: Average Reimbursement | N29: =K25/L25 -> 225.56483
B30: =IF(D10="E+1","EE & One","EE & Spouse") -> EE & Spouse | C30: 79.37 | D30: =IF($A30="s",VLOOKUP("Print",'[1]Plan Input Form'!$C$6:$L$97,14),"") | E30: 5.55 | F30: =IF($A30="s",VLOOKUP("Print",'[1]Plan Input Form'!$C$6:$L$97,14),"") | G30: =C30+E30 -> 84.92 | J30: Average Number of Claims per Employee per Year | N30: =((L25/COUNTIF(G12:G23,">0"))*12)/G25 -> 1.5466667
B31: EE & Children | C31: 79.37 | D31: =IF($A31="s",VLOOKUP("Print",'[1]Plan Input Form'!$C$6:$L$97,14),"") | E31: 5.55 | F31: =IF($A31="s",VLOOKUP("Print",'[1]Plan Input Form'!$C$6:$L$97,14),"") | G31: =C31+E31 -> 84.92 | J31: Average Reimbursement % of Submitted Charges | N31: =K25/J25 -> 0.52844477
B32: EE & Family | C32: 131 | D32: =IF($A32="s",VLOOKUP("Print",'[1]Plan Input Form'!$C$6:$L$97,14),"") | E32: 5.55 | F32: =IF($A32="s",VLOOKUP("Print",'[1]Plan Input Form'!$C$6:$L$97,14),"") | G32: =C32+E32 -> 136.55 | J32: Average Claim Paid per Employee per Month | N32: =K25/G25/(COUNTIF(G12:G23,">0")) -> 29.0728
B35: Plan Design | J35: Prior Year Data
B36: 100% of the first $300 | J36: Average Claim Submitted | N36: 368.56
B37: 50% of the remaining maximum | J37: Average Reimbursement | N37: 244.47
B38: Ortho IS NOT covered for Adults and Children | J38: Average Number of Claims per Employee per Year | N38: 1.15
B39: Annual Maximum Amount $1,000 | J39: Average Reimbursement % of Submitted Charges | N39: 0.6633
B40: Assignment of Benefits | J40: Average Claim Paid per Employee per Month | N40: 23.49
J41: Surplus (Deficit) | N41: 7859.66
B43: Important Note: This report reflects claims paid and mailed as of the end of each month. It does not include claims incurred and not yet processed or paid. There are also ongoing adjustments to an employer's benefit account such as corrected claim checks, checks not cashed and claims processed but not yet released due to Simple waiting on the funding of the claims account by the employer. Also, adjustments or corrections to employee enrollments will affect the actual outcomes. Finally, an employer may have deposited more or less to the claims bank account than shown in the budgeted claims column.

Sheet Dental Acct
C1: =Summary!B1 -> Mountainseed Appraisal Management, LLC.
C2: Dental Plan Year Accounting
D4: Plan Year: | E4: =Summary!H3 -> 45962 | F4: through | H4: =Summary!J3 -> 46326
C6: Group ID: | D6: =Summary!D5 -> S480 | H6: Coverage: | J6: =Summary!D6 -> Dental
C8: Month | D8: Deposit | E8: Plan Expenses | H8: Account Balance | I8: Refund of balance in Account | J8: *Notes
E9: Claims | F9: Admin | G9: Total
C10: Prior Plan Year Ending Balance | H10: 7195.77
C11: =Summary!B12 -> 45962 | D11: 0 | E11: =Summary!K12 -> 0 | F11: =Summary!H12 -> 510.6 | G11: =E11+F11 -> 510.6 | H11: =H10-G11 -> 6685.17
C12: =Summary!B13 -> 45992 | D12: 19520.05 | E12: =Summary!K13 -> 12020.83 | F12: =Summary!H13 -> 499.5 | G12: =E12+F12 -> 12520.33 | H12: =D12-G12 -> 6999.72
C13: =Summary!B14 -> 46023 | E13: =Summary!K14 -> 2547.44 | F13: =Summary!H14 -> 499.5 | G13: =E13+F13 -> 3046.94 | H13: =D13-G13 -> -3046.94
C14: =Summary!B15 -> 46054 | E14: =Summary!K15 -> 5732.4 | F14: =Summary!H15 -> 471.75 | G14: =E14+F14 -> 6204.15 | H14: =D14-G14 -> -6204.15
C15: =Summary!B16 -> 46082 | D15: 8408.45 | E15: =Summary!K16 -> 5056.42 | F15: =Summary!H16 -> 488.4 | G15: =E15+F15 -> 5544.82 | H15: =D15-G15 -> 2863.63
C16: =Summary!B17 -> 46113
C17: =Summary!B18 -> 46143
C18: =Summary!B19 -> 46174
C19: =Summary!B20 -> 46204
C20: =Summary!B21 -> 46235
C21: =Summary!B22 -> 46266 | H21: =D21-G21 -> 0
C22: =Summary!B23 -> 46296 | H22: =D22-G22 -> 0
C24: Total | D24: =SUM(D11:D22) -> 27928.5 | E24: =SUM(E11:E22) -> 25357.09 | F24: =SUM(F11:F22) -> 2469.75 | G24: =SUM(G11:G22) -> 27826.84 | H24: =SUM(H10:H22) -> 14493.2
C27: Note: The above figures do not include claim adjustments.
C28: * Pending claims include claims processed and not yet released for reimbursement due to low account balance.
C29: *Claims may also be pending if funding was received and posted after the final check run for the month.
