Workbook

Sheet Summary
B1: Mahoning County Job & Family Services
B2: Monthly Performance Report - Budgeted vs Actual Claims Paid
G3: Plan Year: | H3: 45839 | I3: through | J3: 46203
H4: Based on a 2 year contract 2025-2027
B5: Group ID: | D5: S474 | K5: Plan Name: | M5: Summary
B6: Coverage: | D6: Dental
B8: ENROLLMENT | H8: ADMIN | I8: CLAIMS | M8: PROFIT OR LOSS
M9: Surplus/ | N9: Loss
B10: Mon, Yr | C10: EE | F10: EF | G10: Total | H10: Costs | I10: Budgeted | J10: Submitted | K10: Paid | L10: Number | M10: Deficit | N10: Ratio
B12: 45839 | C12: =Union!C12+'Non Union'!C12 -> 5 | F12: =Union!F12+'Non Union'!F12 -> 17 | G12: =SUM(C12:F12) -> 22 | H12: =SUM(Union!H12)+('Non Union'!H12) -> 82.5 | I12: =Union!I12+'Non Union'!I12 -> 1184.5 | J12: =Union!J12+'Non Union'!J12 -> 1456 | K12: =Union!K12+'Non Union'!K12 -> 1001.6 | L12: =Union!L12+'Non Union'!L12 -> 7 | M12: =H12+I12-K12 -> 265.4 | N12: =K12/(H12+I12) -> 0.79052881
B13: 45870 | C13: =Union!C13+'Non Union'!C13 -> 5 | F13: =Union!F13+'Non Union'!F13 -> 17 | G13: =SUM(C13:F13) -> 22 | H13: =SUM(Union!H13)+('Non Union'!H13) -> 82.5 | I13: =Union!I13+'Non Union'!I13 -> 1184.5 | J13: =Union!J13+'Non Union'!J13 -> 3961 | K13: =Union!K13+'Non Union'!K13 -> 2778.8 | L13: =Union!L13+'Non Union'!L13 -> 11 | M13: =H13+I13-K13 -> -1511.8 | N13: =K13/(H13+I13) -> 2.1932123
B14: 45901 | C14: =Union!C14+'Non Union'!C14 -> 5 | F14: =Union!F14+'Non Union'!F14 -> 17 | G14: =SUM(C14:F14) -> 22 | H14: =SUM(Union!H14)+('Non Union'!H14) -> 82.5 | I14: =Union!I14+'Non Union'!I14 -> 1184.5 | J14: =Union!J14+'Non Union'!J14 -> 950 | K14: =Union!K14+'Non Union'!K14 -> 875.8 | L14: =Union!L14+'Non Union'!L14 -> 6 | M14: =H14+I14-K14 -> 391.2 | N14: =K14/(H14+I14) -> 0.69123915
B15: 45931 | C15: =Union!C15+'Non Union'!C15 -> 5 | F15: =Union!F15+'Non Union'!F15 -> 18 | G15: =SUM(C15:F15) -> 23 | H15: =SUM(Union!H15)+('Non Union'!H15) -> 86.25 | I15: =Union!I15+'Non Union'!I15 -> 1247.55 | J15: =Union!J15+'Non Union'!J15 -> 2040 | K15: =Union!K15+'Non Union'!K15 -> 1303.1 | L15: =Union!L15+'Non Union'!L15 -> 7 | M15: =H15+I15-K15 -> 30.7 | N15: =K15/(H15+I15) -> 0.97698306
B16: 45962 | C16: =Union!C16+'Non Union'!C16 -> 5 | F16: =Union!F16+'Non Union'!F16 -> 19 | G16: =SUM(C16:F16) -> 24 | H16: =SUM(Union!H16)+('Non Union'!H16) -> 90 | I16: =Union!I16+'Non Union'!I16 -> 1310.6 | J16: =Union!J16+'Non Union'!J16 -> 973 | K16: =Union!K16+'Non Union'!K16 -> 683.7 | L16: =Union!L16+'Non Union'!L16 -> 3 | M16: =H16+I16-K16 -> 716.9 | N16: =K16/(H16+I16) -> 0.48814794
B17: 45992 | C17: =Union!C17+'Non Union'!C17 -> 5 | F17: =Union!F17+'Non Union'!F17 -> 19 | G17: =SUM(C17:F17) -> 24 | H17: =SUM(Union!H17)+('Non Union'!H17) -> 90 | I17: =Union!I17+'Non Union'!I17 -> 1310.6 | J17: =Union!J17+'Non Union'!J17 -> 981 | K17: =Union!K17+'Non Union'!K17 -> 690.1 | L17: =Union!L17+'Non Union'!L17 -> 6 | M17: =H17+I17-K17 -> 710.5 | N17: =K17/(H17+I17) -> 0.49271741
B18: 46023 | C18: =Union!C18+'Non Union'!C18 -> 5 | F18: =Union!F18+'Non Union'!F18 -> 19 | G18: =SUM(C18:F18) -> 24 | H18: =SUM(Union!H18)+('Non Union'!H18) -> 90 | I18: =Union!I18+'Non Union'!I18 -> 1310.6 | J18: =Union!J18+'Non Union'!J18 -> 956 | K18: =Union!K18+'Non Union'!K18 -> 802.7 | L18: =Union!L18+'Non Union'!L18 -> 4 | M18: =H18+I18-K18 -> 597.9 | N18: =K18/(H18+I18) -> 0.57311152
B19: 46054 | C19: =Union!C19+'Non Union'!C19 -> 6 | F19: =Union!F19+'Non Union'!F19 -> 19 | G19: =SUM(C19:F19) -> 25 | H19: =SUM(Union!H19)+('Non Union'!H19) -> 93.75 | I19: =Union!I19+'Non Union'!I19 -> 1333.13 | J19: =Union!J19+'Non Union'!J19 -> 2209 | K19: =Union!K19+'Non Union'!K19 -> 1261 | L19: =Union!L19+'Non Union'!L19 -> 7 | M19: =H19+I19-K19 -> 165.88 | N19: =K19/(H19+I19) -> 0.88374636
B20: 46082 | C20: =Union!C20+'Non Union'!C20 -> 6 | F20: =Union!F20+'Non Union'!F20 -> 18 | G20: =SUM(C20:F20) -> 24 | H20: =SUM(Union!H20)+('Non Union'!H20) -> 90 | I20: =Union!I20+'Non Union'!I20 -> 1270.08 | J20: =Union!J20+'Non Union'!J20 -> 3879 | K20: =Union!K20+'Non Union'!K20 -> 3214.5 | L20: =Union!L20+'Non Union'!L20 -> 17 | M20: =H20+I20-K20 -> -1854.42 | N20: =K20/(H20+I20) -> 2.3634639
B21: 46113 | C21: =Union!C21+'Non Union'!C21 -> 6 | F21: =Union!F21+'Non Union'!F21 -> 18 | G21: =SUM(C21:F21) -> 24 | H21: =SUM(Union!H21)+('Non Union'!H21) -> 90 | I21: =Union!I21+'Non Union'!I21 -> 1270.08 | J21: =Union!J21+'Non Union'!J21 -> 2182 | K21: =Union!K21+'Non Union'!K21 -> 1235 | L21: =Union!L21+'Non Union'!L21 -> 4 | M21: =H21+I21-K21 -> 125.08 | N21: =K21/(H21+I21) -> 0.90803482
B22: 46143 | C22: =Union!C22+'Non Union'!C22 -> 6 | F22: =Union!F22+'Non Union'!F22 -> 18 | G22: =SUM(C22:F22) -> 24 | H22: =SUM(Union!H22)+('Non Union'!H22) -> 90 | I22: =Union!I22+'Non Union'!I22 -> 1270.08 | J22: =Union!J22+'Non Union'!J22 -> 0 | K22: =Union!K22+'Non Union'!K22 -> 0 | L22: =Union!L22+'Non Union'!L22 -> 0 | M22: =H22+I22-K22 -> 1360.08 | N22: =K22/(H22+I22) -> 0
B23: 46174 | C23: =Union!C23+'Non Union'!C23 -> 7 | F23: =Union!F23+'Non Union'!F23 -> 17 | G23: =SUM(C23:F23) -> 24 | H23: =SUM(Union!H23)+('Non Union'!H23) -> 90 | I23: =Union!I23+'Non Union'!I23 -> 1229.56 | J23: =Union!J23+'Non Union'!J23 -> 200 | K23: =Union!K23+'Non Union'!K23 -> 200 | L23: =Union!L23+'Non Union'!L23 -> 1 | M23: =H23+I23-K23 -> 1119.56 | N23: =K23/(H23+I23) -> 0.15156567
B25: Averages | C25: =AVERAGEIF(C12:C17,">0") -> 5 | F25: =AVERAGEIF(F12:F17,">0") -> 17.833333 | G25: =AVERAGEIF(G12:G17,">0") -> 22.833333 | H25: =SUM(H11:H23) -> 1057.5 | I25: =SUM(I11:I23) -> 15105.78 | J25: =SUM(J11:J23) -> 19787 | K25: =SUM(K11:K23) -> 14046.3 | L25: =SUM(L12:L23) -> 73 | M25: =SUM(M12:M23) -> 2116.98 | N25: =IF((H25+I25)>0,K25/(H25+I25),"") -> 0.86902535
J27: Important Year to Date Data
J28: Average Claim Submitted | N28: =J25/L25 -> 271.05479
J29: Average Reimbursement | N29: =K25/L25 -> 192.41507
J30: Average Number of Claims per Employee per Year | N30: =((L25/COUNTIF(G12:G17,">0"))*12)/G25 -> 6.3941606
J31: Average Reimbursement % of Submitted Charges | N31: =K25/J25 -> 0.70987517
J32: Average Claim Paid per Employee per Month | N32: =K25/G25/(COUNTIF(G12:G17,">0")) -> 102.52774
J35: Prior Year Data
J36: Average Claim Submitted | N36: 252.07
J37: Average Reimbursement | N37: 163.09
J38: Average Number of Claims per Employee per Year | N38: 5.19
J39: Average Reimbursement % of Submitted Charges | N39: 0.647
J40: Average Claim Paid per Employee per Month | N40: 70.59
J41: Surplus (Deficit) | N41: 8220.32
B43: Important Note: This report reflects claims paid and mailed as of the end of each month. It does not include claims incurred and not yet processed or paid. There are also ongoing adjustments to an employer's benefit account such as corrected claim checks, checks not cashed and claims processed but not yet released due to Simple waiting on the funding of the claims account by the employer. Also, adjustments or corrections to employee enrollments will affect the actual outcomes. Finally, an employer may have deposited more or less to the claims bank account than shown in the budgeted claims column.

Sheet Union
B1: Mahoning County Job & Family Services
B2: Monthly Performance Report - Budgeted vs Actual Claims Paid
G3: Plan Year: | H3: 45839 | I3: through | J3: 46203
G4: Based on a 2 year contract
B5: Group ID: | D5: S474 | K5: Plan Name: | M5: Union Plan
B6: Coverage: | D6: Dental | K6: Plan ID: | M6: S474DEN UNION
B8: ENROLLMENT | H8: ADMIN | I8: CLAIMS | M8: PROFIT OR LOSS
M9: Surplus/ | N9: Loss
B10: Mon, Yr | C10: EE | F10: EF | G10: Total | H10: Costs | I10: Budgeted | J10: Submitted | K10: Paid | L10: Number | M10: Deficit | N10: Ratio
B12: 45839 | C12: 3 | F12: 9 | G12: =SUM(C12:F12) -> 12 | H12: =(C12*$E$29)+(D12*$E$30)+(E12*$E$31)+(F12*$E$32) -> 45 | I12: =(C12*$C$29)+(D12*$C$30)+(E12*$C$31)+(F12*$C$32) -> 635.04 | J12: 1245 | K12: 896.1 | L12: 6 | M12: =H12+I12-K12 -> -216.06 | N12: =K12/(H12+I12) -> 1.3177166
B13: 45870 | C13: 3 | F13: 9 | G13: =SUM(C13:F13) -> 12 | H13: =(C13*$E$29)+(D13*$E$30)+(E13*$E$31)+(F13*$E$32) -> 45 | I13: =(C13*$C$29)+(D13*$C$30)+(E13*$C$31)+(F13*$C$32) -> 635.04 | J13: 2522 | K13: 1753.1 | L13: 5 | M13: =H13+I13-K13 -> -1073.06 | N13: =K13/(H13+I13) -> 2.5779366
B14: 45901 | C14: 3 | F14: 9 | G14: =SUM(C14:F14) -> 12 | H14: =(C14*$E$29)+(D14*$E$30)+(E14*$E$31)+(F14*$E$32) -> 45 | I14: =(C14*$C$29)+(D14*$C$30)+(E14*$C$31)+(F14*$C$32) -> 635.04 | J14: 545 | K14: 544.8 | L14: 3 | M14: =H14+I14-K14 -> 135.24 | N14: =K14/(H14+I14) -> 0.80112935
B15: 45931 | C15: 3 | F15: 9 | G15: =SUM(C15:F15) -> 12 | H15: =(C15*$E$29)+(D15*$E$30)+(E15*$E$31)+(F15*$E$32) -> 45 | I15: =(C15*$C$29)+(D15*$C$30)+(E15*$C$31)+(F15*$C$32) -> 635.04 | J15: 1402 | K15: 831 | L15: 5 | M15: =H15+I15-K15 -> -150.96 | N15: =K15/(H15+I15) -> 1.2219869
B16: 45962 | C16: 3 | F16: 10 | G16: =SUM(C16:F16) -> 13 | H16: =(C16*$E$29)+(D16*$E$30)+(E16*$E$31)+(F16*$E$32) -> 48.75 | I16: =(C16*$C$29)+(D16*$C$30)+(E16*$C$31)+(F16*$C$32) -> 698.09 | J16: 973 | K16: 683.7 | L16: 3 | M16: =H16+I16-K16 -> 63.14 | N16: =K16/(H16+I16) -> 0.91545713
B17: 45992 | C17: 3 | F17: 10 | G17: =SUM(C17:F17) -> 13 | H17: =(C17*$E$29)+(D17*$E$30)+(E17*$E$31)+(F17*$E$32) -> 48.75 | I17: =(C17*$C$29)+(D17*$C$30)+(E17*$C$31)+(F17*$C$32) -> 698.09 | J17: 756 | K17: 550.9 | L17: 5 | M17: =H17+I17-K17 -> 195.94 | N17: =K17/(H17+I17) -> 0.73764126
B18: 46023 | C18: 3 | F18: 9 | G18: =SUM(C18:F18) -> 12 | H18: =(C18*$E$29)+(D18*$E$30)+(E18*$E$31)+(F18*$E$32) -> 45 | I18: =(C18*$C$29)+(D18*$C$30)+(E18*$C$31)+(F18*$C$32) -> 635.04 | J18: 956 | K18: 802.7 | L18: 4 | M18: =H18+I18-K18 -> -122.66 | N18: =K18/(H18+I18) -> 1.1803717
B19: 46054 | C19: 3 | F19: 9 | G19: =SUM(C19:F19) -> 12 | H19: =(C19*$E$29)+(D19*$E$30)+(E19*$E$31)+(F19*$E$32) -> 45 | I19: =(C19*$C$29)+(D19*$C$30)+(E19*$C$31)+(F19*$C$32) -> 635.04 | J19: 1800 | K19: 962.7 | L19: 5 | M19: =H19+I19-K19 -> -282.66 | N19: =K19/(H19+I19) -> 1.415652
B20: 46082 | C20: 3 | F20: 9 | G20: =SUM(C20:F20) -> 12 | H20: =(C20*$E$29)+(D20*$E$30)+(E20*$E$31)+(F20*$E$32) -> 45 | I20: =(C20*$C$29)+(D20*$C$30)+(E20*$C$31)+(F20*$C$32) -> 635.04 | J20: 1849 | K20: 2199.5 | L20: 11 | M20: =H20+I20-K20 -> -1519.46 | N20: =K20/(H20+I20) -> 3.2343686
B21: 46113 | C21: 3 | F21: 9 | G21: =SUM(C21:F21) -> 12 | H21: =(C21*$E$29)+(D21*$E$30)+(E21*$E$31)+(F21*$E$32) -> 45 | I21: =(C21*$C$29)+(D21*$C$30)+(E21*$C$31)+(F21*$C$32) -> 635.04 | J21: 2012 | K21: 1125 | L21: 3 | M21: =H21+I21-K21 -> -444.96 | N21: =K21/(H21+I21) -> 1.6543145
B22: 46143 | C22: 3 | F22: 9 | G22: =SUM(C22:F22) -> 12 | H22: =(C22*$E$29)+(D22*$E$30)+(E22*$E$31)+(F22*$E$32) -> 45 | I22: =(C22*$C$29)+(D22*$C$30)+(E22*$C$31)+(F22*$C$32) -> 635.04 | J22: 0 | K22: 0 | L22: 0 | M22: =H22+I22-K22 -> 680.04 | N22: =K22/(H22+I22) -> 0
B23: 46174 | C23: 4 | F23: 8 | G23: =SUM(C23:F23) -> 12 | H23: =(C23*$E$29)+(D23*$E$30)+(E23*$E$31)+(F23*$E$32) -> 45 | I23: =(C23*$C$29)+(D23*$C$30)+(E23*$C$31)+(F23*$C$32) -> 594.52 | J23: 200 | K23: 200 | L23: 1 | M23: =H23+I23-K23 -> 439.52 | N23: =K23/(H23+I23) -> 0.31273455
B25: Averages | C25: =AVERAGEIF(C12:C17,">0") -> 3 | F25: =AVERAGEIF(F12:F17,">0") -> 9.3333333 | G25: =AVERAGEIF(G12:G17,">0") -> 12.333333 | H25: =SUM(H11:H23) -> 547.5 | I25: =SUM(I11:I23) -> 7706.06 | J25: =SUM(J11:J23) -> 14260 | K25: =SUM(K11:K23) -> 10549.5 | L25: =SUM(L12:L23) -> 51 | M25: =SUM(M12:M23) -> -2295.94 | N25: =IF((H25+I25)>0,K25/(H25+I25),"") -> 1.2781757
B27: Plan Information | J27: Important Year to Date Data
C28: Claims | E28: Administration | G28: Total | J28: Average Claim Submitted | N28: =J25/L25 -> 279.60784
B29: EE Only | C29: 22.53 | E29: 3.75 | G29: =C29+E29 -> 26.28 | J29: Average Reimbursement | N29: =K25/L25 -> 206.85294
J30: Average Number of Claims per Employee per Year | N30: =((L25/COUNTIF(G12:G17,">0"))*12)/G25 -> 8.2702703
J31: Average Reimbursement % of Submitted Charges | N31: =K25/J25 -> 0.73979663
B32: EE & Family | C32: 63.05 | E32: 3.75 | G32: =C32+E32 -> 66.8 | J32: Average Claim Paid per Employee per Month | N32: =K25/G25/(COUNTIF(G12:G17,">0")) -> 142.56081
B35: Plan Design | J35: Prior Year Data
B36: 100% of the first $200 | J36: Average Claim Submitted | N36: 201.27
B37: 80% of the next $100; 50% of the next $1,440. | J37: Average Reimbursement | N37: 164.12
B38: Ortho covered for Adults and Children (same benefits) | J38: Average Number of Claims per Employee per Year | N38: 4.86
B39: Annual Maximum Amount $1,000 | J39: Average Reimbursement % of Submitted Charges | N39: 0.8155
B40: Assignment of Benefits | J40: Average Claim Paid per Employee per Month | N40: 66.54
J41: Surplus (Deficit) | N41: 4572.57
B43: Important Note: This report reflects claims paid and mailed as of the end of each month. It does not include claims incurred and not yet processed or paid. There are also ongoing adjustments to an employer's benefit account such as corrected claim checks, checks not cashed and claims processed but not yet released due to Simple waiting on the funding of the claims account by the employer. Also, adjustments or corrections to employee enrollments will affect the actual outcomes. Finally, an employer may have deposited more or less to the claims bank account than shown in the budgeted claims column.

Sheet Non Union
B1: Mahoning County Job & Family Services
B2: Monthly Performance Report - Budgeted vs Actual Claims Paid
G3: Plan Year: | H3: 45839 | I3: through | J3: 46203
H4: Based on a 2 year contract 2023-2025
B5: Group ID: | D5: S474 | K5: Plan Name: | M5: Non Union
B6: Coverage: | D6: Dental | K6: Plan ID: | M6: S474DEN NON UNION
B8: ENROLLMENT | H8: ADMIN | I8: CLAIMS | M8: PROFIT OR LOSS
M9: Surplus/ | N9: Loss
B10: Mon, Yr | C10: EE | F10: EF | G10: Total | H10: Costs | I10: Budgeted | J10: Submitted | K10: Paid | L10: Number | M10: Deficit | N10: Ratio
B12: 45839 | C12: 2 | F12: 8 | G12: =SUM(C12:F12) -> 10 | H12: =(C12*$E$29)+(D12*$E$30)+(E12*$E$31)+(F12*$E$32) -> 37.5 | I12: =(C12*$C$29)+(D12*$C$30)+(E12*$C$31)+(F12*$C$32) -> 549.46 | J12: 211 | K12: 105.5 | L12: 1 | M12: =H12+I12-K12 -> 481.46 | N12: =K12/(H12+I12) -> 0.17973968
B13: 45870 | C13: 2 | F13: 8 | G13: =SUM(C13:F13) -> 10 | H13: =(C13*$E$29)+(D13*$E$30)+(E13*$E$31)+(F13*$E$32) -> 37.5 | I13: =(C13*$C$29)+(D13*$C$30)+(E13*$C$31)+(F13*$C$32) -> 549.46 | J13: 1439 | K13: 1025.7 | L13: 6 | M13: =H13+I13-K13 -> -438.74 | N13: =K13/(H13+I13) -> 1.7474785
B14: 45901 | C14: 2 | F14: 8 | G14: =SUM(C14:F14) -> 10 | H14: =(C14*$E$29)+(D14*$E$30)+(E14*$E$31)+(F14*$E$32) -> 37.5 | I14: =(C14*$C$29)+(D14*$C$30)+(E14*$C$31)+(F14*$C$32) -> 549.46 | J14: 405 | K14: 331 | L14: 3 | M14: =H14+I14-K14 -> 255.96 | N14: =K14/(H14+I14) -> 0.56392258
B15: 45931 | C15: 2 | F15: 9 | G15: =SUM(C15:F15) -> 11 | H15: =(C15*$E$29)+(D15*$E$30)+(E15*$E$31)+(F15*$E$32) -> 41.25 | I15: =(C15*$C$29)+(D15*$C$30)+(E15*$C$31)+(F15*$C$32) -> 612.51 | J15: 638 | K15: 472.1 | L15: 2 | M15: =H15+I15-K15 -> 181.66 | N15: =K15/(H15+I15) -> 0.72213045
B16: 45962 | C16: 2 | F16: 9 | G16: =SUM(C16:F16) -> 11 | H16: =(C16*$E$29)+(D16*$E$30)+(E16*$E$31)+(F16*$E$32) -> 41.25 | I16: =(C16*$C$29)+(D16*$C$30)+(E16*$C$31)+(F16*$C$32) -> 612.51 | J16: 0 | K16: 0 | L16: 0 | M16: =H16+I16-K16 -> 653.76 | N16: =K16/(H16+I16) -> 0
B17: 45992 | C17: 2 | F17: 9 | G17: =SUM(C17:F17) -> 11 | H17: =(C17*$E$29)+(D17*$E$30)+(E17*$E$31)+(F17*$E$32) -> 41.25 | I17: =(C17*$C$29)+(D17*$C$30)+(E17*$C$31)+(F17*$C$32) -> 612.51 | J17: 225 | K17: 139.2 | L17: 1 | M17: =H17+I17-K17 -> 514.56 | N17: =K17/(H17+I17) -> 0.21292217
B18: 46023 | C18: 2 | F18: 10 | G18: =SUM(C18:F18) -> 12 | H18: =(C18*$E$29)+(D18*$E$30)+(E18*$E$31)+(F18*$E$32) -> 45 | I18: =(C18*$C$29)+(D18*$C$30)+(E18*$C$31)+(F18*$C$32) -> 675.56 | J18: 0 | K18: 0 | L18: 0 | M18: =H18+I18-K18 -> 720.56 | N18: =K18/(H18+I18) -> 0
B19: 46054 | C19: 3 | F19: 10 | G19: =SUM(C19:F19) -> 13 | H19: =(C19*$E$29)+(D19*$E$30)+(E19*$E$31)+(F19*$E$32) -> 48.75 | I19: =(C19*$C$29)+(D19*$C$30)+(E19*$C$31)+(F19*$C$32) -> 698.09 | J19: 409 | K19: 298.3 | L19: 2 | M19: =H19+I19-K19 -> 448.54 | N19: =K19/(H19+I19) -> 0.39941621
B20: 46082 | C20: 3 | F20: 9 | G20: =SUM(C20:F20) -> 12 | H20: =(C20*$E$29)+(D20*$E$30)+(E20*$E$31)+(F20*$E$32) -> 45 | I20: =(C20*$C$29)+(D20*$C$30)+(E20*$C$31)+(F20*$C$32) -> 635.04 | J20: 2030 | K20: 1015 | L20: 6 | M20: =H20+I20-K20 -> -334.96 | N20: =K20/(H20+I20) -> 1.4925593
B21: 46113 | C21: 3 | F21: 9 | G21: =SUM(C21:F21) -> 12 | H21: =(C21*$E$29)+(D21*$E$30)+(E21*$E$31)+(F21*$E$32) -> 45 | I21: =(C21*$C$29)+(D21*$C$30)+(E21*$C$31)+(F21*$C$32) -> 635.04 | J21: 170 | K21: 110 | L21: 1 | M21: =H21+I21-K21 -> 570.04 | N21: =K21/(H21+I21) -> 0.16175519
B22: 46143 | C22: 3 | F22: 9 | G22: =SUM(C22:F22) -> 12 | H22: =(C22*$E$29)+(D22*$E$30)+(E22*$E$31)+(F22*$E$32) -> 45 | I22: =(C22*$C$29)+(D22*$C$30)+(E22*$C$31)+(F22*$C$32) -> 635.04 | J22: 0 | K22: 0 | L22: 0 | M22: =H22+I22-K22 -> 680.04 | N22: =K22/(H22+I22) -> 0
B23: 46174 | C23: 3 | F23: 9 | G23: =SUM(C23:F23) -> 12 | H23: =(C23*$E$29)+(D23*$E$30)+(E23*$E$31)+(F23*$E$32) -> 45 | I23: =(C23*$C$29)+(D23*$C$30)+(E23*$C$31)+(F23*$C$32) -> 635.04 | J23: 0 | K23: 0 | L23: 0 | M23: =H23+I23-K23 -> 680.04 | N23: =K23/(H23+I23) -> 0
B25: Averages | C25: =AVERAGEIF(C12:C17,">0") -> 2 | F25: =AVERAGEIF(F12:F17,">0") -> 8.5 | G25: =AVERAGEIF(G12:G17,">0") -> 10.5 | H25: =SUM(H11:H23) -> 510 | I25: =SUM(I11:I23) -> 7399.72 | J25: =SUM(J11:J23) -> 5527 | K25: =SUM(K11:K23) -> 3496.8 | L25: =SUM(L12:L23) -> 22 | M25: =SUM(M12:M23) -> 4412.92 | N25: =IF((H25+I25)>0,K25/(H25+I25),"") -> 0.44208897
B27: Plan Information | J27: Important Year to Date Data
C28: Claims | E28: Administration | G28: Total | J28: Average Claim Submitted | N28: =J25/L25 -> 251.22727
B29: EE Only | C29: 22.53 | E29: 3.75 | G29: =C29+E29 -> 26.28 | J29: Average Reimbursement | N29: =K25/L25 -> 158.94545
J30: Average Number of Claims per Employee per Year | N30: =((L25/COUNTIF(G12:G17,">0"))*12)/G25 -> 4.1904762
J31: Average Reimbursement % of Submitted Charges | N31: =K25/J25 -> 0.63267595
B32: EE & Family | C32: 63.05 | E32: 3.75 | G32: =C32+E32 -> 66.8 | J32: Average Claim Paid per Employee per Month | N32: =K25/G25/(COUNTIF(G12:G17,">0")) -> 55.504762
B35: Plan Design | J35: Prior Year Data
B36: 100% of the first $100 | J36: Average Claim Submitted | N36: 306.5
B37: 80% of the next $100; 50% of the next $1,640. | J37: Average Reimbursement | N37: 161.98
B38: Ortho covered for Adults and Children (same benefits) | J38: Average Number of Claims per Employee per Year | N38: 5.6
B39: Annual Maximum Amount $1,000 | J39: Average Reimbursement % of Submitted Charges | N39: 0.5285
B40: Assignment of Benefits | J40: Average Claim Paid per Employee per Month | N40: 75.59
J41: Surplus (Deficit) | N41: 3647.75
B43: Important Note: This report reflects claims paid and mailed as of the end of each month. It does not include claims incurred and not yet processed or paid. There are also ongoing adjustments to an employer's benefit account such as corrected claim checks, checks not cashed and claims processed but not yet released due to Simple waiting on the funding of the claims account by the employer. Also, adjustments or corrections to employee enrollments will affect the actual outcomes. Finally, an employer may have deposited more or less to the claims bank account than shown in the budgeted claims column.
