Workbook

Sheet Summary
B1: Gainesville City School
B2: Monthly Performance Report - Budgeted vs Actual Claims Paid
G3: Plan Year: | H3: 46023 | I3: through | J3: 46387
B5: Group ID: | D5: S29 | K5: Plan Name: | M5: Summary
B6: Coverage: | D6: Dental | K6: Plan ID: | M6: S29DEN
B8: ENROLLMENT | H8: ADMIN | I8: CLAIMS | M8: PROFIT OR LOSS
M9: Surplus/ | N9: Loss
B10: Mon, Yr | C10: EE | D10: ES | F10: EF | G10: Total | H10: Costs | I10: Budgeted | J10: Submitted | K10: Paid | L10: Number | M10: Deficit | N10: Ratio
B12: 46023 | C12: =('Standard 2026'!C12)+'Premium 2026'!C12 -> 286 | D12: ='Standard 2026'!D12+'Premium 2026'!D12 -> 140 | F12: ='Standard 2026'!F12+'Premium 2026'!F12 -> 165 | G12: =SUM(C12:F12) -> 591 | H12: ='Standard 2026'!H12+'Premium 2026'!H12 -> 3073.2 | I12: =VALUE('Standard 2026'!I12)+'Premium 2026'!I12 -> 33836.6 | J12: 0 | K12: 0 | L12: 0 | M12: =I12-K12 -> 33836.6 | N12: =K12/I12 -> 0
B13: 46054 | C13: =('Standard 2026'!C13)+'Premium 2026'!C13 -> 288 | D13: ='Standard 2026'!D13+'Premium 2026'!D13 -> 140 | F13: ='Standard 2026'!F13+'Premium 2026'!F13 -> 163 | G13: =SUM(C13:F13) -> 591 | H13: ='Standard 2026'!H13+'Premium 2026'!H13 -> 3073.2 | I13: =VALUE('Standard 2026'!I13)+'Premium 2026'!I13 -> 33695.99 | J13: =VALUE('Standard 2026'!J13)+'Premium 2026'!J13 -> 45003.13 | K13: =VALUE('Standard 2026'!K13)+'Premium 2026'!K13 -> 23970.15 | L13: =VALUE('Standard 2026'!L13)+'Premium 2026'!L13 -> 85 | M13: =I13-K13 -> 9725.84 | N13: =K13/I13 -> 0.71136506
B14: 46082 | C14: =('Standard 2026'!C14)+'Premium 2026'!C14 -> 289 | D14: ='Standard 2026'!D14+'Premium 2026'!D14 -> 139 | F14: ='Standard 2026'!F14+'Premium 2026'!F14 -> 163 | G14: =SUM(C14:F14) -> 591 | H14: ='Standard 2026'!H14+'Premium 2026'!H14 -> 3073.2 | I14: =VALUE('Standard 2026'!I14)+'Premium 2026'!I14 -> 33649.12 | J14: =VALUE('Standard 2026'!J14)+'Premium 2026'!J14 -> 194327.25 | K14: =VALUE('Standard 2026'!K14)+'Premium 2026'!K14 -> 77883.52 | L14: =VALUE('Standard 2026'!L14)+'Premium 2026'!L14 -> 334 | M14: =I14-K14 -> -44234.4 | N14: =K14/I14 -> 2.3145782
B15: 46113 | C15: =('Standard 2026'!C15)+'Premium 2026'!C15 -> 286 | D15: ='Standard 2026'!D15+'Premium 2026'!D15 -> 139 | F15: ='Standard 2026'!F15+'Premium 2026'!F15 -> 163 | G15: =SUM(C15:F15) -> 588 | H15: ='Standard 2026'!H15+'Premium 2026'!H15 -> 3057.6 | I15: =VALUE('Standard 2026'!I15)+'Premium 2026'!I15 -> 33524.38 | J15: =VALUE('Standard 2026'!J15)+'Premium 2026'!J15 -> 114024.48 | K15: =VALUE('Standard 2026'!K15)+'Premium 2026'!K15 -> 38498.97 | L15: =VALUE('Standard 2026'!L15)+'Premium 2026'!L15 -> 205 | M15: =I15-K15 -> -4974.59 | N15: =K15/I15 -> 1.1483872
B16: 46143 | C16: =('Standard 2026'!C16)+'Premium 2026'!C16 -> 284 | D16: ='Standard 2026'!D16+'Premium 2026'!D16 -> 110 | F16: ='Standard 2026'!F16+'Premium 2026'!F16 -> 160 | G16: =SUM(C16:F16) -> 554 | H16: ='Standard 2026'!H16+'Premium 2026'!H16 -> 2880.8 | I16: =VALUE('Standard 2026'!I16)+'Premium 2026'!I16 -> 31042.46 | J16: =VALUE('Standard 2026'!J16)+'Premium 2026'!J16 -> 87582.38 | K16: =VALUE('Standard 2026'!K16)+'Premium 2026'!K16 -> 40506.99 | L16: =VALUE('Standard 2026'!L16)+'Premium 2026'!L16 -> 201 | M16: =I16-K16 -> -9464.53 | N16: =K16/I16 -> 1.3048898
B17: 46174 | C17: =('Standard 2026'!C17)+'Premium 2026'!C17 -> 283 | D17: ='Standard 2026'!D17+'Premium 2026'!D17 -> 144 | F17: ='Standard 2026'!F17+'Premium 2026'!F17 -> 159 | G17: =SUM(C17:F17) -> 586 | H17: ='Standard 2026'!H17+'Premium 2026'!H17 -> 3047.2 | I17: =VALUE('Standard 2026'!I17)+'Premium 2026'!I17 -> 33323.5 | J17: =VALUE('Standard 2026'!J17)+'Premium 2026'!J17 -> 73496.84 | K17: =VALUE('Standard 2026'!K17)+'Premium 2026'!K17 -> 33455.91 | L17: =VALUE('Standard 2026'!L17)+'Premium 2026'!L17 -> 142 | M17: =I17-K17 -> -132.41 | N17: =K17/I17 -> 1.0039735
B18: 46204
B19: 46235
B20: 46266
B21: 46296
B22: 46327
B23: 46357
B25: Averages | C25: =AVERAGEIF(C12:C23,">0") -> 286 | D25: =AVERAGEIF(D12:D23,">0") -> 135.33333 | F25: =AVERAGEIF(F12:F23,">0") -> 162.16667 | G25: =AVERAGEIF(G12:G23,">0") -> 583.5 | H25: =SUM(H11:H23) -> 18205.2 | I25: =SUM(I11:I23) -> 199072.05 | J25: =SUM(J11:J23) -> 514434.08 | K25: =SUM(K11:K23) -> 214315.54 | L25: =SUM(L12:L23) -> 967 | M25: =SUM(M12:M23) -> -15243.49 | N25: =K25/I25 -> 1.0765727
J27: Important Year to Date Data
J28: Average Claim Submitted | N28: =J25/L25 -> 531.98974
J29: Average Reimbursement | N29: =K25/L25 -> 221.62931
J30: Average Number of Claims per Employee per Year | N30: =((L25/COUNTIF(G12:G23,">0"))*12)/G25 -> 3.3144816
J31: Average Reimbursement % of Submitted Charges | N31: =K25/J25 -> 0.41660448
J32: Average Claim Paid per Employee per Month | N32: =K25/G25/(COUNTIF(G12:G23,">0")) -> 61.215521
J34: Prior Year Data
J35: Average Claim Submitted | N35: 418.44
J36: Average Reimbursement | N36: 262.25
J37: Average Number of Claims per Employee per Year | N37: 2.64
J38: Average Reimbursement % of Submitted Charges | N38: 0.6267
J39: Average Claim Paid per Employee per Month | N39: 57.63
J40: Surplus (Deficit) | N40: 31051.29
B43: Important Note: This report reflects claims paid and mailed as of the end of each month. It does not include claims incurred and not yet processed or paid. There are also ongoing adjustments to an employer's benefit account such as corrected claim checks, checks not cashed and claims processed but not yet released due to Simple waiting on the funding of the claims account by the employer. Also, adjustments or corrections to employee enrollments will affect the actual outcomes. Finally, an employer may have deposited more or less to the claims bank account than shown in the budgeted claims column.

Sheet Standard 2026
B1: Gainesville City Schools
B2: Monthly Performance Report - Budgeted vs Actual Claims Paid
G3: Plan Year: | H3: 46023 | I3: through | J3: 46387
B5: Group ID: | D5: S29 | K5: Plan Name: | M5: Standard
B6: Coverage: | D6: Dental | K6: Plan ID: | M6: 29DEN Standard
B8: ENROLLMENT | H8: ADMIN | I8: CLAIMS | M8: PROFIT OR LOSS
M9: Surplus/ | N9: Loss
B10: Mon, Yr | C10: EE | D10: E+1 | F10: EF | G10: Total | H10: Costs | I10: Budgeted | J10: Submitted | K10: Paid | L10: Number | M10: Deficit | N10: Ratio
B12: =Summary!B12 -> 46023 | C12: 185 | D12: =20+54 -> 74 | F12: 73 | G12: =SUM(C12:F12) -> 332 | H12: =(C12*$E$29)+(D12*$E$30)+(E12*$E$31)+(F12*$E$32) -> 1726.4 | I12: =(C12*$C$29)+(D12*$C$30)+(E12*$C$31)+(F12*$C$32) -> 14492.35 | J12: 0 | K12: 0 | L12: 0 | M12: =I12-K12 -> 14492.35 | N12: =K12/I12 -> 0
B13: =Summary!B13 -> 46054 | C13: 185 | D13: =54+21 -> 75 | F13: 72 | G13: =SUM(C13:F13) -> 332 | H13: =(C13*$E$29)+(D13*$E$30)+(E13*$E$31)+(F13*$E$32) -> 1726.4 | I13: =(C13*$C$29)+(D13*$C$30)+(E13*$C$31)+(F13*$C$32) -> 14464.01 | J13: 12660 | K13: 7708.65 | L13: 35 | M13: =I13-K13 -> 6755.36 | N13: =K13/I13 -> 0.53295386
B14: =Summary!B14 -> 46082 | C14: 186 | D14: =54+21 -> 75 | F14: 72 | G14: =SUM(C14:F14) -> 333 | H14: =(C14*$E$29)+(D14*$E$30)+(E14*$E$31)+(F14*$E$32) -> 1731.6 | I14: =(C14*$C$29)+(D14*$C$30)+(E14*$C$31)+(F14*$C$32) -> 14490.33 | J14: 78330.46 | K14: 32529.45 | L14: 150 | M14: =I14-K14 -> -18039.12 | N14: =K14/I14 -> 2.2449075
B15: =Summary!B15 -> 46113 | C15: 185 | D15: 76 | F15: 72 | G15: =SUM(C15:F15) -> 333 | H15: =(C15*$E$29)+(D15*$E$30)+(E15*$E$31)+(F15*$E$32) -> 1731.6 | I15: =(C15*$C$29)+(D15*$C$30)+(E15*$C$31)+(F15*$C$32) -> 14515.4 | J15: 37758.31 | K15: 13043.08 | L15: 83 | M15: =I15-K15 -> 1472.32 | N15: =K15/I15 -> 0.89856842
B16: =Summary!B16 -> 46143 | C16: 185 | D16: 78 | F16: 69 | G16: =SUM(C16:F16) -> 332 | H16: =(C16*$E$29)+(D16*$E$30)+(E16*$E$31)+(F16*$E$32) -> 1726.4 | I16: =(C16*$C$29)+(D16*$C$30)+(E16*$C$31)+(F16*$C$32) -> 14378.99 | J16: 35798.93 | K16: 15461.84 | L16: 72 | M16: =I16-K16 -> -1082.85 | N16: =K16/I16 -> 1.0753078
B17: =Summary!B17 -> 46174 | C17: 184 | D17: 81 | F17: 69 | G17: =SUM(C17:F17) -> 334 | H17: =(C17*$E$29)+(D17*$E$30)+(E17*$E$31)+(F17*$E$32) -> 1736.8 | I17: =(C17*$C$29)+(D17*$C$30)+(E17*$C$31)+(F17*$C$32) -> 14506.84 | J17: 27988 | K17: 14249.24 | L17: 59 | M17: =I17-K17 -> 257.6 | N17: =K17/I17 -> 0.98224286
B18: =Summary!B18 -> 46204 | G18: =SUM(C18:F18) -> 0 | H18: =(C18*$E$29)+(D18*$E$30)+(E18*$E$31)+(F18*$E$32) -> 0 | I18: =(C18*$C$29)+(D18*$C$30)+(E18*$C$31)+(F18*$C$32) -> 0 | M18: =I18-K18 -> 0
B19: =Summary!B19 -> 46235 | G19: =SUM(C19:F19) -> 0 | H19: =(C19*$E$29)+(D19*$E$30)+(E19*$E$31)+(F19*$E$32) -> 0 | I19: =(C19*$C$29)+(D19*$C$30)+(E19*$C$31)+(F19*$C$32) -> 0 | M19: =I19-K19 -> 0
B20: =Summary!B20 -> 46266 | G20: =SUM(C20:F20) -> 0 | H20: =(C20*$E$29)+(D20*$E$30)+(E20*$E$31)+(F20*$E$32) -> 0 | I20: =(C20*$C$29)+(D20*$C$30)+(E20*$C$31)+(F20*$C$32) -> 0 | M20: =I20-K20 -> 0 | N20: =K20/(H20+I20) -> #DIV/0!
B21: =Summary!B21 -> 46296 | G21: =SUM(C21:F21) -> 0 | H21: =(C21*$E$29)+(D21*$E$30)+(E21*$E$31)+(F21*$E$32) -> 0 | I21: =(C21*$C$29)+(D21*$C$30)+(E21*$C$31)+(F21*$C$32) -> 0 | M21: =I21-K21 -> 0 | N21: =K21/(H21+I21) -> #DIV/0!
B22: =Summary!B22 -> 46327 | G22: =SUM(C22:F22) -> 0 | H22: =(C22*$E$29)+(D22*$E$30)+(E22*$E$31)+(F22*$E$32) -> 0 | I22: =(C22*$C$29)+(D22*$C$30)+(E22*$C$31)+(F22*$C$32) -> 0 | M22: =I22-K22 -> 0 | N22: =K22/(H22+I22) -> #DIV/0!
B23: =Summary!B23 -> 46357 | G23: =SUM(C23:F23) -> 0 | H23: =(C23*$E$29)+(D23*$E$30)+(E23*$E$31)+(F23*$E$32) -> 0 | I23: =(C23*$C$29)+(D23*$C$30)+(E23*$C$31)+(F23*$C$32) -> 0 | M23: =I23-K23 -> 0 | N23: =K23/(H23+I23) -> #DIV/0!
B25: Averages | C25: =AVERAGEIF(C12:C23,">0") -> 185 | D25: =AVERAGEIF(D12:D23,">0") -> 76.5 | F25: =AVERAGEIF(F12:F23,">0") -> 71.166667 | G25: =AVERAGEIF(G12:G23,">0") -> 332.66667 | H25: =SUM(H11:H23) -> 10379.2 | I25: =SUM(I11:I23) -> 86847.92 | J25: =SUM(J11:J23) -> 192535.7 | K25: =SUM(K11:K23) -> 82992.26 | L25: =SUM(L12:L23) -> 399 | M25: =SUM(M12:M23) -> 3855.66 | N25: =K25/I25 -> 0.95560446
B27: Plan Information | J27: Important Year to Date Data
C28: Claims | E28: Administration | G28: Total | J28: Average Claim Submitted | N28: =J25/L25 -> 482.54561
B29: EE Only | C29: 26.32 | E29: 5.2 | G29: =C29+E29 -> 31.52 | J29: Average Reimbursement | N29: =K25/L25 -> 208.00065
B30: =IF(D10="E+1","EE & One","EE & Spouse") -> EE & One | C30: 51.39 | E30: 5.2 | G30: =C30+E30 -> 56.59 | J30: Average Number of Claims per Employee per Year | N30: =((L25/COUNTIF(G12:G23,">0"))*12)/G25 -> 2.3987976
J31: Average Reimbursement % of Submitted Charges | N31: =K25/J25 -> 0.43104868
B32: EE & Family | C32: 79.73 | E32: 5.2 | G32: =C32+E32 -> 84.93 | J32: Average Claim Paid per Employee per Month | N32: =K25/G25/(COUNTIF(G12:G23,">0")) -> 41.579289
B35: Plan Design | J35: Prior Year Data
B36: 100% of the first $200 | J36: Average Claim Submitted | N36: 357.17
B37: 50% of the next $1,600 | J37: Average Reimbursement | N37: 216.48
B38: Ortho not covered | J38: Average Number of Claims per Employee per Year | N38: 2.03
B39: Annual Maximum Amount $1000 | J39: Average Reimbursement % of Submitted Charges | N39: 0.6061
B40: Assignment of Benefits | J40: Average Claim Paid per Employee per Month | N40: 36.69
J41: Surplus (Deficit) | N41: 45054.81
B43: Important Note: This report reflects claims paid and mailed as of the end of each month. It does not include claims incurred and not yet processed or paid. There are also ongoing adjustments to an employer's benefit account such as corrected claim checks, checks not cashed and claims processed but not yet released due to Simple waiting on the funding of the claims account by the employer. Also, adjustments or corrections to employee enrollments will affect the actual outcomes. Finally, an employer may have deposited more or less to the claims bank account than shown in the budgeted claims column.

Sheet Premium 2026
B1: Gainesville City Schools
B2: Monthly Performance Report - Budgeted vs Actual Claims Paid
G3: Plan Year: | H3: 46023 | I3: through | J3: 46387
B5: Group ID: | D5: S29 | K5: Plan Name: | M5: Premium
B6: Coverage: | D6: Dental | K6: Plan ID: | M6: 29DEN Premium
B8: ENROLLMENT | H8: ADMIN | I8: CLAIMS | M8: PROFIT OR LOSS
M9: Surplus/ | N9: Loss
B10: Mon, Yr | C10: EE | D10: E+1 | F10: EF | G10: Total | H10: Costs | I10: Budgeted | J10: Submitted | K10: Paid | L10: Number | M10: Deficit | N10: Ratio
B12: =Summary!B12 -> 46023 | C12: 101 | D12: =36+30 -> 66 | F12: 92 | G12: =C12+D12+F12 -> 259 | H12: =(C12*$E$29)+(D12*$E$30)+(E12*$E$31)+(F12*$E$32) -> 1346.8 | I12: =(C12*$C$29)+(D12*$C$30)+(E12*$C$31)+(F12*$C$32) -> 19344.25 | M12: =I12-K12 -> 19344.25 | N12: =K12/I12 -> 0
B13: =Summary!B13 -> 46054 | C13: 103 | D13: =31+34 -> 65 | F13: 91 | G13: =C13+D13+F13 -> 259 | H13: =(C13*$E$29)+(D13*$E$30)+(E13*$E$31)+(F13*$E$32) -> 1346.8 | I13: =(C13*$C$29)+(D13*$C$30)+(E13*$C$31)+(F13*$C$32) -> 19231.98 | J13: 32343.13 | K13: 16261.5 | L13: 50 | M13: =I13-K13 -> 2970.48 | N13: =K13/I13 -> 0.84554476
B14: =Summary!B14 -> 46082 | C14: 103 | D14: =33+31 -> 64 | F14: 91 | G14: =C14+D14+F14 -> 258 | H14: =(C14*$E$29)+(D14*$E$30)+(E14*$E$31)+(F14*$E$32) -> 1341.6 | I14: =(C14*$C$29)+(D14*$C$30)+(E14*$C$31)+(F14*$C$32) -> 19158.79 | J14: 115996.79 | K14: 45354.07 | L14: 184 | M14: =I14-K14 -> -26195.28 | N14: =K14/I14 -> 2.3672722
B15: =Summary!B15 -> 46113 | C15: 101 | D15: 63 | F15: 91 | G15: =C15+D15+F15 -> 255 | H15: =(C15*$E$29)+(D15*$E$30)+(E15*$E$31)+(F15*$E$32) -> 1326 | I15: =(C15*$C$29)+(D15*$C$30)+(E15*$C$31)+(F15*$C$32) -> 19008.98 | J15: 76266.17 | K15: 25455.89 | L15: 122 | M15: =I15-K15 -> -6446.91 | N15: =K15/I15 -> 1.3391508
B16: =Summary!B16 -> 46143 | C16: 99 | D16: 32 | F16: 91 | G16: =C16+D16+F16 -> 222 | H16: =(C16*$E$29)+(D16*$E$30)+(E16*$E$31)+(F16*$E$32) -> 1154.4 | I16: =(C16*$C$29)+(D16*$C$30)+(E16*$C$31)+(F16*$C$32) -> 16663.47 | J16: 51783.45 | K16: 25045.15 | L16: 129 | M16: =I16-K16 -> -8381.68 | N16: =K16/I16 -> 1.5029973
B17: =Summary!B17 -> 46174 | C17: 99 | D17: 63 | F17: 90 | G17: =C17+D17+F17 -> 252 | H17: =(C17*$E$29)+(D17*$E$30)+(E17*$E$31)+(F17*$E$32) -> 1310.4 | I17: =(C17*$C$29)+(D17*$C$30)+(E17*$C$31)+(F17*$C$32) -> 18816.66 | J17: 45508.84 | K17: 19206.67 | L17: 83 | M17: =I17-K17 -> -390.01 | N17: =K17/I17 -> 1.0207268
B18: =Summary!B18 -> 46204 | G18: =C18+D18+F18 -> 0 | H18: =(C18*$E$29)+(D18*$E$30)+(E18*$E$31)+(F18*$E$32) -> 0 | I18: =(C18*$C$29)+(D18*$C$30)+(E18*$C$31)+(F18*$C$32) -> 0 | M18: =I18-K18 -> 0
B19: =Summary!B19 -> 46235 | G19: =C19+D19+F19 -> 0 | H19: =(C19*$E$29)+(D19*$E$30)+(E19*$E$31)+(F19*$E$32) -> 0 | I19: =(C19*$C$29)+(D19*$C$30)+(E19*$C$31)+(F19*$C$32) -> 0 | M19: =I19-K19 -> 0
B20: =Summary!B20 -> 46266 | G20: =C20+D20+F20 -> 0 | H20: =(C20*$E$29)+(D20*$E$30)+(E20*$E$31)+(F20*$E$32) -> 0 | I20: =(C20*$C$29)+(D20*$C$30)+(E20*$C$31)+(F20*$C$32) -> 0 | M20: =I20-K20 -> 0 | N20: =K20/(H20+I20) -> #DIV/0!
B21: =Summary!B21 -> 46296 | G21: =C21+D21+F21 -> 0 | H21: =(C21*$E$29)+(D21*$E$30)+(E21*$E$31)+(F21*$E$32) -> 0 | I21: =(C21*$C$29)+(D21*$C$30)+(E21*$C$31)+(F21*$C$32) -> 0 | M21: =I21-K21 -> 0 | N21: =K21/(H21+I21) -> #DIV/0!
B22: =Summary!B22 -> 46327 | G22: =C22+D22+F22 -> 0 | H22: =(C22*$E$29)+(D22*$E$30)+(E22*$E$31)+(F22*$E$32) -> 0 | I22: =(C22*$C$29)+(D22*$C$30)+(E22*$C$31)+(F22*$C$32) -> 0 | M22: =I22-K22 -> 0 | N22: =K22/(H22+I22) -> #DIV/0!
B23: =Summary!B23 -> 46357 | G23: =C23+D23+F23 -> 0 | H23: =(C23*$E$29)+(D23*$E$30)+(E23*$E$31)+(F23*$E$32) -> 0 | I23: =(C23*$C$29)+(D23*$C$30)+(E23*$C$31)+(F23*$C$32) -> 0 | M23: =I23-K23 -> 0 | N23: =K23/(H23+I23) -> #DIV/0!
B25: Averages | C25: =AVERAGEIF(C12:C23,">0") -> 101 | D25: =AVERAGEIF(D12:D23,">0") -> 58.833333 | F25: =AVERAGEIF(F12:F23,">0") -> 91 | G25: =AVERAGEIF(G12:G23,">0") -> 250.83333 | H25: =SUM(H11:H23) -> 7826 | I25: =SUM(I11:I23) -> 112224.13 | J25: =SUM(J11:J23) -> 321898.38 | K25: =SUM(K11:K23) -> 131323.28 | L25: =SUM(L12:L23) -> 568 | M25: =SUM(M12:M23) -> -19099.15 | N25: =K25/I25 -> 1.1701876
B27: Plan Information | J27: Important Year to Date Data
C28: Claims | E28: Administration | G28: Total | J28: Average Claim Submitted | N28: =J25/L25 -> 566.7225
B29: EE Only | C29: 38.31 | E29: 5.2 | G29: =C29+E29 -> 43.51 | J29: Average Reimbursement | N29: =K25/L25 -> 231.20296
B30: =IF(D10="E+1","EE & One","EE & Spouse") -> EE & One | C30: 73.19 | E30: 5.2 | G30: =C30+E30 -> 78.39 | J30: Average Number of Claims per Employee per Year | N30: =((L25/COUNTIF(G12:G23,">0"))*12)/G25 -> 4.5289037
J31: Average Reimbursement % of Submitted Charges | N31: =K25/J25 -> 0.40796502
B32: EE & Family | C32: 115.7 | E32: 5.2 | G32: =C32+E32 -> 120.9 | J32: Average Claim Paid per Employee per Month | N32: =K25/G25/(COUNTIF(G12:G23,">0")) -> 87.257993
B35: Plan Design | J35: Prior Year Data
B36: 100% of the first $250 | J36: Average Claim Submitted | N36: 468.47
B37: 70% of the next $150 - 50% of the remaining benefit | J37: Average Reimbursement | N37: 299.62
B38: Child ortho covered only | J38: Average Number of Claims per Employee per Year | N38: 3.48
B39: Annual Maximum Amount $1,500 | J39: Average Reimbursement % of Submitted Charges | N39: 0.6396
B40: Assignment of Benefits | J40: Average Claim Paid per Employee per Month | N40: 86.89
J41: Surplus (Deficit) | N41: -14003.52
B43: Important Note: This report reflects claims paid and mailed as of the end of each month. It does not include claims incurred and not yet processed or paid. There are also ongoing adjustments to an employer's benefit account such as corrected claim checks, checks not cashed and claims processed but not yet released due to Simple waiting on the funding of the claims account by the employer. Also, adjustments or corrections to employee enrollments will affect the actual outcomes. Finally, an employer may have deposited more or less to the claims bank account than shown in the budgeted claims column.

Sheet Standard 2025
B1: Gainesville City Schools
B2: Monthly Performance Report - Budgeted vs Actual Claims Paid
G3: Plan Year: | H3: 45658 | I3: through | J3: 46022
B5: Group ID: | D5: S29 | K5: Plan Name: | M5: Standard
B6: Coverage: | D6: Dental | K6: Plan ID: | M6: 29DEN Standard
B8: ENROLLMENT | H8: ADMIN | I8: CLAIMS | M8: PROFIT OR LOSS
M9: Surplus/ | N9: Loss
B10: Mon, Yr | C10: EE | D10: E+1 | F10: EF | G10: Total | H10: Costs | I10: Budgeted | J10: Submitted | K10: Paid | L10: Number | M10: Deficit | N10: Ratio
B12: 45682 | C12: 200 | D12: =56+20 -> 76 | F12: 70 | G12: =SUM(C12:F12) -> 346 | H12: =(C12*$E$29)+(D12*$E$30)+(E12*$E$31)+(F12*$E$32) -> 1799.2 | I12: =(C12*$C$29)+(D12*$C$30)+(E12*$C$31)+(F12*$C$32) -> 14750.74 | J12: 27209.33 | K12: 14050.01 | L12: 61 | M12: =H12+I12-K12 -> 2499.93 | N12: =K12/(H12+I12) -> 0.84894628
B13: 45713 | C13: 200 | D13: 76 | F13: 70 | G13: =SUM(C13:F13) -> 346 | H13: =(C13*$E$29)+(D13*$E$30)+(E13*$E$31)+(F13*$E$32) -> 1799.2 | I13: =(C13*$C$29)+(D13*$C$30)+(E13*$C$31)+(F13*$C$32) -> 14750.74 | J13: 23604 | K13: 15084.9 | L13: 61 | M13: =H13+I13-K13 -> 1465.04 | N13: =K13/(H13+I13) -> 0.91147762
B14: 45741 | C14: 200 | D14: =56+20 -> 76 | F14: 70 | G14: =SUM(C14:F14) -> 346 | H14: =(C14*$E$29)+(D14*$E$30)+(E14*$E$31)+(F14*$E$32) -> 1799.2 | I14: =(C14*$C$29)+(D14*$C$30)+(E14*$C$31)+(F14*$C$32) -> 14750.74 | J14: 19605.3 | K14: 13888.92 | L14: 59 | M14: =H14+I14-K14 -> 2661.02 | N14: =K14/(H14+I14) -> 0.83921271
B15: 45772 | C15: 200 | D15: 76 | F15: 70 | G15: =SUM(C15:F15) -> 346 | H15: =(C15*$E$29)+(D15*$E$30)+(E15*$E$31)+(F15*$E$32) -> 1799.2 | I15: =(C15*$C$29)+(D15*$C$30)+(E15*$C$31)+(F15*$C$32) -> 14750.74 | J15: 22921.88 | K15: 16447.36 | L15: 65 | M15: =H15+I15-K15 -> 102.58 | N15: =K15/(H15+I15) -> 0.99380179
B16: 45802 | C16: 199 | D16: =56+20 -> 76 | F16: 70 | G16: =SUM(C16:F16) -> 345 | H16: =(C16*$E$29)+(D16*$E$30)+(E16*$E$31)+(F16*$E$32) -> 1794 | I16: =(C16*$C$29)+(D16*$C$30)+(E16*$C$31)+(F16*$C$32) -> 14724.42 | J16: 14504 | K16: 10424.17 | L16: 43 | M16: =H16+I16-K16 -> 6094.25 | N16: =K16/(H16+I16) -> 0.63106338
B17: 45833 | C17: 199 | D17: =56+20 -> 76 | F17: 70 | G17: =SUM(C17:F17) -> 345 | H17: =(C17*$E$29)+(D17*$E$30)+(E17*$E$31)+(F17*$E$32) -> 1794 | I17: =(C17*$C$29)+(D17*$C$30)+(E17*$C$31)+(F17*$C$32) -> 14724.42 | J17: 13316.85 | K17: 8979.48 | L17: 39 | M17: =H17+I17-K17 -> 7538.94 | N17: =K17/(H17+I17) -> 0.54360405
B18: 45863 | C18: 200 | D18: =57+19 -> 76 | F18: 71 | G18: =SUM(C18:F18) -> 347 | H18: =(C18*$E$29)+(D18*$E$30)+(E18*$E$31)+(F18*$E$32) -> 1804.4 | I18: =(C18*$C$29)+(D18*$C$30)+(E18*$C$31)+(F18*$C$32) -> 14830.47 | J18: 18458 | K18: 12559.97 | L18: 55 | M18: =H18+I18-K18 -> 4074.9 | N18: =K18/(H18+I18) -> 0.75503866
B19: 45894 | C19: 198 | D19: =57+19 -> 76 | F19: 71 | G19: =SUM(C19:F19) -> 345 | H19: =(C19*$E$29)+(D19*$E$30)+(E19*$E$31)+(F19*$E$32) -> 1794 | I19: =(C19*$C$29)+(D19*$C$30)+(E19*$C$31)+(F19*$C$32) -> 14777.83 | J19: 36884.85 | K19: 22352.82 | L19: 93 | M19: =H19+I19-K19 -> -5780.99 | N19: =K19/(H19+I19) -> 1.3488444
B20: 45925 | G20: =SUM(C20:F20) -> 0 | H20: =(C20*$E$29)+(D20*$E$30)+(E20*$E$31)+(F20*$E$32) -> 0 | I20: =(C20*$C$29)+(D20*$C$30)+(E20*$C$31)+(F20*$C$32) -> 0 | M20: =H20+I20-K20 -> 0 | N20: =K20/(H20+I20) -> #DIV/0!
B21: 45955 | G21: =SUM(C21:F21) -> 0 | H21: =(C21*$E$29)+(D21*$E$30)+(E21*$E$31)+(F21*$E$32) -> 0 | I21: =(C21*$C$29)+(D21*$C$30)+(E21*$C$31)+(F21*$C$32) -> 0 | M21: =H21+I21-K21 -> 0 | N21: =K21/(H21+I21) -> #DIV/0!
B22: 45986 | G22: =SUM(C22:F22) -> 0 | H22: =(C22*$E$29)+(D22*$E$30)+(E22*$E$31)+(F22*$E$32) -> 0 | I22: =(C22*$C$29)+(D22*$C$30)+(E22*$C$31)+(F22*$C$32) -> 0 | M22: =H22+I22-K22 -> 0 | N22: =K22/(H22+I22) -> #DIV/0!
B23: 46016 | G23: =SUM(C23:F23) -> 0 | H23: =(C23*$E$29)+(D23*$E$30)+(E23*$E$31)+(F23*$E$32) -> 0 | I23: =(C23*$C$29)+(D23*$C$30)+(E23*$C$31)+(F23*$C$32) -> 0 | M23: =H23+I23-K23 -> 0 | N23: =K23/(H23+I23) -> #DIV/0!
B25: Averages | C25: =AVERAGEIF(C12:C23,">0") -> 199.5 | D25: =AVERAGEIF(D12:D23,">0") -> 76 | F25: =AVERAGEIF(F12:F23,">0") -> 70.25 | G25: =AVERAGEIF(G12:G23,">0") -> 345.75 | H25: =SUM(H11:H23) -> 14383.2 | I25: =SUM(I11:I23) -> 118060.1 | J25: =SUM(J11:J23) -> 176504.21 | K25: =SUM(K11:K23) -> 113787.63 | L25: =SUM(L12:L23) -> 476 | M25: =SUM(M12:M23) -> 18655.67 | N25: =IF((H25+I25)>0,K25/(H25+I25),"") -> 0.85914221
B27: Plan Information | J27: Important Year to Date Data
C28: Claims | E28: Administration | G28: Total | J28: Average Claim Submitted | N28: =J25/L25 -> 370.80716
B29: EE Only | C29: 26.32 | E29: 5.2 | G29: =C29+E29 -> 31.52 | J29: Average Reimbursement | N29: =K25/L25 -> 239.04964
B30: =IF(D10="E+1","EE & One","EE & Spouse") -> EE & One | C30: 51.39 | E30: 5.2 | G30: =C30+E30 -> 56.59 | J30: Average Number of Claims per Employee per Year | N30: =((L25/COUNTIF(G12:G23,">0"))*12)/G25 -> 2.0650759
J31: Average Reimbursement % of Submitted Charges | N31: =K25/J25 -> 0.64467374
B32: EE & Family | C32: 79.73 | E32: 5.2 | G32: =C32+E32 -> 84.93 | J32: Average Claim Paid per Employee per Month | N32: =K25/G25/(COUNTIF(G12:G23,">0")) -> 41.137972
B35: Plan Design | J35: Prior Year Data
B36: 100% of the first $200 | J36: Average Claim Submitted | N36: 357.17
B37: 50% of the next $1,600 | J37: Average Reimbursement | N37: 216.48
B38: Ortho not covered | J38: Average Number of Claims per Employee per Year | N38: 2.03
B39: Annual Maximum Amount $1000 | J39: Average Reimbursement % of Submitted Charges | N39: 0.6061
B40: Assignment of Benefits | J40: Average Claim Paid per Employee per Month | N40: 36.69
J41: Surplus (Deficit) | N41: 45054.81
B43: Important Note: This report reflects claims paid and mailed as of the end of each month. It does not include claims incurred and not yet processed or paid. There are also ongoing adjustments to an employer's benefit account such as corrected claim checks, checks not cashed and claims processed but not yet released due to Simple waiting on the funding of the claims account by the employer. Also, adjustments or corrections to employee enrollments will affect the actual outcomes. Finally, an employer may have deposited more or less to the claims bank account than shown in the budgeted claims column.

Sheet Premium 2025
B1: Gainesville City Schools
B2: Monthly Performance Report - Budgeted vs Actual Claims Paid
G3: Plan Year: | H3: 45658 | I3: through | J3: 46022
B5: Group ID: | D5: S29 | K5: Plan Name: | M5: Premium
B6: Coverage: | D6: Dental | K6: Plan ID: | M6: 29DEN Premium
B8: ENROLLMENT | H8: ADMIN | I8: CLAIMS | M8: PROFIT OR LOSS
M9: Surplus/ | N9: Loss
B10: Mon, Yr | C10: EE | D10: E+1 | F10: EF | G10: Total | H10: Costs | I10: Budgeted | J10: Submitted | K10: Paid | L10: Number | M10: Deficit | N10: Ratio
B12: 45682 | C12: 91 | D12: =27+29 -> 56 | F12: 96 | G12: =C12+D12+F12 -> 243 | H12: =(C12*$E$29)+(D12*$E$30)+(E12*$E$31)+(F12*$E$32) -> 1263.6 | I12: =(C12*$C$29)+(D12*$C$30)+(E12*$C$31)+(F12*$C$32) -> 18692.05 | J12: 27363.14 | K12: 19051.09 | L12: 72 | M12: =H12+I12-K12 -> 904.56 | N12: =K12/(H12+I12) -> 0.95467148
B13: 45713 | C13: 91 | D13: =27+30 -> 57 | F13: 96 | G13: =C13+D13+F13 -> 244 | H13: =(C13*$E$29)+(D13*$E$30)+(E13*$E$31)+(F13*$E$32) -> 1268.8 | I13: =(C13*$C$29)+(D13*$C$30)+(E13*$C$31)+(F13*$C$32) -> 18765.24 | J13: =26693.14+6248.6 -> 32941.74 | K13: =17887.55+6248.6 -> 24136.15 | L13: 63 | M13: =H13+I13-K13 -> -4102.11 | N13: =K13/(H13+I13) -> 1.204757
B14: 45741 | C14: 91 | D14: =27+30 -> 57 | F14: 97 | G14: =C14+D14+F14 -> 245 | H14: =(C14*$E$29)+(D14*$E$30)+(E14*$E$31)+(F14*$E$32) -> 1274 | I14: =(C14*$C$29)+(D14*$C$30)+(E14*$C$31)+(F14*$C$32) -> 18880.94 | J14: =24582.6+3109.6 -> 27692.2 | K14: =16890.39+3109.6 -> 19999.99 | L14: 72 | M14: =H14+I14-K14 -> 154.95 | N14: =K14/(H14+I14) -> 0.99231206
B15: 45772 | C15: 91 | D15: 57 | F15: 96 | G15: =C15+D15+F15 -> 244 | H15: =(C15*$E$29)+(D15*$E$30)+(E15*$E$31)+(F15*$E$32) -> 1268.8 | I15: =(C15*$C$29)+(D15*$C$30)+(E15*$C$31)+(F15*$C$32) -> 18765.24 | J15: =34193.7+3057.6 -> 37251.3 | K15: =22361.61+3057.6 -> 25419.21 | L15: 79 | M15: =H15+I15-K15 -> -5385.17 | N15: =K15/(H15+I15) -> 1.268801
B16: 45802 | C16: 91 | D16: =28+30 -> 58 | F16: 95 | G16: =C16+D16+F16 -> 244 | H16: =(C16*$E$29)+(D16*$E$30)+(E16*$E$31)+(F16*$E$32) -> 1268.8 | I16: =(C16*$C$29)+(D16*$C$30)+(E16*$C$31)+(F16*$C$32) -> 18722.73 | J16: =30249.64+3073.2 -> 33322.84 | K16: =19202.74+3073.2 -> 22275.94 | L16: 66 | M16: =H16+I16-K16 -> -2284.41 | N16: =K16/(H16+I16) -> 1.1142689
B17: 45833 | C17: 90 | D17: =28+31 -> 59 | F17: 93 | G17: =C17+D17+F17 -> 242 | H17: =(C17*$E$29)+(D17*$E$30)+(E17*$E$31)+(F17*$E$32) -> 1258.4 | I17: =(C17*$C$29)+(D17*$C$30)+(E17*$C$31)+(F17*$C$32) -> 18526.21 | J17: =34404.42+3042 -> 37446.42 | K17: =21749.57-3042 -> 18707.57 | L17: 71 | M17: =H17+I17-K17 -> 1077.04 | N17: =K17/(H17+I17) -> 0.94556173
B18: 45863 | C18: 90 | D18: =28+31 -> 59 | F18: 93 | G18: =C18+D18+F18 -> 242 | H18: =(C18*$E$29)+(D18*$E$30)+(E18*$E$31)+(F18*$E$32) -> 1258.4 | I18: =(C18*$C$29)+(D18*$C$30)+(E18*$C$31)+(F18*$C$32) -> 18526.21 | J18: =34526.88+3052.4 -> 37579.28 | K18: =20104.26+3052.4 -> 23156.66 | L18: 67 | M18: =H18+I18-K18 -> -3372.05 | N18: =K18/(H18+I18) -> 1.170438
B19: 45894 | C19: 90 | D19: =29+31 -> 60 | F19: 93 | G19: =C19+D19+F19 -> 243 | H19: =(C19*$E$29)+(D19*$E$30)+(E19*$E$31)+(F19*$E$32) -> 1263.6 | I19: =(C19*$C$29)+(D19*$C$30)+(E19*$C$31)+(F19*$C$32) -> 18599.4 | J19: =33716.63+3047.2 -> 36763.83 | K19: =20419.81+3047.2 -> 23467.01 | L19: 86 | M19: =H19+I19-K19 -> -3604.01 | N19: =K19/(H19+I19) -> 1.1814434
B20: 45925 | G20: =C20+D20+F20 -> 0 | H20: =(C20*$E$29)+(D20*$E$30)+(E20*$E$31)+(F20*$E$32) -> 0 | I20: =(C20*$C$29)+(D20*$C$30)+(E20*$C$31)+(F20*$C$32) -> 0 | M20: =H20+I20-K20 -> 0 | N20: =K20/(H20+I20) -> #DIV/0!
B21: 45955 | G21: =C21+D21+F21 -> 0 | H21: =(C21*$E$29)+(D21*$E$30)+(E21*$E$31)+(F21*$E$32) -> 0 | I21: =(C21*$C$29)+(D21*$C$30)+(E21*$C$31)+(F21*$C$32) -> 0 | M21: =H21+I21-K21 -> 0 | N21: =K21/(H21+I21) -> #DIV/0!
B22: 45986 | G22: =C22+D22+F22 -> 0 | H22: =(C22*$E$29)+(D22*$E$30)+(E22*$E$31)+(F22*$E$32) -> 0 | I22: =(C22*$C$29)+(D22*$C$30)+(E22*$C$31)+(F22*$C$32) -> 0 | M22: =H22+I22-K22 -> 0 | N22: =K22/(H22+I22) -> #DIV/0!
B23: 46016 | G23: =C23+D23+F23 -> 0 | H23: =(C23*$E$29)+(D23*$E$30)+(E23*$E$31)+(F23*$E$32) -> 0 | I23: =(C23*$C$29)+(D23*$C$30)+(E23*$C$31)+(F23*$C$32) -> 0 | M23: =H23+I23-K23 -> 0 | N23: =K23/(H23+I23) -> #DIV/0!
B25: Averages | C25: =AVERAGEIF(C12:C23,">0") -> 90.625 | D25: =AVERAGEIF(D12:D23,">0") -> 57.875 | F25: =AVERAGEIF(F12:F23,">0") -> 94.875 | G25: =AVERAGEIF(G12:G23,">0") -> 243.375 | H25: =SUM(H11:H23) -> 10124.4 | I25: =SUM(I11:I23) -> 149478.02 | J25: =SUM(J11:J23) -> 270360.75 | K25: =SUM(K11:K23) -> 176213.62 | L25: =SUM(L12:L23) -> 576 | M25: =SUM(M12:M23) -> -16611.2 | N25: =IF((H25+I25)>0,K25/(H25+I25),"") -> 1.1040786
B27: Plan Information | J27: Important Year to Date Data
C28: Claims | E28: Administration | G28: Total | J28: Average Claim Submitted | N28: =J25/L25 -> 469.3763
B29: EE Only | C29: 38.31 | E29: 5.2 | G29: =C29+E29 -> 43.51 | J29: Average Reimbursement | N29: =K25/L25 -> 305.92642
B30: =IF(D10="E+1","EE & One","EE & Spouse") -> EE & One | C30: 73.19 | E30: 5.2 | G30: =C30+E30 -> 78.39 | J30: Average Number of Claims per Employee per Year | N30: =((L25/COUNTIF(G12:G23,">0"))*12)/G25 -> 3.550077
J31: Average Reimbursement % of Submitted Charges | N31: =K25/J25 -> 0.6517722
B32: EE & Family | C32: 115.7 | E32: 5.2 | G32: =C32+E32 -> 120.9 | J32: Average Claim Paid per Employee per Month | N32: =K25/G25/(COUNTIF(G12:G23,">0")) -> 90.505198
B35: Plan Design | J35: Prior Year Data
B36: 100% of the first $250 | J36: Average Claim Submitted | N36: 468.47
B37: 70% of the next $100 - 50% of the remaining benefit | J37: Average Reimbursement | N37: 299.62
B38: Child ortho covered only | J38: Average Number of Claims per Employee per Year | N38: 3.48
B39: Annual Maximum Amount $1,500 | J39: Average Reimbursement % of Submitted Charges | N39: 0.6396
B40: Assignment of Benefits | J40: Average Claim Paid per Employee per Month | N40: 86.89
J41: Surplus (Deficit) | N41: -14003.52
B43: Important Note: This report reflects claims paid and mailed as of the end of each month. It does not include claims incurred and not yet processed or paid. There are also ongoing adjustments to an employer's benefit account such as corrected claim checks, checks not cashed and claims processed but not yet released due to Simple waiting on the funding of the claims account by the employer. Also, adjustments or corrections to employee enrollments will affect the actual outcomes. Finally, an employer may have deposited more or less to the claims bank account than shown in the budgeted claims column.
