Workbook

Sheet Standard
B1: Red Lake Public School
B2: Monthly Performance Report - Budgeted vs Actual Claims Paid
G3: Plan Year: | H3: 45901 | I3: through | J3: 46265
B5: Group ID: | D5: S174 | K5: Plan Name: | M5: S174DEN
B6: Coverage: | D6: Dental | K6: Plan ID: | M6: S174
B8: ENROLLMENT | H8: ADMIN | I8: CLAIMS | M8: PROFIT OR LOSS
M9: Surplus/ | N9: Loss
B10: Mon, Yr | C10: EE | F10: EF | G10: Total | H10: Costs | I10: Budgeted | J10: Submitted | K10: Paid | L10: Number | M10: Deficit | N10: Ratio
B12: 45914 | C12: 146 | F12: 124 | G12: =SUM(C12:F12) -> 270 | H12: =(C12*$E$29)+(D12*$E$30)+(E12*$E$31)+(F12*$E$32) -> 1363.5 | I12: =(C12*$C$29)+(D12*$C$30)+(E12*$C$31)+(F12*$C$32) -> 16295 | J12: 22031 | K12: 14370.38 | L12: 60 | M12: =H12+I12-K12 -> 3288.12 | N12: =K12/(H12+I12) -> 0.81379392
B13: 45944 | C13: 146 | F13: 126 | G13: =SUM(C13:F13) -> 272 | H13: =(C13*$E$29)+(D13*$E$30)+(E13*$E$31)+(F13*$E$32) -> 1373.6 | I13: =(C13*$C$29)+(D13*$C$30)+(E13*$C$31)+(F13*$C$32) -> 16478.7 | J13: 33434.05 | K13: 24157.42 | L13: 69 | M13: =H13+I13-K13 -> -6305.12 | N13: =K13/(H13+I13) -> 1.3531825
B14: 45975 | C14: 148 | F14: 130 | G14: =SUM(C14:F14) -> 278 | H14: =(C14*$E$29)+(D14*$E$30)+(E14*$E$31)+(F14*$E$32) -> 1403.9 | I14: =(C14*$C$29)+(D14*$C$30)+(E14*$C$31)+(F14*$C$32) -> 16913.3 | J14: 14580.48 | K14: 11327.86 | L14: 31 | M14: =H14+I14-K14 -> 6989.34 | N14: =K14/(H14+I14) -> 0.61842749
B15: 46005 | C15: 149 | F15: 132 | G15: =SUM(C15:F15) -> 281 | H15: =(C15*$E$29)+(D15*$E$30)+(E15*$E$31)+(F15*$E$32) -> 1419.05 | I15: =(C15*$C$29)+(D15*$C$30)+(E15*$C$31)+(F15*$C$32) -> 17130.6 | J15: 33509.79 | K15: 21727.79 | L15: 73 | M15: =H15+I15-K15 -> -3178.14 | N15: =K15/(H15+I15) -> 1.1713315
B16: 46036 | C16: 146 | F16: 134 | G16: =SUM(C16:F16) -> 280 | H16: =(C16*$E$29)+(D16*$E$30)+(E16*$E$31)+(F16*$E$32) -> 1414 | I16: =(C16*$C$29)+(D16*$C$30)+(E16*$C$31)+(F16*$C$32) -> 17213.5 | J16: 35449.22 | K16: 22414.13 | L16: 68 | M16: =H16+I16-K16 -> -3786.63 | N16: =K16/(H16+I16) -> 1.2032817
B17: 46067 | C17: 146 | F17: 135 | G17: =SUM(C17:F17) -> 281 | H17: =(C17*$E$29)+(D17*$E$30)+(E17*$E$31)+(F17*$E$32) -> 1419.05 | I17: =(C17*$C$29)+(D17*$C$30)+(E17*$C$31)+(F17*$C$32) -> 17305.35 | J17: 19342.97 | K17: 12996.24 | L17: 47 | M17: =H17+I17-K17 -> 5728.16 | N17: =K17/(H17+I17) -> 0.69408045
B18: 46095 | C18: 146 | F18: 135 | G18: =SUM(C18:F18) -> 281 | H18: =(C18*$E$29)+(D18*$E$30)+(E18*$E$31)+(F18*$E$32) -> 1419.05 | I18: =(C18*$C$29)+(D18*$C$30)+(E18*$C$31)+(F18*$C$32) -> 17305.35 | J18: 24734.93 | K18: 16697.19 | L18: 67 | M18: =H18+I18-K18 -> 2027.21 | N18: =K18/(H18+I18) -> 0.89173431
B19: 46126 | C19: 145 | F19: 135 | G19: =SUM(C19:F19) -> 280 | H19: =(C19*$E$29)+(D19*$E$30)+(E19*$E$31)+(F19*$E$32) -> 1414 | I19: =(C19*$C$29)+(D19*$C$30)+(E19*$C$31)+(F19*$C$32) -> 17271.75 | J19: 23673.07 | K19: 15760.39 | L19: 55 | M19: =H19+I19-K19 -> 2925.36 | N19: =K19/(H19+I19) -> 0.84344434
B20: 46156 | C20: 138 | F20: 136 | G20: =SUM(C20:F20) -> 274 | H20: =(C20*$E$29)+(D20*$E$30)+(E20*$E$31)+(F20*$E$32) -> 1383.7 | I20: =(C20*$C$29)+(D20*$C$30)+(E20*$C$31)+(F20*$C$32) -> 17128.4 | J20: 0 | K20: 0 | L20: 0 | M20: =H20+I20-K20 -> 18512.1 | N20: =K20/(H20+I20) -> 0
B21: 46187 | C21: 142 | F21: 135 | G21: =SUM(C21:F21) -> 277 | H21: =(C21*$E$29)+(D21*$E$30)+(E21*$E$31)+(F21*$E$32) -> 1398.85 | I21: =(C21*$C$29)+(D21*$C$30)+(E21*$C$31)+(F21*$C$32) -> 17170.95 | J21: 73220.93 | K21: 29634.29 | L21: 160 | M21: =H21+I21-K21 -> -11064.49 | N21: =K21/(H21+I21) -> 1.5958325
B22: 46217 | G22: =SUM(C22:F22) -> 0 | H22: =(C22*(($E$29)-0.06))+(D22*(($E$30)-0.06))+(E22*(($E$31)-0.06))+(F22*(($E$32)-0.06)) -> 0 | I22: =(C22*$C$29)+(D22*$C$30)+(E22*$C$31)+(F22*$C$32) -> 0 | M22: =H22+I22-K22 -> 0 | N22: =K22/(H22+I22) -> #DIV/0!
B23: 46248 | G23: =SUM(C23:F23) -> 0 | H23: =(C23*(($E$29)-0.06))+(D23*(($E$30)-0.06))+(E23*(($E$31)-0.06))+(F23*(($E$32)-0.06)) -> 0 | I23: =(C23*$C$29)+(D23*$C$30)+(E23*$C$31)+(F23*$C$32) -> 0 | M23: =H23+I23-K23 -> 0 | N23: =K23/(H23+I23) -> #DIV/0!
B25: Averages | C25: =AVERAGEIF(C12:C23,">0") -> 145.2 | F25: =AVERAGEIF(F12:F23,">0") -> 132.2 | G25: =AVERAGEIF(G12:G23,">0") -> 277.4 | H25: =SUM(H11:H23) -> 14008.7 | I25: =SUM(I11:I23) -> 170212.9 | J25: =SUM(J11:J23) -> 279976.44 | K25: =SUM(K11:K23) -> 169085.69 | L25: =SUM(L12:L23) -> 630 | M25: =SUM(M12:M23) -> 15135.91 | N25: =IF((H25+I25)>0,K25/(H25+I25),"") -> 0.91783857
B27: Plan Information | J27: Important Year to Date Data
C28: Claims | E28: Administration | G28: Total | J28: Average Claim Submitted | N28: =J25/L25 -> 444.40705
B29: EE Only | C29: 33.6 | E29: 5.05 | G29: =C29+E29 -> 38.65 | J29: Average Reimbursement | N29: =K25/L25 -> 268.38998
J30: Average Number of Claims per Employee per Year | N30: =((L25/COUNTIF(G12:G23,">0"))*12)/G25 -> 2.7253064
J31: Average Reimbursement % of Submitted Charges | N31: =K25/J25 -> 0.60392828
B32: EE & Family | C32: 91.85 | E32: 5.05 | G32: =C32+E32 -> 96.9 | J32: Average Claim Paid per Employee per Month | N32: =K25/G25/(COUNTIF(G12:G23,">0")) -> 60.953745
B35: Plan Design | J35: Prior Year Data
B36: 100% of the first $100 | J36: Average Claim Submitted | N36: 407.42
B37: $35/$105 Deductible: 80% of the next $1081.25 | J37: Average Reimbursement | N37: 273.96
B38: Ortho covered for Adults and Children at 50% to Lifetime Max $2000 | J38: Average Number of Claims per Employee per Year | N38: 2.73
B39: Annual Maximum Amount $1000 | J39: Average Reimbursement % of Submitted Charges | N39: 0.6724
B40: Assignment of Benefits | J40: Average Claim Paid per Employee per Month | N40: 62.43
J41: Surplus (Deficit) | N41: 6551.81
B43: Important Note: This report reflects claims paid and mailed as of the end of each month. It does not include claims incurred and not yet processed or paid. There are also ongoing adjustments to an employer's benefit account such as corrected claim checks, checks not cashed and claims processed but not yet released due to Simple waiting on the funding of the claims account by the employer. Also, adjustments or corrections to employee enrollments will affect the actual outcomes. Finally, an employer may have deposited more or less to the claims bank account than shown in the budgeted claims column.

Sheet Plan Acct
B1: =Standard!B1 -> Red Lake Public School
B2: Dental Plan Year Accounting
C4: Plan Year: | D4: =Standard!H3 -> 45901 | E4: through | G4: =Standard!J3 -> 46265
B6: Group ID: | C6: =Standard!D5 -> S174 | G6: Coverage: | H6: =Standard!D6 -> Dental
B8: Month | C8: Deposit | D8: Plan Expenses | G8: Account Balance | H8: Notes
D9: Claims | E9: Admin | F9: Total
B10: Prior Plan Year Ending Balance | G10: 36059.79 | H10: Admin Fee Paid as a Claim
B11: =Standard!B12 -> 45914 | C11: =18126.75+1080+1291.35 -> 20498.1 | D11: 14370.38 | E11: 1291.35 | F11: =D11+E11 -> 15661.73 | G11: =C11-F11 -> 4836.37 | H11: Refund $1080.00
B12: =Standard!B13 -> 45944 | C12: 16876.8 | D12: =24157.42-2675.05 -> 21482.37 | E12: 2675.05 | F12: =D12+E12 -> 24157.42 | G12: =C12-F12 -> -7280.62
B13: =Standard!B14 -> 45975 | C13: 17871.35 | D13: 9913.86 | E13: 1414 | F13: =D13+E13 -> 11327.86 | G13: =C13-F13 -> 6543.49
B14: =Standard!B15 -> 46005 | C14: 18394.5 | D14: =21839.79-1403.9 -> 20435.89 | E14: 1403.9 | F14: =D14+E14 -> 21839.79 | G14: =C14-F14 -> -3445.29
B15: =Standard!B16 -> 46036 | C15: 18433.7 | D15: =22414.13-1444.3 -> 20969.83 | E15: 1444.3 | F15: =D15+E15 -> 22414.13 | G15: =C15-F15 -> -3980.43
B16: =Standard!B17 -> 46067 | C16: 19034.15 | D16: =12996.24-1398.85 -> 11597.39 | E16: 1398.85 | F16: =D16+E16 -> 12996.24 | G16: =C16-F16 -> 6037.91
B17: =Standard!B18 -> 46095 | C17: 0 | D17: =16697.19-1414 -> 15283.19 | E17: 1414 | F17: =D17+E17 -> 16697.19 | G17: =C17-F17 -> -16697.19
B18: =Standard!B19 -> 46126 | C18: 0 | D18: =16195.32-1388.75 -> 14806.57 | E18: 1388.75 | F18: =D18+E18 -> 16195.32 | G18: =C18-F18 -> -16195.32
B19: =Standard!B20 -> 46156 | F19: =D19+E19 -> 0 | G19: =C19-F19 -> 0
B20: =Standard!B21 -> 46187 | F20: =D20+E20 -> 0 | G20: =C20-F20 -> 0
B21: =Standard!B22 -> 46217 | F21: =D21+E21 -> 0 | G21: =C21-F21 -> 0
B22: =Standard!B23 -> 46248 | F22: =D22+E22 -> 0 | G22: =C22-F22 -> 0
B24: Total | C24: =SUM(C11:C22) -> 111108.6 | D24: =SUM(D11:D22) -> 128859.48 | E24: =SUM(E11:E22) -> 12430.2 | F24: =SUM(F11:F22) -> 141289.68 | G24: =SUM(G10:G22) -> 5878.71
B27: Note: The above figures do not include claim adjustments.
B28: * Pending claims include claims processed and not yet released for reimbursement due to low account balance.
B29: * Claims may also be pending if funding was received and posted after the final check run for the month.
