Workbook

Sheet Summary
B1: Florida Health Care Plan, Inc.
B2: Monthly Performance Report - Budgeted vs Actual Claims Paid
G3: Plan Year: | H3: 46023 | I3: through | J3: 46387
B5: Group ID: | D5: S451 | K5: Plan Name: | M5: Summary
B6: Coverage: | D6: Dental | K6: Plan ID: | M6: S451DEN
B8: ENROLLMENT | H8: ADMIN | I8: CLAIMS | M8: PROFIT OR LOSS
M9: Surplus/ | N9: Loss
B10: Mon, Yr | C10: EE | D10: ES | E10: EC | F10: EF | G10: Total | H10: Costs | I10: Budgeted | J10: Submitted | K10: Paid | L10: Number | M10: Deficit | N10: Ratio
B12: 46023 | C12: =(STANDARD!C12)+(PREMIUM!C12) -> 381 | D12: =(STANDARD!D12)+(PREMIUM!D12) -> 120 | E12: =(STANDARD!E12)+(PREMIUM!E12) -> 89 | F12: =(STANDARD!F12)+(PREMIUM!F12) -> 130 | G12: =(STANDARD!G12)+(PREMIUM!G12) -> 720 | H12: =(STANDARD!H12)+(PREMIUM!H12) -> 3060 | I12: =(STANDARD!I12)+(PREMIUM!I12) -> 36492.73 | J12: 0 | K12: 0 | L12: 0 | M12: =(STANDARD!M12)+(PREMIUM!M12) -> 10417.84 | N12: =K12/I12 -> 0
B13: 46054 | C13: =(STANDARD!C13)+(PREMIUM!C13) -> 378 | D13: =(STANDARD!D13)+(PREMIUM!D13) -> 119 | E13: =(STANDARD!E13)+(PREMIUM!E13) -> 88 | F13: =(STANDARD!F13)+(PREMIUM!F13) -> 130 | G13: =(STANDARD!G13)+(PREMIUM!G13) -> 715 | H13: =(STANDARD!H13)+(PREMIUM!H13) -> 3038.75 | I13: =(STANDARD!I13)+(PREMIUM!I13) -> 36216.42 | J13: =(STANDARD!J13)+(PREMIUM!J13) -> 22045.65 | ... M13: =(STANDARD!M13)+(PREMIUM!M13) -> 25430.26 | N13: =K13/I13 -> 0.29782513
B14: 46082 | C14: =(STANDARD!C14)+(PREMIUM!C14) -> 380 | D14: =(STANDARD!D14)+(PREMIUM!D14) -> 120 | E14: =(STANDARD!E14)+(PREMIUM!E14) -> 88 | F14: =(STANDARD!F14)+(PREMIUM!F14) -> 130 | G14: =(STANDARD!G14)+(PREMIUM!G14) -> 718 | H14: =(STANDARD!H14)+(PREMIUM!H14) -> 3051.5 | I14: =(STANDARD!I14)+(PREMIUM!I14) -> 36329.45 | J14: =(STANDARD!J14)+(PREMIUM!J14) -> 194064.82 | ... M14: =(STANDARD!M14)+(PREMIUM!M14) -> -61245.69 | N14: =K14/I14 -> 2.6858414
B15: 46113 | C15: =(STANDARD!C15)+(PREMIUM!C15) -> 351 | D15: =(STANDARD!D15)+(PREMIUM!D15) -> 113 | E15: =(STANDARD!E15)+(PREMIUM!E15) -> 77 | F15: =(STANDARD!F15)+(PREMIUM!F15) -> 123 | G15: =(STANDARD!G15)+(PREMIUM!G15) -> 664 | H15: =(STANDARD!H15)+(PREMIUM!H15) -> 2822 | I15: =(STANDARD!I15)+(PREMIUM!I15) -> 33679.72 | J15: =(STANDARD!J15)+(PREMIUM!J15) -> 222682.5 | ... M15: =(STANDARD!M15)+(PREMIUM!M15) -> -43549.66 | N15: =K15/I15 -> 2.2930529
B16: 46143 | C16: =(STANDARD!C16)+(PREMIUM!C16) -> 339 | D16: =(STANDARD!D16)+(PREMIUM!D16) -> 111 | E16: =(STANDARD!E16)+(PREMIUM!E16) -> 74 | F16: =(STANDARD!F16)+(PREMIUM!F16) -> 122 | G16: =(STANDARD!G16)+(PREMIUM!G16) -> 646 | H16: =(STANDARD!H16)+(PREMIUM!H16) -> 2745.5 | I16: =(STANDARD!I16)+(PREMIUM!I16) -> 33001.09 | J16: =(STANDARD!J16)+(PREMIUM!J16) -> 73395.13 | K16: =(STANDARD!K16)+(PREMIUM!K16) -> 38466.33 | L16: 173 | M16: =(STANDARD!M16)+(PREMIUM!M16) -> -5465.24 | N16: =K16/I16 -> 1.1656079
B17: 46174 | C17: =(STANDARD!C17)+(PREMIUM!C17) -> 329 | D17: =(STANDARD!D17)+(PREMIUM!D17) -> 109 | E17: =(STANDARD!E17)+(PREMIUM!E17) -> 73 | F17: =(STANDARD!F17)+(PREMIUM!F17) -> 118 | G17: =(STANDARD!G17)+(PREMIUM!G17) -> 629 | H17: =(STANDARD!H17)+(PREMIUM!H17) -> 2673.25 | I17: =(STANDARD!I17)+(PREMIUM!I17) -> 32118.32 | J17: =(STANDARD!J17)+(PREMIUM!J17) -> 53233 | K17: =(STANDARD!K17)+(PREMIUM!K17) -> 24456.06 | L17: 98 | M17: =(STANDARD!M17)+(PREMIUM!M17) -> 7662.26 | N17: =K17/I17 -> 0.76143646
B18: 46204 | C18: =(STANDARD!C18)+(PREMIUM!C18) -> 0 | D18: =(STANDARD!D18)+(PREMIUM!D18) -> 0 | E18: =(STANDARD!E18)+(PREMIUM!E18) -> 0 | F18: =(STANDARD!F18)+(PREMIUM!F18) -> 0 | G18: =(STANDARD!G18)+(PREMIUM!G18) -> 0 | H18: =(STANDARD!H18)+(PREMIUM!H18) -> 0 | I18: =(STANDARD!I18)+(PREMIUM!I18) -> 0 | J18: =(STANDARD!J18)+(PREMIUM!J18) -> 0 | K18: =(STANDARD!K18)+(PREMIUM!K18) -> 0 | M18: =(STANDARD!M18)+(PREMIUM!M18) -> 0
B19: 46235 | C19: =(STANDARD!C19)+(PREMIUM!C19) -> 0 | D19: =(STANDARD!D19)+(PREMIUM!D19) -> 0 | E19: =(STANDARD!E19)+(PREMIUM!E19) -> 0 | F19: =(STANDARD!F19)+(PREMIUM!F19) -> 0 | G19: =(STANDARD!G19)+(PREMIUM!G19) -> 0 | H19: =(STANDARD!H19)+(PREMIUM!H19) -> 0 | I19: =(STANDARD!I19)+(PREMIUM!I19) -> 0 | J19: =(STANDARD!J19)+(PREMIUM!J19) -> 0 | K19: =(STANDARD!K19)+(PREMIUM!K19) -> 0 | M19: =(STANDARD!M19)+(PREMIUM!M19) -> 0
B20: 46266 | C20: =(STANDARD!C20)+(PREMIUM!C20) -> 0 | D20: =(STANDARD!D20)+(PREMIUM!D20) -> 0 | E20: =(STANDARD!E20)+(PREMIUM!E20) -> 0 | F20: =(STANDARD!F20)+(PREMIUM!F20) -> 0 | G20: =(STANDARD!G20)+(PREMIUM!G20) -> 0 | H20: =(STANDARD!H20)+(PREMIUM!H20) -> 0 | I20: =(STANDARD!I20)+(PREMIUM!I20) -> 0 | J20: =(STANDARD!J20)+(PREMIUM!J20) -> 0 | K20: =(STANDARD!K20)+(PREMIUM!K20) -> 0 | M20: =(STANDARD!M20)+(PREMIUM!M20) -> 0
B21: 46296 | C21: =(STANDARD!C21)+(PREMIUM!C21) -> 0 | D21: =(STANDARD!D21)+(PREMIUM!D21) -> 0 | E21: =(STANDARD!E21)+(PREMIUM!E21) -> 0 | F21: =(STANDARD!F21)+(PREMIUM!F21) -> 0 | G21: =(STANDARD!G21)+(PREMIUM!G21) -> 0 | H21: =(STANDARD!H21)+(PREMIUM!H21) -> 0 | I21: =(STANDARD!I21)+(PREMIUM!I21) -> 0 | J21: =(STANDARD!J21)+(PREMIUM!J21) -> 0 | K21: =(STANDARD!K21)+(PREMIUM!K21) -> 0 | M21: =(STANDARD!M21)+(PREMIUM!M21) -> 0
B22: 46327 | C22: =(STANDARD!C22)+(PREMIUM!C22) -> 0 | D22: =(STANDARD!D22)+(PREMIUM!D22) -> 0 | E22: =(STANDARD!E22)+(PREMIUM!E22) -> 0 | F22: =(STANDARD!F22)+(PREMIUM!F22) -> 0 | G22: =(STANDARD!G22)+(PREMIUM!G22) -> 0 | H22: =(STANDARD!H22)+(PREMIUM!H22) -> 0 | I22: =(STANDARD!I22)+(PREMIUM!I22) -> 0 | J22: =(STANDARD!J22)+(PREMIUM!J22) -> 0 | K22: =(STANDARD!K22)+(PREMIUM!K22) -> 0 | M22: =(STANDARD!M22)+(PREMIUM!M22) -> 0
B23: 46357 | C23: =(STANDARD!C23)+(PREMIUM!C23) -> 0 | D23: =(STANDARD!D23)+(PREMIUM!D23) -> 0 | E23: =(STANDARD!E23)+(PREMIUM!E23) -> 0 | F23: =(STANDARD!F23)+(PREMIUM!F23) -> 0 | G23: =(STANDARD!G23)+(PREMIUM!G23) -> 0 | H23: =(STANDARD!H23)+(PREMIUM!H23) -> 0 | I23: =(STANDARD!I23)+(PREMIUM!I23) -> 0 | J23: =(STANDARD!J23)+(PREMIUM!J23) -> 0 | K23: =(STANDARD!K23)+(PREMIUM!K23) -> 0 | M23: =(STANDARD!M23)+(PREMIUM!M23) -> 0
B25: Averages | C25: =AVERAGEIF(C12:C23,">0") -> 359.66667 | D25: =AVERAGEIF(D12:D23,">0") -> 115.33333 | E25: =AVERAGEIF(E12:E23,">0") -> 81.5 | F25: =AVERAGEIF(F12:F23,">0") -> 125.5 | G25: =AVERAGEIF(G12:G23,">0") -> 682 | H25: =SUM(H11:H23) -> 17391 | I25: =SUM(I11:I23) -> 207837.73 | J25: =SUM(J11:J23) -> 565421.1 | K25: =SUM(K11:K23) -> 248513.07 | L25: =SUM(L12:L23) -> 1102 | M25: =SUM(M12:M23) -> -66750.23 | N25: =K25/I25 -> 1.1957072
J27: Important Year to Date Data
J28: Average Claim Submitted | N28: =J25/L25 -> 513.0863
J29: Average Reimbursement | N29: =K25/L25 -> 225.51095
J30: Average Number of Claims per Employee per Year | N30: =((L25/COUNTIF(G12:G23,">0"))*12)/G25 -> 3.2316716
J31: Average Reimbursement % of Submitted Charges | N31: =K25/J25 -> 0.43951856
J32: Average Claim Paid per Employee per Month | N32: =K25/G25/(COUNTIF(G12:G23,">0")) -> 60.731444
J35: Prior Year Data
J36: Average Claim Submitted | N36: 382.63
J37: Average Reimbursement | N37: 244.05
J38: Average Number of Claims per Employee per Year | N38: 2.66
J39: Average Reimbursement % of Submitted Charges | N39: 0.6378
J40: Average Claim Paid per Employee per Month | N40: 54.04
J41: Surplus (Deficit) | N41: -1707.15
B43: Important Note: This report reflects claims paid and mailed as of the end of each month. It does not include claims incurred and not yet processed or paid. There are also ongoing adjustments to an employer's benefit account such as corrected claim checks, checks not cashed and claims processed but not yet released due to Simple waiting on the funding of the claims account by the employer. Also, adjustments or corrections to employee enrollments will affect the actual outcomes. Finally, an employer may have deposited more or less to the claims bank account than shown in the budgeted claims column.

Sheet STANDARD
B1: =Summary!B1 -> Florida Health Care Plan, Inc.
B2: =Summary!B2 -> Monthly Performance Report - Budgeted vs Actual Claims Paid
G3: Plan Year: | H3: =Summary!H3 -> 46023 | I3: through | J3: =Summary!J3 -> 46387
B5: Group ID: | D5: =Summary!D5 -> S451 | K5: Plan Name: | M5: Low
B6: Coverage: | D6: Dental | K6: Plan ID: | M6: S451DEN STANDARD
B8: ENROLLMENT | H8: ADMIN | I8: CLAIMS | M8: PROFIT OR LOSS
M9: Surplus/ | N9: Loss
B10: Mon, Yr | C10: EE | D10: ES | E10: EC | F10: EF | G10: Total | H10: Costs | I10: Budgeted | J10: Submitted | K10: Paid | L10: Number | M10: Deficit | N10: Ratio
B12: =Summary!B12 -> 46023 | C12: 184 | D12: 50 | E12: 32 | F12: 52 | G12: =SUM(C12:F12) -> 318 | H12: =(C12*$E$29)+(D12*$E$30)+(E12*$E$31)+(F12*$E$32) -> 1351.5 | I12: =(C12*$C$29)+(D12*$C$30)+(E12*$C$31)+(F12*$C$32) -> 10253.84 | J12: 0 | K12: 0 | L12: 0 | M12: =I12-K12 -> 10253.84 | N12: =K12/I12 -> 0
B13: =Summary!B13 -> 46054 | C13: 185 | D13: 50 | E13: 32 | F13: 52 | G13: =SUM(C13:F13) -> 319 | H13: =(C13*$E$29)+(D13*$E$30)+(E13*$E$31)+(F13*$E$32) -> 1355.75 | I13: =(C13*$C$29)+(D13*$C$30)+(E13*$C$31)+(F13*$C$32) -> 10273.69 | J13: 9543.15 | K13: 4928.47 | L13: 28 | M13: =I13-K13 -> 5345.22 | N13: =K13/I13 -> 0.47971761
B14: =Summary!B14 -> 46082 | C14: 187 | D14: 50 | E14: 32 | F14: 52 | G14: =SUM(C14:F14) -> 321 | H14: =(C14*$E$29)+(D14*$E$30)+(E14*$E$31)+(F14*$E$32) -> 1364.25 | I14: =(C14*$C$29)+(D14*$C$30)+(E14*$C$31)+(F14*$C$32) -> 10313.39 | J14: 58136 | K14: 27814.19 | L14: 140 | M14: =I14-K14 -> -17500.8 | N14: =K14/I14 -> 2.6969008
B15: =Summary!B15 -> 46113 | C15: 175 | D15: 47 | E15: 28 | F15: 49 | G15: =SUM(C15:F15) -> 299 | H15: =(C15*$E$29)+(D15*$E$30)+(E15*$E$31)+(F15*$E$32) -> 1270.75 | I15: =(C15*$C$29)+(D15*$C$30)+(E15*$C$31)+(F15*$C$32) -> 9603.75 | J15: 91193.25 | K15: 24756.24 | L15: 154 | M15: =I15-K15 -> -15152.49 | N15: =K15/I15 -> 2.5777681
B16: =Summary!B16 -> 46143 | C16: 163 | D16: 47 | E16: 28 | F16: 48 | G16: =SUM(C16:F16) -> 286 | H16: =(C16*$E$29)+(D16*$E$30)+(E16*$E$31)+(F16*$E$32) -> 1215.5 | I16: =(C16*$C$29)+(D16*$C$30)+(E16*$C$31)+(F16*$C$32) -> 9301.55 | J16: 26008 | K16: 11947.35 | L16: 74 | M16: =I16-K16 -> -2645.8 | N16: =K16/I16 -> 1.2844472
B17: =Summary!B17 -> 46174 | C17: 159 | D17: 46 | E17: 27 | F17: 47 | G17: =SUM(C17:F17) -> 279 | H17: =(C17*$E$29)+(D17*$E$30)+(E17*$E$31)+(F17*$E$32) -> 1185.75 | I17: =(C17*$C$29)+(D17*$C$30)+(E17*$C$31)+(F17*$C$32) -> 9078.31 | J17: 16357 | K17: 7755.91 | L17: 35 | M17: =I17-K17 -> 1322.4 | N17: =K17/I17 -> 0.85433412
B18: =Summary!B18 -> 46204 | G18: =SUM(C18:F18) -> 0 | H18: =(C18*$E$29)+(D18*$E$30)+(E18*$E$31)+(F18*$E$32) -> 0 | I18: =(C18*$C$29)+(D18*$C$30)+(E18*$C$31)+(F18*$C$32) -> 0 | M18: =I18-K18 -> 0
B19: =Summary!B19 -> 46235 | G19: =SUM(C19:F19) -> 0 | H19: =(C19*$E$29)+(D19*$E$30)+(E19*$E$31)+(F19*$E$32) -> 0 | I19: =(C19*$C$29)+(D19*$C$30)+(E19*$C$31)+(F19*$C$32) -> 0 | M19: =I19-K19 -> 0
B20: =Summary!B20 -> 46266 | G20: =SUM(C20:F20) -> 0 | H20: =(C20*$E$29)+(D20*$E$30)+(E20*$E$31)+(F20*$E$32) -> 0 | I20: =(C20*$C$29)+(D20*$C$30)+(E20*$C$31)+(F20*$C$32) -> 0 | M20: =I20-K20 -> 0
B21: =Summary!B21 -> 46296 | G21: =SUM(C21:F21) -> 0 | H21: =(C21*$E$29)+(D21*$E$30)+(E21*$E$31)+(F21*$E$32) -> 0 | I21: =(C21*$C$29)+(D21*$C$30)+(E21*$C$31)+(F21*$C$32) -> 0 | M21: =I21-K21 -> 0
B22: =Summary!B22 -> 46327 | G22: =SUM(C22:F22) -> 0 | H22: =(C22*$E$29)+(D22*$E$30)+(E22*$E$31)+(F22*$E$32) -> 0 | I22: =(C22*$C$29)+(D22*$C$30)+(E22*$C$31)+(F22*$C$32) -> 0 | M22: =I22-K22 -> 0
B23: =Summary!B23 -> 46357 | G23: =SUM(C23:F23) -> 0 | H23: =(C23*$E$29)+(D23*$E$30)+(E23*$E$31)+(F23*$E$32) -> 0 | I23: =(C23*$C$29)+(D23*$C$30)+(E23*$C$31)+(F23*$C$32) -> 0 | M23: =I23-K23 -> 0
B25: Averages | C25: =AVERAGEIF(C12:C23,">0") -> 175.5 | D25: =AVERAGEIF(D12:D23,">0") -> 48.333333 | E25: =AVERAGEIF(E12:E23,">0") -> 29.833333 | F25: =AVERAGEIF(F12:F23,">0") -> 50 | G25: =AVERAGEIF(G12:G23,">0") -> 303.66667 | H25: =SUM(H11:H23) -> 7743.5 | I25: =SUM(I11:I23) -> 58824.53 | J25: =SUM(J11:J23) -> 201237.4 | K25: =SUM(K11:K23) -> 77202.16 | L25: =SUM(L12:L23) -> 431 | M25: =SUM(M12:M23) -> -18377.63 | N25: =K25/I25 -> 1.3124144
B27: Plan Information | J27: Important Year to Date Data
C28: Claims | E28: Administration | G28: Total | J28: Average Claim Submitted | N28: =J25/L25 -> 466.90812
B29: EE Only | C29: 19.85 | E29: 4.25 | G29: =C29+E29 -> 24.1 | J29: Average Reimbursement | N29: =K25/L25 -> 179.12334
B30: =IF(D10="E+1","EE & One","EE & Spouse") -> EE & Spouse | C30: 39.92 | E30: 4.25 | G30: =C30+E30 -> 44.17 | J30: Average Number of Claims per Employee per Year | N30: =((L25/COUNTIF(G12:G23,">0"))*12)/G25 -> 2.8386389
B31: EE & Children | C31: 39.92 | E31: 4.25 | G31: =C31+E31 -> 44.17 | J31: Average Reimbursement % of Submitted Charges | N31: =K25/J25 -> 0.38363724
B32: EE & Family | C32: 64 | E32: 4.25 | G32: =C32+E32 -> 68.25 | J32: Average Claim Paid per Employee per Month | N32: =K25/G25/(COUNTIF(G12:G23,">0")) -> 42.372206
B35: Plan Design | J35: Prior Year Data
B36: 100% of the first $200 | J36: Average Claim Submitted | N36: 331.72
B37: 50% of the remaining maximum | J37: Average Reimbursement | N37: 204.39
B38: Ortho is not covered | J38: Average Number of Claims per Employee per Year | N38: 2.07
B39: Annual Maximum Amount $1,000 | J39: Average Reimbursement % of Submitted Charges | N39: 0.6162
B40: Assignment of Benefits | J40: Average Claim Paid per Employee per Month | N40: 35.23
J41: Surplus (Deficit) | N41: 3507.66
B43: Important Note: This report reflects claims paid and mailed as of the end of each month. It does not include claims incurred and not yet processed or paid. There are also ongoing adjustments to an employer's benefit account such as corrected claim checks, checks not cashed and claims processed but not yet released due to Simple waiting on the funding of the claims account by the employer. Also, adjustments or corrections to employee enrollments will affect the actual outcomes. Finally, an employer may have deposited more or less to the claims bank account than shown in the budgeted claims column.

Sheet PREMIUM
B1: =Summary!B1 -> Florida Health Care Plan, Inc.
B2: =Summary!B2 -> Monthly Performance Report - Budgeted vs Actual Claims Paid
G3: Plan Year: | H3: =Summary!H3 -> 46023 | I3: through | J3: =Summary!J3 -> 46387
B5: Group ID: | D5: =Summary!D5 -> S451 | K5: Plan Name: | M5: High
B6: Coverage: | D6: Dental | K6: Plan ID: | M6: S451DEN PREMIUM
B8: ENROLLMENT | H8: ADMIN | I8: CLAIMS | M8: PROFIT OR LOSS
M9: Surplus/ | N9: Loss
B10: Mon, Yr | C10: EE | D10: E+S | E10: EC | F10: EF | G10: Total | H10: Costs | I10: Budgeted | J10: Submitted | K10: Paid | L10: Number | M10: Deficit | N10: Ratio
B12: =Summary!B12 -> 46023 | C12: 197 | D12: 70 | E12: 57 | F12: 78 | G12: =SUM(C12:F12) -> 402 | H12: =(C12*$E$29)+(D12*$E$30)+(E12*$E$31)+(F12*$E$32) -> 1708.5 | I12: =(C12*C$29)+(D12*C$30)+(E12*$C$31)+(F12*$C$32) -> 26238.89 | J12: =34339.8+3816.25 -> 38156.05 | K12: =22258.64+3816.25 -> 26074.89 | L12: 90 | M12: =I12-K12 -> 164 | N12: =K12/I12 -> 0.99374974
B13: =Summary!B13 -> 46054 | C13: 193 | D13: 69 | E13: 56 | F13: 78 | G13: =SUM(C13:F13) -> 396 | H13: =(C13*$E$29)+(D13*$E$30)+(E13*$E$31)+(F13*$E$32) -> 1683 | I13: =(C13*C$29)+(D13*C$30)+(E13*$C$31)+(F13*$C$32) -> 25942.73 | J13: 12502.5 | K13: 5857.69 | L13: 19 | M13: =I13-K13 -> 20085.04 | N13: =K13/I13 -> 0.22579312
B14: =Summary!B14 -> 46082 | C14: 193 | D14: 70 | E14: 56 | F14: 78 | G14: =SUM(C14:F14) -> 397 | H14: =(C14*$E$29)+(D14*$E$30)+(E14*$E$31)+(F14*$E$32) -> 1687.25 | I14: =(C14*C$29)+(D14*C$30)+(E14*$C$31)+(F14*$C$32) -> 26016.06 | J14: 135928.82 | K14: 69760.95 | L14: 262 | M14: =I14-K14 -> -43744.89 | N14: =K14/I14 -> 2.6814571
B15: =Summary!B15 -> 46113 | C15: 176 | D15: 66 | E15: 49 | F15: 74 | G15: =SUM(C15:F15) -> 365 | H15: =(C15*$E$29)+(D15*$E$30)+(E15*$E$31)+(F15*$E$32) -> 1551.25 | I15: =(C15*C$29)+(D15*C$30)+(E15*$C$31)+(F15*$C$32) -> 24075.97 | J15: 131489.25 | K15: 52473.14 | L15: 228 | M15: =I15-K15 -> -28397.17 | N15: =K15/I15 -> 2.1794819
B16: =Summary!B16 -> 46143 | C16: 176 | D16: 64 | E16: 46 | F16: 74 | G16: =SUM(C16:F16) -> 360 | H16: =(C16*$E$29)+(D16*$E$30)+(E16*$E$31)+(F16*$E$32) -> 1530 | I16: =(C16*C$29)+(D16*C$30)+(E16*$C$31)+(F16*$C$32) -> 23699.54 | J16: 47387.13 | K16: 26518.98 | L16: 99 | M16: =I16-K16 -> -2819.44 | N16: =K16/I16 -> 1.118966
B17: =Summary!B17 -> 46174 | C17: 170 | D17: 63 | E17: 46 | F17: 71 | G17: =SUM(C17:F17) -> 350 | H17: =(C17*$E$29)+(D17*$E$30)+(E17*$E$31)+(F17*$E$32) -> 1487.5 | I17: =(C17*C$29)+(D17*C$30)+(E17*$C$31)+(F17*$C$32) -> 23040.01 | J17: 36876 | K17: 16700.15 | L17: 63 | M17: =I17-K17 -> 6339.86 | N17: =K17/I17 -> 0.72483258
B18: =Summary!B18 -> 46204 | G18: =SUM(C18:F18) -> 0 | H18: =(C18*$E$29)+(D18*$E$30)+(E18*$E$31)+(F18*$E$32) -> 0 | I18: =(C18*C$29)+(D18*C$30)+(E18*$C$31)+(F18*$C$32) -> 0 | M18: =I18-K18 -> 0
B19: =Summary!B19 -> 46235 | G19: =SUM(C19:F19) -> 0 | H19: =(C19*$E$29)+(D19*$E$30)+(E19*$E$31)+(F19*$E$32) -> 0 | I19: =(C19*C$29)+(D19*C$30)+(E19*$C$31)+(F19*$C$32) -> 0 | M19: =I19-K19 -> 0
B20: =Summary!B20 -> 46266 | G20: =SUM(C20:F20) -> 0 | H20: =(C20*$E$29)+(D20*$E$30)+(E20*$E$31)+(F20*$E$32) -> 0 | I20: =(C20*C$29)+(D20*C$30)+(E20*$C$31)+(F20*$C$32) -> 0 | M20: =I20-K20 -> 0
B21: =Summary!B21 -> 46296 | G21: =SUM(C21:F21) -> 0 | H21: =(C21*$E$29)+(D21*$E$30)+(E21*$E$31)+(F21*$E$32) -> 0 | I21: =(C21*C$29)+(D21*C$30)+(E21*$C$31)+(F21*$C$32) -> 0 | M21: =I21-K21 -> 0
B22: =Summary!B22 -> 46327 | G22: =SUM(C22:F22) -> 0 | H22: =(C22*$E$29)+(D22*$E$30)+(E22*$E$31)+(F22*$E$32) -> 0 | I22: =(C22*C$29)+(D22*C$30)+(E22*$C$31)+(F22*$C$32) -> 0 | M22: =I22-K22 -> 0
B23: =Summary!B23 -> 46357 | G23: =SUM(C23:F23) -> 0 | H23: =(C23*$E$29)+(D23*$E$30)+(E23*$E$31)+(F23*$E$32) -> 0 | I23: =(C23*C$29)+(D23*C$30)+(E23*$C$31)+(F23*$C$32) -> 0 | M23: =I23-K23 -> 0
B25: Averages | C25: =AVERAGEIF(C12:C23,">0") -> 184.16667 | D25: =AVERAGEIF(D12:D23,">0") -> 67 | E25: =AVERAGEIF(E12:E23,">0") -> 51.666667 | F25: =AVERAGEIF(F12:F23,">0") -> 75.5 | G25: =AVERAGEIF(G12:G23,">0") -> 378.33333 | H25: =SUM(H11:H23) -> 9647.5 | I25: =SUM(I11:I23) -> 149013.2 | J25: =SUM(J11:J23) -> 402339.75 | K25: =SUM(K11:K23) -> 197385.8 | L25: =SUM(L12:L23) -> 761 | M25: =SUM(M12:M23) -> -48372.6 | N25: =K25/I25 -> 1.3246196
B27: Plan Information | J27: Important Year to Date Data
C28: Claims | E28: Administration | G28: Total | J28: Average Claim Submitted | N28: =J25/L25 -> 528.69875
B29: EE Only | C29: 36.56 | E29: 4.25 | G29: =C29+E29 -> 40.81 | J29: Average Reimbursement | N29: =K25/L25 -> 259.37687
B30: =IF(D10="E+1","EE & One","EE & Spouse") -> EE & Spouse | C30: 73.33 | E30: 4.25 | G30: =C30+E30 -> 77.58 | J30: Average Number of Claims per Employee per Year | N30: =((L25/COUNTIF(G12:G23,">0"))*12)/G25 -> 4.0229075
B31: EE & Children | C31: 76.59 | E31: 4.25 | G31: =C31+E31 -> 80.84 | J31: Average Reimbursement % of Submitted Charges | N31: =K25/J25 -> 0.49059483
B32: EE & Family | C32: 122.28 | E32: 4.25 | G32: =C32+E32 -> 126.53 | J32: Average Claim Paid per Employee per Month | N32: =K25/G25/(COUNTIF(G12:G23,">0")) -> 86.954097
B35: Plan Design | J35: Prior Year Data
B36: 100% of the first $250, then 80% next $100 | J36: Average Claim Submitted | N36: 437.65
B37: 50% of the remaining maximum | J37: Average Reimbursement | N37: 283.31
B38: Ortho covered for Children only to age 19 | J38: Average Number of Claims per Employee per Year | N38: 2.95
B39: Annual Maximum Amount $1,500 | J39: Average Reimbursement % of Submitted Charges | N39: 0.6474
B40: Assignment of Benefits | J40: Average Claim Paid per Employee per Month | N40: 69.59
J41: Surplus (Deficit) | N41: -5214.81
B43: Important Note: This report reflects claims paid and mailed as of the end of each month. It does not include claims incurred and not yet processed or paid. There are also ongoing adjustments to an employer's benefit account such as corrected claim checks, checks not cashed and claims processed but not yet released due to Simple waiting on the funding of the claims account by the employer. Also, adjustments or corrections to employee enrollments will affect the actual outcomes. Finally, an employer may have deposited more or less to the claims bank account than shown in the budgeted claims column.
