Workbook

Sheet Summary
B1: Jefferson County Schools
B2: Monthly Performance Report - Budgeted vs Actual Claims Paid
G3: Plan Year: | H3: 46023 | I3: through | J3: 46387
B5: Group ID: | D5: S420 | K5: Plan Name: | M5: Summary
B6: Coverage: | D6: Dental | K6: Plan ID: | M6: S420DEN/VIS
B8: ENROLLMENT | H8: ADMIN | I8: CLAIMS | M8: PROFIT OR LOSS
M9: Surplus/ | N9: Loss
B10: Mon, Yr | C10: EE | D10: E+1 | F10: EF | G10: Total | H10: Costs | I10: Budgeted | J10: Submitted | K10: Paid | L10: Number | M10: Deficit | N10: Ratio
B12: 46023 | C12: =(Dental!C12)+('Dental-Vision'!C12) -> 441 | D12: =(Dental!DE12)+('Dental-Vision'!D12) -> 131 | F12: =(Dental!F12)+('Dental-Vision'!F12) -> 241 | G12: =(Dental!G12)+('Dental-Vision'!G12) -> 833 | H12: =(Dental!H12)+('Dental-Vision'!H12) -> 3467.45 | I12: =(Dental!I12)+('Dental-Vision'!I12) -> 46623.82 | J12: =(Dental!J12)+('Dental-Vision'!J12) -> 6787.03 | K12: =(Dental!K12)+('Dental-Vision'!K12) -> 5020.01 | L12: =(Dental!L12)+('Dental-Vision'!L12) -> 26 | M12: =(Dental!M12)+('Dental-Vision'!M12) -> 41603.81 | N12: =K12/I12 -> 0.1076705
B13: 46054 | C13: =(Dental!C13)+('Dental-Vision'!C13) -> 388 | D13: =(Dental!DE13)+('Dental-Vision'!D13) -> 110 | F13: =(Dental!F13)+('Dental-Vision'!F13) -> 208 | G13: =(Dental!G13)+('Dental-Vision'!G13) -> 726 | H13: =(Dental!H13)+('Dental-Vision'!H13) -> 3013.35 | I13: =(Dental!I13)+('Dental-Vision'!I13) -> 40403.93 | J13: =(Dental!J13)+('Dental-Vision'!J13) -> 109546.86 | K13: =(Dental!K13)+('Dental-Vision'!K13) -> 56821.01 | L13: =(Dental!L13)+('Dental-Vision'!L13) -> 255 | M13: =(Dental!M13)+('Dental-Vision'!M13) -> -16417.08 | N13: =K13/I13 -> 1.4063238
B14: 46082 | C14: =(Dental!C14)+('Dental-Vision'!C14) -> 388 | D14: =(Dental!DE14)+('Dental-Vision'!D14) -> 109 | F14: =(Dental!F14)+('Dental-Vision'!F14) -> 206 | G14: =(Dental!G14)+('Dental-Vision'!G14) -> 723 | H14: =(Dental!H14)+('Dental-Vision'!H14) -> 2999.95 | I14: =(Dental!I14)+('Dental-Vision'!I14) -> 40149.79 | J14: =(Dental!J14)+('Dental-Vision'!J14) -> 239995.63 | K14: =(Dental!K14)+('Dental-Vision'!K14) -> 86230.21 | L14: =(Dental!L14)+('Dental-Vision'!L14) -> 467 | M14: =(Dental!M14)+('Dental-Vision'!M14) -> -46080.42 | N14: =K14/I14 -> 2.1477126
B15: 46113 | C15: =(Dental!C15)+('Dental-Vision'!C15) -> 387 | D15: =(Dental!DE15)+('Dental-Vision'!D15) -> 112 | F15: =(Dental!F15)+('Dental-Vision'!F15) -> 203 | G15: =(Dental!G15)+('Dental-Vision'!G15) -> 721 | H15: =(Dental!H15)+('Dental-Vision'!H15) -> 2992.1 | I15: =(Dental!I15)+('Dental-Vision'!I15) -> 39949.68 | J15: =(Dental!J15)+('Dental-Vision'!J15) -> 149056.68 | K15: =(Dental!K15)+('Dental-Vision'!K15) -> 58836.93 | L15: =(Dental!L15)+('Dental-Vision'!L15) -> 331 | M15: =(Dental!M15)+('Dental-Vision'!M15) -> -18887.25 | N15: =K15/I15 -> 1.472776
B16: 46143 | C16: =(Dental!C16)+('Dental-Vision'!C16) -> 388 | D16: 131 | F16: =(Dental!F16)+('Dental-Vision'!F16) -> 203 | G16: =(Dental!G16)+('Dental-Vision'!G16) -> 722 | H16: =(Dental!H16)+('Dental-Vision'!H16) -> 2996.35 | I16: =(Dental!I16)+('Dental-Vision'!I16) -> 39981.26 | J16: =(Dental!J16)+('Dental-Vision'!J16) -> 132426.7 | K16: =(Dental!K16)+('Dental-Vision'!K16) -> 43287.75 | L16: =(Dental!L16)+('Dental-Vision'!L16) -> 283 | M16: =(Dental!M16)+('Dental-Vision'!M16) -> -3306.49 | N16: =K16/I16 -> 1.082701
B17: 46174 | C17: =(Dental!C17)+('Dental-Vision'!C17) -> 388 | D17: =(Dental!DE17)+('Dental-Vision'!D17) -> 115 | F17: =(Dental!F17)+('Dental-Vision'!F17) -> 199 | G17: =(Dental!G17)+('Dental-Vision'!G17) -> 721 | H17: =(Dental!H17)+('Dental-Vision'!H17) -> 2992.1 | I17: =(Dental!I17)+('Dental-Vision'!I17) -> 39773.17 | J17: =(Dental!J17)+('Dental-Vision'!J17) -> 136573.84 | K17: =(Dental!K17)+('Dental-Vision'!K17) -> 52160.18 | L17: =(Dental!L17)+('Dental-Vision'!L17) -> 339 | M17: =(Dental!M17)+('Dental-Vision'!M17) -> -12387.01 | N17: =K17/I17 -> 1.3114414
B18: 46204 | C18: =(Dental!C18)+('Dental-Vision'!C18) -> 0 | D18: =(Dental!DE18)+('Dental-Vision'!D18) -> 0 | F18: =(Dental!F18)+('Dental-Vision'!F18) -> 0 | G18: =(Dental!G18)+('Dental-Vision'!G18) -> 0 | H18: =(Dental!H18)+('Dental-Vision'!H18) -> 0 | I18: =(Dental!I18)+('Dental-Vision'!I18) -> 0 | J18: =(Dental!J18)+('Dental-Vision'!J18) -> 0 | K18: =(Dental!K18)+('Dental-Vision'!K18) -> 0 | M18: =(Dental!M18)+('Dental-Vision'!M18) -> 0
B19: 46235 | C19: =(Dental!C19)+('Dental-Vision'!C19) -> 0 | D19: =(Dental!DE19)+('Dental-Vision'!D19) -> 0 | F19: =(Dental!F19)+('Dental-Vision'!F19) -> 0 | G19: =(Dental!G19)+('Dental-Vision'!G19) -> 0 | H19: =(Dental!H19)+('Dental-Vision'!H19) -> 0 | I19: =(Dental!I19)+('Dental-Vision'!I19) -> 0 | J19: =(Dental!J19)+('Dental-Vision'!J19) -> 0 | K19: =(Dental!K19)+('Dental-Vision'!K19) -> 0 | M19: =(Dental!M19)+('Dental-Vision'!M19) -> 0
B20: 46266 | C20: =(Dental!C20)+('Dental-Vision'!C20) -> 0 | D20: =(Dental!DE20)+('Dental-Vision'!D20) -> 0 | F20: =(Dental!F20)+('Dental-Vision'!F20) -> 0 | G20: =(Dental!G20)+('Dental-Vision'!G20) -> 0 | H20: =(Dental!H20)+('Dental-Vision'!H20) -> 0 | I20: =(Dental!I20)+('Dental-Vision'!I20) -> 0 | J20: =(Dental!J20)+('Dental-Vision'!J20) -> 0 | K20: =(Dental!K20)+('Dental-Vision'!K20) -> 0 | M20: =(Dental!M20)+('Dental-Vision'!M20) -> 0
B21: 46296 | C21: =(Dental!C21)+('Dental-Vision'!C21) -> 0 | D21: =(Dental!DE21)+('Dental-Vision'!D21) -> 0 | F21: =(Dental!F21)+('Dental-Vision'!F21) -> 0 | G21: =(Dental!G21)+('Dental-Vision'!G21) -> 0 | H21: =(Dental!H21)+('Dental-Vision'!H21) -> 0 | I21: =(Dental!I21)+('Dental-Vision'!I21) -> 0 | J21: =(Dental!J21)+('Dental-Vision'!J21) -> 0 | K21: =(Dental!K21)+('Dental-Vision'!K21) -> 0 | M21: =(Dental!M21)+('Dental-Vision'!M21) -> 0
B22: 46327 | C22: =(Dental!C22)+('Dental-Vision'!C22) -> 0 | D22: =(Dental!DE22)+('Dental-Vision'!D22) -> 0 | F22: =(Dental!F22)+('Dental-Vision'!F22) -> 0 | G22: =(Dental!G22)+('Dental-Vision'!G22) -> 0 | H22: =(Dental!H22)+('Dental-Vision'!H22) -> 0 | I22: =(Dental!I22)+('Dental-Vision'!I22) -> 0 | J22: =(Dental!J22)+('Dental-Vision'!J22) -> 0 | K22: =(Dental!K22)+('Dental-Vision'!K22) -> 0 | M22: =(Dental!M22)+('Dental-Vision'!M22) -> 0
B23: 46357 | C23: =(Dental!C23)+('Dental-Vision'!C23) -> 0 | D23: =(Dental!DE23)+('Dental-Vision'!D23) -> 0 | F23: =(Dental!F23)+('Dental-Vision'!F23) -> 0 | G23: =(Dental!G23)+('Dental-Vision'!G23) -> 0 | H23: =(Dental!H23)+('Dental-Vision'!H23) -> 0 | I23: =(Dental!I23)+('Dental-Vision'!I23) -> 0 | J23: =(Dental!J23)+('Dental-Vision'!J23) -> 0 | K23: =(Dental!K23)+('Dental-Vision'!K23) -> 0 | M23: =(Dental!M23)+('Dental-Vision'!M23) -> 0
B25: Averages | C25: =AVERAGEIF(C12:C23,">0") -> 396.66667 | D25: =AVERAGEIF(D12:D23,">0") -> 118 | F25: =AVERAGEIF(F12:F23,">0") -> 210 | G25: =AVERAGEIF(G12:G23,">0") -> 741 | H25: =SUM(H11:H23) -> 18461.3 | I25: =SUM(I11:I23) -> 246881.65 | J25: =SUM(J11:J23) -> 774386.74 | K25: =SUM(K11:K23) -> 302356.09 | L25: =SUM(L12:L23) -> 1701 | M25: =SUM(M12:M23) -> -55474.44 | N25: =K25/I25 -> 1.2247005
J27: Important Year to Date Data
J28: Average Claim Submitted | N28: =J25/L25 -> 455.25382
J29: Average Reimbursement | N29: =K25/L25 -> 177.75196
J30: Average Number of Claims per Employee per Year | N30: =((L25/COUNTIF(G12:G23,">0"))*12)/G25 -> 4.5910931
J31: Average Reimbursement % of Submitted Charges | N31: =K25/J25 -> 0.39044585
J32: Average Claim Paid per Employee per Month | N32: =K25/G25/(COUNTIF(G12:G23,">0")) -> 68.006318
J35: Prior Year Data
J36: Average Claim Submitted | N36: 357.33
J37: Average Reimbursement | N37: 203.87
J38: Average Number of Claims per Employee per Year | N38: 3.33
J39: Average Reimbursement % of Submitted Charges | N39: 0.5706
J40: Average Claim Paid per Employee per Month | N40: 56.57
J41: Surplus (Deficit) | N41: 31069.07
B43: Important Note: This report reflects claims paid and mailed as of the end of each month. It does not include claims incurred and not yet processed or paid. There are also ongoing adjustments to an employer's benefit account such as corrected claim checks, checks not cashed and claims processed but not yet released due to Simple waiting on the funding of the claims account by the employer. Also, adjustments or corrections to employee enrollments will affect the actual outcomes. Finally, an employer may have deposited more or less to the claims bank account than shown in the budgeted claims column.

Sheet Dental
B1: =Summary!B1 -> Jefferson County Schools
B2: =Summary!B2 -> Monthly Performance Report - Budgeted vs Actual Claims Paid
G3: Plan Year: | H3: =Summary!H3 -> 46023 | I3: through | J3: =Summary!J3 -> 46387
B5: Group ID: | D5: S420 | K5: Plan Name: | M5: Standard Dental
B6: Coverage: | D6: Dental | K6: Plan ID: | M6: S420DEN
B8: ENROLLMENT | H8: ADMIN | I8: CLAIMS | M8: PROFIT OR LOSS
M9: Surplus/ | N9: Loss
B10: Mon, Yr | C10: EE | D10: E+1 | F10: EF | G10: Total | H10: Costs | I10: Budgeted | J10: Submitted | K10: Paid | L10: Number | M10: Deficit | N10: Ratio
B12: =Summary!B12 -> 46023 | C12: 55 | D12: =13+7 -> 20 | F12: 37 | G12: =SUM(C12:F12) -> 112 | H12: =(C12*$E$29)+(D12*$E$30)+(E12*$E$31)+(F12*$E$32) -> 403.2 | I12: =(C12*$C$29)+(D12*$C$30)+(E12*$C$31)+(F12*$C$32) -> 6210.51 | J12: 6787.03 | K12: 5020.01 | L12: 26 | M12: =I12-K12 -> 1190.5 | N12: =K12/I12 -> 0.80830882
B13: =Summary!B13 -> 46054 | C13: 55 | D13: =13+7 -> 20 | F13: 36 | G13: =SUM(C13:F13) -> 111 | H13: =(C13*$E$29)+(D13*$E$30)+(E13*$E$31)+(F13*$E$32) -> 399.6 | I13: =(C13*$C$29)+(D13*$C$30)+(E13*$C$31)+(F13*$C$32) -> 6119.53 | J13: 13065.96 | K13: 6037.33 | L13: 32 | M13: =I13-K13 -> 82.2 | N13: =K13/I13 -> 0.9865676
B14: =Summary!B14 -> 46082 | C14: 57 | D14: =7+13 -> 20 | F14: 35 | G14: =SUM(C14:F14) -> 112 | H14: =(C14*$E$29)+(D14*$E$30)+(E14*$E$31)+(F14*$E$32) -> 403.2 | I14: =(C14*$C$29)+(D14*$C$30)+(E14*$C$31)+(F14*$C$32) -> 6089.09 | J14: 37068.17 | K14: 14763.98 | L14: 62 | M14: =I14-K14 -> -8674.89 | N14: =K14/I14 -> 2.4246612
B15: =Summary!B15 -> 46113 | C15: 57 | D15: 19 | F15: 35 | G15: =SUM(C15:F15) -> 111 | H15: =(C15*$E$29)+(D15*$E$30)+(E15*$E$31)+(F15*$E$32) -> 399.6 | I15: =(C15*$C$29)+(D15*$C$30)+(E15*$C$31)+(F15*$C$32) -> 6030.12 | J15: 16030.83 | K15: 5936.96 | L15: 34 | M15: =I15-K15 -> 93.16 | N15: =K15/I15 -> 0.98455089
B16: =Summary!B16 -> 46143 | C16: 57 | D16: 19 | F16: 35 | G16: =SUM(C16:F16) -> 111 | H16: =(C16*$E$29)+(D16*$E$30)+(E16*$E$31)+(F16*$E$32) -> 399.6 | I16: =(C16*$C$29)+(D16*$C$30)+(E16*$C$31)+(F16*$C$32) -> 6030.12 | J16: 23550.08 | K16: 9838.07 | L16: 47 | M16: =I16-K16 -> -3807.95 | N16: =K16/I16 -> 1.6314883
B17: =Summary!B17 -> 46174 | C17: 57 | D17: 19 | F17: 35 | G17: =SUM(C17:F17) -> 111 | H17: =(C17*$E$29)+(D17*$E$30)+(E17*$E$31)+(F17*$E$32) -> 399.6 | I17: =(C17*$C$29)+(D17*$C$30)+(E17*$C$31)+(F17*$C$32) -> 6030.12 | J17: 25124.23 | K17: 8230.08 | L17: 53 | M17: =I17-K17 -> -2199.96 | N17: =K17/I17 -> 1.3648286
B18: =Summary!B18 -> 46204 | G18: =SUM(C18:F18) -> 0 | H18: =(C18*$E$29)+(D18*$E$30)+(E18*$E$31)+(F18*$E$32) -> 0 | I18: =(C18*$C$29)+(D18*$C$30)+(E18*$C$31)+(F18*$C$32) -> 0 | M18: =I18-K18 -> 0
B19: =Summary!B19 -> 46235 | G19: =SUM(C19:F19) -> 0 | H19: =(C19*$E$29)+(D19*$E$30)+(E19*$E$31)+(F19*$E$32) -> 0 | I19: =(C19*$C$29)+(D19*$C$30)+(E19*$C$31)+(F19*$C$32) -> 0 | M19: =I19-K19 -> 0
B20: =Summary!B20 -> 46266 | G20: =SUM(C20:F20) -> 0 | H20: =(C20*$E$29)+(D20*$E$30)+(E20*$E$31)+(F20*$E$32) -> 0 | I20: =(C20*$C$29)+(D20*$C$30)+(E20*$C$31)+(F20*$C$32) -> 0 | M20: =I20-K20 -> 0
B21: =Summary!B21 -> 46296 | G21: =SUM(C21:F21) -> 0 | H21: =(C21*$E$29)+(D21*$E$30)+(E21*$E$31)+(F21*$E$32) -> 0 | I21: =(C21*$C$29)+(D21*$C$30)+(E21*$C$31)+(F21*$C$32) -> 0 | M21: =I21-K21 -> 0
B22: =Summary!B22 -> 46327 | G22: =SUM(C22:F22) -> 0 | H22: =(C22*$E$29)+(D22*$E$30)+(E22*$E$31)+(F22*$E$32) -> 0 | I22: =(C22*$C$29)+(D22*$C$30)+(E22*$C$31)+(F22*$C$32) -> 0 | M22: =I22-K22 -> 0
B23: =Summary!B23 -> 46357 | G23: =SUM(C23:F23) -> 0 | H23: =(C23*$E$29)+(D23*$E$30)+(E23*$E$31)+(F23*$E$32) -> 0 | I23: =(C23*$C$29)+(D23*$C$30)+(E23*$C$31)+(F23*$C$32) -> 0 | M23: =I23-K23 -> 0
B25: Averages | C25: =AVERAGEIF(C12:C23,">0") -> 56.333333 | D25: =AVERAGEIF(D12:D23,">0") -> 19.5 | F25: =AVERAGEIF(F12:F23,">0") -> 35.5 | G25: =AVERAGEIF(G12:G23,">0") -> 111.33333 | H25: =SUM(H11:H23) -> 2404.8 | I25: =SUM(I11:I23) -> 36509.49 | J25: =SUM(J11:J23) -> 121626.3 | K25: =SUM(K11:K23) -> 49826.43 | L25: =SUM(L12:L23) -> 254 | M25: =SUM(M12:M23) -> -13316.94 | N25: =K25/I25 -> 1.3647528
B27: Plan Information | J27: Important Year to Date Data
C28: Claims | E28: Administration | G28: Total | J28: Average Claim Submitted | N28: =J25/L25 -> 478.8437
B29: EE Only | C29: 30.27 | E29: 3.6 | G29: =C29+E29 -> 33.87 | J29: Average Reimbursement | N29: =K25/L25 -> 196.16705
B30: =IF(D10="E+1","EE & One","EE & Spouse") -> EE & One | C30: 58.97 | E30: 3.6 | G30: =C30+E30 -> 62.57 | J30: Average Number of Claims per Employee per Year | N30: =((L25/COUNTIF(G12:G23,">0"))*12)/G25 -> 4.5628743
J31: Average Reimbursement % of Submitted Charges | N31: =K25/J25 -> 0.40966822
B32: EE & Family | C32: 90.98 | E32: 3.6 | G32: =C32+E32 -> 94.58 | J32: Average Claim Paid per Employee per Month | N32: =K25/G25/(COUNTIF(G12:G23,">0")) -> 74.590464
B35: Plan Design | J35: Prior Year Data
B36: 100% of the first $175 | J36: Average Claim Submitted | N36: 336.59
B37: 50% of the next $2050 | J37: Average Reimbursement | N37: 194.67
B38: Ortho covered for Adults & Children | J38: Average Number of Claims per Employee per Year | N38: 2.84
B39: Plan Year Maximum: $1,200 | J39: Average Reimbursement % of Submitted Charges | N39: 0.5783
B40: Assignment of Benefits | J40: Average Claim Paid per Employee per Month | N40: 46.13
J41: Surplus (Deficit) | N41: 17031.06
B43: Important Note: This report reflects claims paid and mailed as of the end of each month. It does not include claims incurred and not yet processed or paid. There are also ongoing adjustments to an employer's benefit account such as corrected claim checks, checks not cashed and claims processed but not yet released due to Simple waiting on the funding of the claims account by the employer. Also, adjustments or corrections to employee enrollments will affect the actual outcomes. Finally, an employer may have deposited more or less to the claims bank account than shown in the budgeted claims column.

Sheet Dental-Vision
B1: =Summary!B1 -> Jefferson County Schools
B2: =Summary!B2 -> Monthly Performance Report - Budgeted vs Actual Claims Paid
G3: Plan Year: | H3: =Summary!H3 -> 46023 | I3: through | J3: =Summary!J3 -> 46387
B5: Group ID: | D5: S420 | K5: Plan Name: | M5: Dental/Vision
B6: Coverage: | D6: Dental | K6: Plan ID: | M6: S420DEN-VIS
B8: ENROLLMENT | H8: ADMIN | I8: CLAIMS | M8: PROFIT OR LOSS
M9: Surplus/ | N9: Loss
B10: Mon, Yr | C10: EE | D10: E+1 | F10: EF | G10: Total | H10: Costs | I10: Budgeted | J10: Submitted | K10: Paid | L10: Number | M10: Deficit | N10: Ratio
B12: =Summary!B12 -> 46023 | C12: =55+331 -> 386 | D12: =13+7+76+35 -> 131 | F12: =36+168 -> 204 | G12: =SUM(C12:F12) -> 721 | H12: =(C12*$E$29)+(D12*$E$30)+(E12*$E$31)+(F12*$E$32) -> 3064.25 | I12: =(C12*$C$29)+(D12*$C$30)+(E12*$C$31)+(F12*$C$32) -> 40413.31 | J12: 0 | K12: 0 | L12: 0 | M12: =I12-K12 -> 40413.31 | N12: =K12/I12 -> 0
B13: =Summary!B13 -> 46054 | C13: 333 | D13: =76+34 -> 110 | F13: 172 | G13: =SUM(C13:F13) -> 615 | H13: =(C13*$E$29)+(D13*$E$30)+(E13*$E$31)+(F13*$E$32) -> 2613.75 | I13: =(C13*$C$29)+(D13*$C$30)+(E13*$C$31)+(F13*$C$32) -> 34284.4 | J13: 96480.9 | K13: 50783.68 | L13: 223 | M13: =I13-K13 -> -16499.28 | N13: =K13/I13 -> 1.4812474
B14: =Summary!B14 -> 46082 | C14: 331 | D14: =33+76 -> 109 | F14: 171 | G14: =SUM(C14:F14) -> 611 | H14: =(C14*$E$29)+(D14*$E$30)+(E14*$E$31)+(F14*$E$32) -> 2596.75 | I14: =(C14*$C$29)+(D14*$C$30)+(E14*$C$31)+(F14*$C$32) -> 34060.7 | J14: 202927.46 | K14: 71466.23 | L14: 405 | M14: =I14-K14 -> -37405.53 | N14: =K14/I14 -> 2.098202
B15: =Summary!B15 -> 46113 | C15: 330 | D15: 112 | F15: 168 | G15: =SUM(C15:F15) -> 610 | H15: =(C15*$E$29)+(D15*$E$30)+(E15*$E$31)+(F15*$E$32) -> 2592.5 | I15: =(C15*$C$29)+(D15*$C$30)+(E15*$C$31)+(F15*$C$32) -> 33919.56 | J15: 133025.85 | K15: 52899.97 | L15: 297 | M15: =I15-K15 -> -18980.41 | N15: =K15/I15 -> 1.5595712
B16: =Summary!B16 -> 46143 | C16: 331 | D16: 112 | F16: 168 | G16: =SUM(C16:F16) -> 611 | H16: =(C16*$E$29)+(D16*$E$30)+(E16*$E$31)+(F16*$E$32) -> 2596.75 | I16: =(C16*$C$29)+(D16*$C$30)+(E16*$C$31)+(F16*$C$32) -> 33951.14 | J16: 108876.62 | K16: 33449.68 | L16: 236 | M16: =I16-K16 -> 501.46 | N16: =K16/I16 -> 0.98522995
B17: =Summary!B17 -> 46174 | C17: 331 | D17: 115 | F17: 164 | G17: =SUM(C17:F17) -> 610 | H17: =(C17*$E$29)+(D17*$E$30)+(E17*$E$31)+(F17*$E$32) -> 2592.5 | I17: =(C17*$C$29)+(D17*$C$30)+(E17*$C$31)+(F17*$C$32) -> 33743.05 | J17: 111449.61 | K17: 43930.1 | L17: 286 | M17: =I17-K17 -> -10187.05 | N17: =K17/I17 -> 1.3019007
B18: =Summary!B18 -> 46204 | G18: =SUM(C18:F18) -> 0 | H18: =(C18*$E$29)+(D18*$E$30)+(E18*$E$31)+(F18*$E$32) -> 0 | I18: =(C18*$C$29)+(D18*$C$30)+(E18*$C$31)+(F18*$C$32) -> 0 | M18: =I18-K18 -> 0
B19: =Summary!B19 -> 46235 | G19: =SUM(C19:F19) -> 0 | H19: =(C19*$E$29)+(D19*$E$30)+(E19*$E$31)+(F19*$E$32) -> 0 | I19: =(C19*$C$29)+(D19*$C$30)+(E19*$C$31)+(F19*$C$32) -> 0 | M19: =I19-K19 -> 0
B20: =Summary!B20 -> 46266 | G20: =SUM(C20:F20) -> 0 | H20: =(C20*$E$29)+(D20*$E$30)+(E20*$E$31)+(F20*$E$32) -> 0 | I20: =(C20*$C$29)+(D20*$C$30)+(E20*$C$31)+(F20*$C$32) -> 0 | M20: =I20-K20 -> 0
B21: =Summary!B21 -> 46296 | G21: =SUM(C21:F21) -> 0 | H21: =(C21*$E$29)+(D21*$E$30)+(E21*$E$31)+(F21*$E$32) -> 0 | I21: =(C21*$C$29)+(D21*$C$30)+(E21*$C$31)+(F21*$C$32) -> 0 | M21: =I21-K21 -> 0
B22: =Summary!B22 -> 46327 | G22: =SUM(C22:F22) -> 0 | H22: =(C22*$E$29)+(D22*$E$30)+(E22*$E$31)+(F22*$E$32) -> 0 | I22: =(C22*$C$29)+(D22*$C$30)+(E22*$C$31)+(F22*$C$32) -> 0 | M22: =I22-K22 -> 0
B23: =Summary!B23 -> 46357 | G23: =SUM(C23:F23) -> 0 | H23: =(C23*$E$29)+(D23*$E$30)+(E23*$E$31)+(F23*$E$32) -> 0 | I23: =(C23*$C$29)+(D23*$C$30)+(E23*$C$31)+(F23*$C$32) -> 0 | M23: =I23-K23 -> 0
B25: Averages | C25: =AVERAGEIF(C12:C23,">0") -> 340.33333 | D25: =AVERAGEIF(D12:D23,">0") -> 114.83333 | F25: =AVERAGEIF(F12:F23,">0") -> 174.5 | G25: =AVERAGEIF(G12:G23,">0") -> 629.66667 | H25: =SUM(H11:H23) -> 16056.5 | I25: =SUM(I11:I23) -> 210372.16 | J25: =SUM(J11:J23) -> 652760.44 | K25: =SUM(K11:K23) -> 252529.66 | L25: =SUM(L12:L23) -> 1447 | M25: =SUM(M12:M23) -> -42157.5 | N25: =K25/I25 -> 1.2003949
B27: Plan Information | J27: Important Year to Date Data
C28: Claims | E28: Administration | G28: Total | J28: Average Claim Submitted | N28: =J25/L25 -> 451.11295
B29: EE Only | C29: 31.58 | E29: 4.25 | G29: =C29+E29 -> 35.83 | J29: Average Reimbursement | N29: =K25/L25 -> 174.51946
B30: =IF(D10="E+1","EE & One","EE & Spouse") -> EE & One | C30: 62.01 | E30: 4.25 | G30: =C30+E30 -> 66.26 | J30: Average Number of Claims per Employee per Year | N30: =((L25/COUNTIF(G12:G23,">0"))*12)/G25 -> 4.5960826
J31: Average Reimbursement % of Submitted Charges | N31: =K25/J25 -> 0.38686422
B32: EE & Family | C32: 98.53 | E32: 4.25 | G32: =C32+E32 -> 102.78 | J32: Average Claim Paid per Employee per Month | N32: =K25/G25/(COUNTIF(G12:G23,">0")) -> 66.842155
B35: Plan Design | J35: Prior Year Data
B36: 100% of the first $175 | J36: Average Claim Submitted | N36: 360.59
B37: 50% of the next $2650 | J37: Average Reimbursement | N37: 205.32
B38: Ortho covered for Adults & Children | J38: Average Number of Claims per Employee per Year | N38: 3.42
B39: Plan Year Maximum: $1,500/includes $300 vision | J39: Average Reimbursement % of Submitted Charges | N39: 0.5694
B40: Assignment of Benefits | J40: Average Claim Paid per Employee per Month | N40: 58.55
J41: Surplus (Deficit) | N41: 14038.01
B43: Important Note: This report reflects claims paid and mailed as of the end of each month. It does not include claims incurred and not yet processed or paid. There are also ongoing adjustments to an employer's benefit account such as corrected claim checks, checks not cashed and claims processed but not yet released due to Simple waiting on the funding of the claims account by the employer. Also, adjustments or corrections to employee enrollments will affect the actual outcomes. Finally, an employer may have deposited more or less to the claims bank account than shown in the budgeted claims column.
